Workbook
Name a: '[1]Admin Nombres'!$F$28:$F$44
Name A_Transversal_Incidencia: 'Lista desplegable'!$I$2:$I$59
Name AA_Incidencia: 'Lista desplegable'!$AK$2:$AK$59
Name actividades4: [2]Hoja9!$F$3:$F$26
Name administrativo: [3]Actividad!$C$146:$D$150
Name B_Construyendo_Sostenibilidad: 'Lista desplegable'!$G$2:$G$59
Name BA_Adaptación_climática: 'Lista desplegable'!$AG$2:$AG$59
Name BB_Cuidado_del_medio_ambiente: 'Lista desplegable'!$AH$2:$AH$59
Name BC_Reducción_del_Riesgo_de_Desastres__RRD: 'Lista desplegable'!$AI$2:$AI$59
Name C_Niños_en_crisis: 'Lista desplegable'!$H$2:$H$59
Name CA_Niños_desplazados_en_crisis_protegidas: 'Lista desplegable'!$AJ$2:$AJ$59
Name CA_Proteccion_y_respuesta_lideradas_localmente: 'Lista desplegable'!$AJ$36:$AJ$60
Name Creciendo: [4]Actividad!$C$2:$D$17
Name Creciendo_Contigo: [3]Actividad!$C$2:$D$17
Name cuena: '[4]Admin Nombres'!$K$19:$K$48
Name cuentas: '[3]Admin Nombres'!$K$19:$K$48
Name D_Desarrollo_de_la_primera_infancia: 'Lista desplegable'!$C$2:$C$59
Name DA_Cuidado_receptivo: 'Lista desplegable'!$T$2:$T$59
Name DB_Atención_y_educación_de_la_primera_infancia_en_centros__ECCE: 'Lista desplegable'!$U$2:$U$59
Name Etapav1: [3]Actividad!$C$2:$C$17
Name etapav2: [3]Actividad!$C$18:$C$49
Name etapav23: [3]Actividad!$C$88:$C$116
Name etapav2a: [4]Actividad!$C$18:$C$49
Name etapav3: [3]Actividad!$C$50:$C$87
Name gestion_admin: [3]Actividad!$C$146:$C$150
Name gestion_p: [3]Actividad!$C$139:$C$145
Name GFC: 'Lista desplegable'!$AX$2:$AX$6
Name GFC_Fondo_Global_para_la_Niñez: 'Lista desplegable'!$AW$2
Name H_Salud: 'Lista desplegable'!$B$2:$B$59
Name HA_WASH: 'Lista desplegable'!$O$2:$O$59
Name HB_Nutrición: 'Lista desplegable'!$P$2:$P$59
Name HC_Salud_maternoinfantil: 'Lista desplegable'!$Q$2:$Q$59
Name HD_Salud_reproductiva: 'Lista desplegable'!$R$2:$R$59
Name HE__Enfermedad_infecciosa: 'Lista desplegable'!$S$2:$S$59
Name L_Medios_de_vida: 'Lista desplegable'!$F$2:$F$59
Name LA_Empoderamiento_económico_para_las_familias: 'Lista desplegable'!$AD$2:$AD$59
Name LB_Empoderamiento_económico_para_los_jóvenes: 'Lista desplegable'!$AE$2:$AE$59
Name LC_Seguridad_alimentaria: 'Lista desplegable'!$AF$2:$AF$59
Name M_Transversal_Salud_mental: 'Lista desplegable'!$J$2:$J$59
Name MA_Salud_mental_y_apoyo_psicosocial: 'Lista desplegable'!$AL$2:$AL$59
Name mecanismo: [3]Actividad!$C$117:$C$138
Name ML_Monitoreo: 'Lista desplegable'!$N$2:$N$59
Name ML_Monitoreo_y_soporte_técnico_del_programa: 'Lista desplegable'!$AP$2:$AP$59
Name modulo_ev1: '[3]Admin Nombres'!$A$28:$A$40
Name modulo_ev2: '[3]Admin Nombres'!$C$28:$C$40
Name modulo_ev3: '[3]Admin Nombres'!$E$28:$E$43
Name mqmc: [3]Actividad!$C$88:$D$116
Name mqmc_ev23: '[3]Admin Nombres'!$F$28:$F$44
Name nsyp: [3]Actividad!$C$18:$D$49
Name nsyp2: [4]Actividad!$C$18:$D$49
Name pacto: [3]Actividad!$C$50:$D$87
Name participantes: '[3]Admin Nombres'!$K$1:$K$15
Name patrocinio: [3]Actividad!$C$139:$D$145
Name PMA: 'Lista desplegable'!$AZ$2:$AZ$5
Name PMA_Programa_Mundial_de_Alimentos: 'Lista desplegable'!$AY$2
Name proteccion: [3]Actividad!$C$117:$D$138
Name R_Protección: 'Lista desplegable'!$E$2:$E$59
Name RA_Seguridad_en_línea: 'Lista desplegable'!$Z$2:$Z$59
Name RB_Trabajo_infantil: 'Lista desplegable'!$AA$2:$AA$59
Name RC_Prevención_y_respuesta_a_prácticas_nocivas: 'Lista desplegable'!$AB$2:$AB$59

Sheet Propuesta 2
A1: ACCION HONDURAS
A2: MATRIZ DE EVALUACION DE DESEMPEÑO DEL COLABORADOR
A4: Nombre y cargo del Colaborador: | H4: Jose Adalid Funes - Técnico de Desarrollo Comunitario | J4: Beyquer Odan Maldonado - Coordinador de Área | O4: Evaluador: | Q4: José Orlando Osorto Pérez - Director General
O5: VoBo RRHH | Q5: Jennifer Sabrina Romero Martínez - Especialista en RRHH
A7: Area | E7: Periodo evaluado | F7: Marco de Resultados | K7: Responsabilidades del colaborador | L7: Cantidad a Lograr | P7: Tiempo Definido (dias) | T7: Estandares de calidad (Escala de 10) | AA7: Nota Final
A8: Principal | B8: Transversal | C8: Responsable | D8: Forma de Ejecucion | F8: S | G8: SS | H8: ML | I8: Ext | L8: Programada | M8: Entregada | N8: Diferencia | O8: % | P8: Programado | Q8: Entregada | R8: Diferencia | S8: % | T8: Puntualidad | U8: Resolucion de Problemas | V8: Coordinaciión local | W8: Nivel de satisfacción de Grupos meta | X8: Nivel de preparación | Y8: Total Estandares (Nota max. 50) | Z8: %
A10: PROG | B10: MEAL | C10: Lider-Prog-EV1 | D10: Personal | F10: H_Salud | G10: HB_Nutrición | H10: HB041-01_Suplementos_nutricionales_para_niños_con_desnutrición_aguda_grave_o_desnutrición_aguda_moderada | I10: 1 | J10: DX | K10: Diseñar herramientas y protocolo para Dx.situacional de EV-1 | N10: =+L10-M10 -> 0 | O10: =IFERROR(IF(7<>0, M10*100/L10, IF(L10=M10, M10*100/L10, 0)), 0) -> 0 | R10: =+P10-Q10 -> 0 | S10: =IFERROR(IF(R10<>0, P10*100/Q10, IF(P10=Q10, P10*100/Q10, 0)), 0) -> 0 | Y10: =SUM(T10:X10) -> 0 | Z10: =+Y10*100/50 -> 0 | AA10: =+(S10+O10+Z10)/3 -> 0
A11: PROG | B11: MEAL | C11: Lider-Prog-EV2 | D11: Personal | F11: H_Salud | G11: HB_Nutrición | H11: HB041-01_Suplementos_nutricionales_para_niños_con_desnutrición_aguda_grave_o_desnutrición_aguda_moderada | I11: 1 | J11: DX | K11: Diseñar herramientas y protocolo para Dx.situacional de EV-2 | N11: =+L11-M11 -> 0 | O11: =IFERROR(IF(7<>0, M11*100/L11, IF(L11=M11, M11*100/L11, 0)), 0) -> 0 | R11: =+P11-Q11 -> 0 | S11: =IFERROR(IF(R11<>0, P11*100/Q11, IF(P11=Q11, P11*100/Q11, 0)), 0) -> 0 | Y11: =SUM(T11:X11) -> 0 | Z11: =+Y11*100/50 -> 0 | AA11: =+(S11+O11+Z11)/3 -> 0
A12: PROG | B12: MEAL | C12: Lider-Prog-EV3 | D12: Personal | F12: H_Salud | G12: HB_Nutrición | H12: HB041-01_Suplementos_nutricionales_para_niños_con_desnutrición_aguda_grave_o_desnutrición_aguda_moderada | I12: 1 | J12: DX | K12: Diseñar herramientas y protocolo para Dx.situacional de EV-3 | N12: =+L12-M12 -> 0 | O12: =IFERROR(IF(7<>0, M12*100/L12, IF(L12=M12, M12*100/L12, 0)), 0) -> 0 | R12: =+P12-Q12 -> 0 | S12: =IFERROR(IF(R12<>0, P12*100/Q12, IF(P12=Q12, P12*100/Q12, 0)), 0) -> 0 | Y12: =SUM(T12:X12) -> 0 | Z12: =+Y12*100/50 -> 0 | AA12: =+(S12+O12+Z12)/3 -> 0
A13: PROG | B13: MEAL | C13: Red de Madres guia | D13: Apoyo voluntario | F13: H_Salud | G13: HB_Nutrición | H13: HB041-01_Suplementos_nutricionales_para_niños_con_desnutrición_aguda_grave_o_desnutrición_aguda_moderada | I13: 1 | J13: DX | K13: Levantar Diagnostico situacional de primera infancia | L13: 500 | M13: 410 | N13: =+L13-M13 -> 90 | O13: =IFERROR(IF(7<>0, M13*100/L13, IF(L13=M13, M13*100/L13, 0)), 0) -> 82 | P13: 15 | Q13: 22 | R13: =+P13-Q13 -> -7 | S13: =IFERROR(IF(R13<>0, P13*100/Q13, IF(P13=Q13, P13*100/Q13, 0)), 0) -> 68.181818 | T13: 9 | U13: 7 | V13: 10 | W13: 8 | X13: 10 | Y13: =SUM(T13:X13) -> 44 | Z13: =+Y13*100/50 -> 88 | AA13: =+(S13+O13+Z13)/3 -> 79.393939
A14: PROG | B14: MEAL | C14: Red de Docentes | D14: Apoyo voluntario | J14: DX | K14: Levantar diagnóstico situacional de NN en el Centro Educativo. | N14: =+L14-M14 -> 0 | O14: =IFERROR(IF(7<>0, M14*100/L14, IF(L14=M14, M14*100/L14, 0)), 0) -> 0 | R14: =+P14-Q14 -> 0 | S14: =IFERROR(IF(R14<>0, P14*100/Q14, IF(P14=Q14, P14*100/Q14, 0)), 0) -> 0 | Y14: =SUM(T14:X14) -> 0 | Z14: =+Y14*100/50 -> 0 | AA14: =+(S14+O14+Z14)/3 -> 0
A15: PROG | B15: MEAL | C15: Red de Apoyo Juvenil | D15: Apoyo voluntario | J15: DX | K15: Levantar diagnóstico aptitudinal y de intereses de AJ en las comunidades | N15: =+L15-M15 -> 0 | O15: =IFERROR(IF(7<>0, M15*100/L15, IF(L15=M15, M15*100/L15, 0)), 0) -> 0 | R15: =+P15-Q15 -> 0 | S15: =IFERROR(IF(R15<>0, P15*100/Q15, IF(P15=Q15, P15*100/Q15, 0)), 0) -> 0 | Y15: =SUM(T15:X15) -> 0 | Z15: =+Y15*100/50 -> 0 | AA15: =+(S15+O15+Z15)/3 -> 0
A16: PROG | B16: MEAL | C16: Lider-Prog-EV1 | D16: Personal | J16: DX | K16: Procesar y limpiar datos de Dx para elaborar informe sobre situacion EV-1 | N16: =+L16-M16 -> 0 | O16: =IFERROR(IF(7<>0, M16*100/L16, IF(L16=M16, M16*100/L16, 0)), 0) -> 0 | R16: =+P16-Q16 -> 0 | S16: =IFERROR(IF(R16<>0, P16*100/Q16, IF(P16=Q16, P16*100/Q16, 0)), 0) -> 0 | Y16: =SUM(T16:X16) -> 0 | Z16: =+Y16*100/50 -> 0 | AA16: =+(S16+O16+Z16)/3 -> 0
A17: PROG | B17: MEAL | C17: Lider-Prog-EV2 | D17: Personal | J17: DX | K17: Procesar y limpiar datos de Dx para elaborar informe sobre situacion EV-2 | N17: =+L17-M17 -> 0 | O17: =IFERROR(IF(7<>0, M17*100/L17, IF(L17=M17, M17*100/L17, 0)), 0) -> 0 | R17: =+P17-Q17 -> 0 | S17: =IFERROR(IF(R17<>0, P17*100/Q17, IF(P17=Q17, P17*100/Q17, 0)), 0) -> 0 | Y17: =SUM(T17:X17) -> 0 | Z17: =+Y17*100/50 -> 0 | AA17: =+(S17+O17+Z17)/3 -> 0
A18: PROG | B18: MEAL | C18: Lider-Prog-EV3 | D18: Personal | J18: DX | K18: Procesar y limpiar datos de Dx para elaborar informe sobre situacion EV-3 | N18: =+L18-M18 -> 0 | O18: =IFERROR(IF(7<>0, M18*100/L18, IF(L18=M18, M18*100/L18, 0)), 0) -> 0 | R18: =+P18-Q18 -> 0 | S18: =IFERROR(IF(R18<>0, P18*100/Q18, IF(P18=Q18, P18*100/Q18, 0)), 0) -> 0 | Y18: =SUM(T18:X18) -> 0 | Z18: =+Y18*100/50 -> 0 | AA18: =+(S18+O18+Z18)/3 -> 0
A19: PROG | B19: MEAL | C19: Lider-Prog-EV1 | D19: Sinergia Equipo | J19: DX | K19: Organizar evento de socialización de resultados de Dx.situacional EV-1 (apoyos) | N19: =+L19-M19 -> 0 | O19: =IFERROR(IF(7<>0, M19*100/L19, IF(L19=M19, M19*100/L19, 0)), 0) -> 0 | R19: =+P19-Q19 -> 0 | S19: =IFERROR(IF(R19<>0, P19*100/Q19, IF(P19=Q19, P19*100/Q19, 0)), 0) -> 0 | Y19: =SUM(T19:X19) -> 0 | Z19: =+Y19*100/50 -> 0 | AA19: =+(S19+O19+Z19)/3 -> 0
A20: PROG | B20: MEAL | C20: Lider-Prog-EV2 | D20: Sinergia Equipo | J20: DX | K20: Organizar evento de socialización de resultados de Dx.situacional EV-2 (apoyos) | N20: =+L20-M20 -> 0 | O20: =IFERROR(IF(7<>0, M20*100/L20, IF(L20=M20, M20*100/L20, 0)), 0) -> 0 | R20: =+P20-Q20 -> 0 | S20: =IFERROR(IF(R20<>0, P20*100/Q20, IF(P20=Q20, P20*100/Q20, 0)), 0) -> 0 | Y20: =SUM(T20:X20) -> 0 | Z20: =+Y20*100/50 -> 0 | AA20: =+(S20+O20+Z20)/3 -> 0
A21: PROG | B21: MEAL | C21: Lider-Prog-EV3 | D21: Sinergia Equipo | J21: DX | K21: Organizar evento de socialización de resultados de Dx.situacional EV-3 (apoyos) | N21: =+L21-M21 -> 0 | O21: =IFERROR(IF(7<>0, M21*100/L21, IF(L21=M21, M21*100/L21, 0)), 0) -> 0 | R21: =+P21-Q21 -> 0 | S21: =IFERROR(IF(R21<>0, P21*100/Q21, IF(P21=Q21, P21*100/Q21, 0)), 0) -> 0 | Y21: =SUM(T21:X21) -> 0 | Z21: =+Y21*100/50 -> 0 | AA21: =+(S21+O21+Z21)/3 -> 0
A22: PROG | B22: MEAL | C22: Lider-Prog-EV1 | D22: Sinergia Equipo | J22: DX | K22: Desarrollar evento de socialización de resultados de Dx.situacional EV-1 | N22: =+L22-M22 -> 0 | O22: =IFERROR(IF(7<>0, M22*100/L22, IF(L22=M22, M22*100/L22, 0)), 0) -> 0 | R22: =+P22-Q22 -> 0 | S22: =IFERROR(IF(R22<>0, P22*100/Q22, IF(P22=Q22, P22*100/Q22, 0)), 0) -> 0 | Y22: =SUM(T22:X22) -> 0 | Z22: =+Y22*100/50 -> 0 | AA22: =+(S22+O22+Z22)/3 -> 0
A23: PROG | B23: MEAL | C23: Lider-Prog-EV2 | D23: Sinergia Equipo | J23: DX | K23: Desarrollar evento de socialización de resultados de Dx.situacional EV-2 | N23: =+L23-M23 -> 0 | O23: =IFERROR(IF(7<>0, M23*100/L23, IF(L23=M23, M23*100/L23, 0)), 0) -> 0 | R23: =+P23-Q23 -> 0 | S23: =IFERROR(IF(R23<>0, P23*100/Q23, IF(P23=Q23, P23*100/Q23, 0)), 0) -> 0 | Y23: =SUM(T23:X23) -> 0 | Z23: =+Y23*100/50 -> 0 | AA23: =+(S23+O23+Z23)/3 -> 0
A24: PROG | B24: MEAL | C24: Lider-Prog-EV3 | D24: Sinergia Equipo | J24: DX | K24: Desarrollar evento de socialización de resultados de Dx.situacional EV-3 | N24: =+L24-M24 -> 0 | O24: =IFERROR(IF(7<>0, M24*100/L24, IF(L24=M24, M24*100/L24, 0)), 0) -> 0 | R24: =+P24-Q24 -> 0 | S24: =IFERROR(IF(R24<>0, P24*100/Q24, IF(P24=Q24, P24*100/Q24, 0)), 0) -> 0 | Y24: =SUM(T24:X24) -> 0 | Z24: =+Y24*100/50 -> 0 | AA24: =+(S24+O24+Z24)/3 -> 0
A25: PROG | C25: Lider-Prog-EV1 | D25: Personal | J25: CI | K25: Buscar y representar a AH en alianzas de coordinacion con socios Proy-EV-1 | N25: =+L25-M25 -> 0 | O25: =IFERROR(IF(7<>0, M25*100/L25, IF(L25=M25, M25*100/L25, 0)), 0) -> 0 | R25: =+P25-Q25 -> 0 | S25: =IFERROR(IF(R25<>0, P25*100/Q25, IF(P25=Q25, P25*100/Q25, 0)), 0) -> 0 | Y25: =SUM(T25:X25) -> 0 | Z25: =+Y25*100/50 -> 0 | AA25: =+(S25+O25+Z25)/3 -> 0
A26: PROG | C26: Lider-Prog-EV2 | D26: Personal | J26: CI | K26: Buscar y representar a AH en alianzas de coordinacion con socios Proy-EV-2 | N26: =+L26-M26 -> 0 | O26: =IFERROR(IF(7<>0, M26*100/L26, IF(L26=M26, M26*100/L26, 0)), 0) -> 0 | R26: =+P26-Q26 -> 0 | S26: =IFERROR(IF(R26<>0, P26*100/Q26, IF(P26=Q26, P26*100/Q26, 0)), 0) -> 0 | Y26: =SUM(T26:X26) -> 0 | Z26: =+Y26*100/50 -> 0 | AA26: =+(S26+O26+Z26)/3 -> 0
A27: PROG | C27: Lider-Prog-EV3 | D27: Personal | J27: CI | K27: Buscar y representar a AH en alianzas de coordinacion con socios Proy-EV-3 | N27: =+L27-M27 -> 0 | O27: =IFERROR(IF(7<>0, M27*100/L27, IF(L27=M27, M27*100/L27, 0)), 0) -> 0 | R27: =+P27-Q27 -> 0 | S27: =IFERROR(IF(R27<>0, P27*100/Q27, IF(P27=Q27, P27*100/Q27, 0)), 0) -> 0 | Y27: =SUM(T27:X27) -> 0 | Z27: =+Y27*100/50 -> 0 | AA27: =+(S27+O27+Z27)/3 -> 0
A28: PROT | C28: Lider-Prot-Incid | D28: Personal | J28: CI | K28: Buscar y representar a AH en alianzas de coordinacion con socios Proteccion e Inc | N28: =+L28-M28 -> 0 | O28: =IFERROR(IF(7<>0, M28*100/L28, IF(L28=M28, M28*100/L28, 0)), 0) -> 0 | R28: =+P28-Q28 -> 0 | S28: =IFERROR(IF(R28<>0, P28*100/Q28, IF(P28=Q28, P28*100/Q28, 0)), 0) -> 0 | Y28: =SUM(T28:X28) -> 0 | Z28: =+Y28*100/50 -> 0 | AA28: =+(S28+O28+Z28)/3 -> 0
A29: PROG | C29: Lider-Prog-EV1 | D29: Personal | K29: Definir contenidos y lineamientos para organizar y coordinar red de madres guia | N29: =+L29-M29 -> 0 | O29: =IFERROR(IF(7<>0, M29*100/L29, IF(L29=M29, M29*100/L29, 0)), 0) -> 0 | R29: =+P29-Q29 -> 0 | S29: =IFERROR(IF(R29<>0, P29*100/Q29, IF(P29=Q29, P29*100/Q29, 0)), 0) -> 0 | Y29: =SUM(T29:X29) -> 0 | Z29: =+Y29*100/50 -> 0 | AA29: =+(S29+O29+Z29)/3 -> 0
A30: PROT | C30: Lider-Prot-Incid | D30: Personal | K30: Definir contenidos y lineamientos para organizar y coordinar MPBC | N30: =+L30-M30 -> 0 | O30: =IFERROR(IF(7<>0, M30*100/L30, IF(L30=M30, M30*100/L30, 0)), 0) -> 0 | R30: =+P30-Q30 -> 0 | S30: =IFERROR(IF(R30<>0, P30*100/Q30, IF(P30=Q30, P30*100/Q30, 0)), 0) -> 0 | Y30: =SUM(T30:X30) -> 0 | Z30: =+Y30*100/50 -> 0 | AA30: =+(S30+O30+Z30)/3 -> 0
A31: PROG | C31: Lider-Prog-EV2 | D31: Personal | K31: Definir contenidos y lineamientos para organizar y coordinar red Educativa | N31: =+L31-M31 -> 0 | O31: =IFERROR(IF(7<>0, M31*100/L31, IF(L31=M31, M31*100/L31, 0)), 0) -> 0 | R31: =+P31-Q31 -> 0 | S31: =IFERROR(IF(R31<>0, P31*100/Q31, IF(P31=Q31, P31*100/Q31, 0)), 0) -> 0 | Y31: =SUM(T31:X31) -> 0 | Z31: =+Y31*100/50 -> 0 | AA31: =+(S31+O31+Z31)/3 -> 0
A32: PROG | C32: Lider-Prog-EV3 | D32: Personal | K32: Definir contenidos y lineamientos para organizar y coordinar red de apoyo juvenil | N32: =+L32-M32 -> 0 | O32: =IFERROR(IF(7<>0, M32*100/L32, IF(L32=M32, M32*100/L32, 0)), 0) -> 0 | R32: =+P32-Q32 -> 0 | S32: =IFERROR(IF(R32<>0, P32*100/Q32, IF(P32=Q32, P32*100/Q32, 0)), 0) -> 0 | Y32: =SUM(T32:X32) -> 0 | Z32: =+Y32*100/50 -> 0 | AA32: =+(S32+O32+Z32)/3 -> 0
A33: PROG | C33: Lider-Prog-EV1 | D33: Por Producto | K33: Elaboracion de material didactico para Proy- EV-1, según Branding (contrato) | N33: =+L33-M33 -> 0 | O33: =IFERROR(IF(7<>0, M33*100/L33, IF(L33=M33, M33*100/L33, 0)), 0) -> 0 | R33: =+P33-Q33 -> 0 | S33: =IFERROR(IF(R33<>0, P33*100/Q33, IF(P33=Q33, P33*100/Q33, 0)), 0) -> 0 | Y33: =SUM(T33:X33) -> 0 | Z33: =+Y33*100/50 -> 0 | AA33: =+(S33+O33+Z33)/3 -> 0
A34: PROG | C34: Lider-Prog-EV2 | D34: Por Producto | K34: Elaboracion de material didactico para Proy- EV-2, según Branding (contrato) | N34: =+L34-M34 -> 0 | O34: =IFERROR(IF(7<>0, M34*100/L34, IF(L34=M34, M34*100/L34, 0)), 0) -> 0 | R34: =+P34-Q34 -> 0 | S34: =IFERROR(IF(R34<>0, P34*100/Q34, IF(P34=Q34, P34*100/Q34, 0)), 0) -> 0 | Y34: =SUM(T34:X34) -> 0 | Z34: =+Y34*100/50 -> 0 | AA34: =+(S34+O34+Z34)/3 -> 0
A35: PROG | C35: Lider-Prog-EV3 | D35: Por Producto | K35: Elaboracion de material didactico para Proy- EV-3, según Branding (contrato) | N35: =+L35-M35 -> 0 | O35: =IFERROR(IF(7<>0, M35*100/L35, IF(L35=M35, M35*100/L35, 0)), 0) -> 0 | R35: =+P35-Q35 -> 0 | S35: =IFERROR(IF(R35<>0, P35*100/Q35, IF(P35=Q35, P35*100/Q35, 0)), 0) -> 0 | Y35: =SUM(T35:X35) -> 0 | Z35: =+Y35*100/50 -> 0 | AA35: =+(S35+O35+Z35)/3 -> 0
A36: PROT | C36: Lider-Prot-Incid | D36: Por Producto | K36: Elaboracion de material didactico para Proteccion e Incidencia (contrato) | N36: =+L36-M36 -> 0 | O36: =IFERROR(IF(7<>0, M36*100/L36, IF(L36=M36, M36*100/L36, 0)), 0) -> 0 | R36: =+P36-Q36 -> 0 | S36: =IFERROR(IF(R36<>0, P36*100/Q36, IF(P36=Q36, P36*100/Q36, 0)), 0) -> 0 | Y36: =SUM(T36:X36) -> 0 | Z36: =+Y36*100/50 -> 0 | AA36: =+(S36+O36+Z36)/3 -> 0
A37: PROG | C37: Lider-Prog-EV1 | D37: Personal | K37: Organizar, coordinar y dar asistencia tecnica a Red de madres guía. | L37: 4 | M37: 4 | N37: =+L37-M37 -> 0 | O37: =IFERROR(IF(7<>0, M37*100/L37, IF(L37=M37, M37*100/L37, 0)), 0) -> 100 | P37: 5 | Q37: 5 | R37: =+P37-Q37 -> 0 | S37: =IFERROR(IF(R37<>0, P37*100/Q37, IF(P37=Q37, P37*100/Q37, 0)), 0) -> 100 | T37: 8 | U37: 6 | V37: 6 | W37: 8 | X37: 8 | Y37: =SUM(T37:X37) -> 36 | Z37: =+Y37*100/50 -> 72 | AA37: =+(S37+O37+Z37)/3 -> 90.666667
A38: PROT | B38: PROG | C38: Lider-Prot-Incid | D38: Personal | K38: Organizar, capacitar y monitorear plan de acción de los MPBC | N38: =+L38-M38 -> 0 | O38: =IFERROR(IF(7<>0, M38*100/L38, IF(L38=M38, M38*100/L38, 0)), 0) -> 0 | R38: =+P38-Q38 -> 0 | S38: =IFERROR(IF(R38<>0, P38*100/Q38, IF(P38=Q38, P38*100/Q38, 0)), 0) -> 0 | Y38: =SUM(T38:X38) -> 0 | Z38: =+Y38*100/50 -> 0 | AA38: =+(S38+O38+Z38)/3 -> 0
A39: PROG | C39: Lider-Prog-EV2 | D39: Personal | K39: Organizar, coordinar y dar asistencia tecnica a Red Educativa-APF y docente. | N39: =+L39-M39 -> 0 | O39: =IFERROR(IF(7<>0, M39*100/L39, IF(L39=M39, M39*100/L39, 0)), 0) -> 0 | R39: =+P39-Q39 -> 0 | S39: =IFERROR(IF(R39<>0, P39*100/Q39, IF(P39=Q39, P39*100/Q39, 0)), 0) -> 0 | Y39: =SUM(T39:X39) -> 0 | Z39: =+Y39*100/50 -> 0 | AA39: =+(S39+O39+Z39)/3 -> 0
A40: PROG | C40: Lider-Prog-EV3 | D40: Personal | K40: Organizar, coordinar y dar asistencia tecnica a Red de Apoyo Juvenil | N40: =+L40-M40 -> 0 | O40: =IFERROR(IF(7<>0, M40*100/L40, IF(L40=M40, M40*100/L40, 0)), 0) -> 0 | R40: =+P40-Q40 -> 0 | S40: =IFERROR(IF(R40<>0, P40*100/Q40, IF(P40=Q40, P40*100/Q40, 0)), 0) -> 0 | Y40: =SUM(T40:X40) -> 0 | Z40: =+Y40*100/50 -> 0 | AA40: =+(S40+O40+Z40)/3 -> 0
A41: PROG | B41: RRHH | C41: Lider-Prog-EV1 | D41: Personal | K41: Diseñar plan de formacion virtual-presencial para ET y red en EV-1 | N41: =+L41-M41 -> 0 | O41: =IFERROR(IF(7<>0, M41*100/L41, IF(L41=M41, M41*100/L41, 0)), 0) -> 0 | R41: =+P41-Q41 -> 0 | S41: =IFERROR(IF(R41<>0, P41*100/Q41, IF(P41=Q41, P41*100/Q41, 0)), 0) -> 0 | Y41: =SUM(T41:X41) -> 0 | Z41: =+Y41*100/50 -> 0 | AA41: =+(S41+O41+Z41)/3 -> 0
A42: PROT | C42: Lider-Prot-Incid | D42: Personal | K42: Diseñar e implementar plan de formacion virtual-presencial para ET y MPBC | N42: =+L42-M42 -> 0 | O42: =IFERROR(IF(7<>0, M42*100/L42, IF(L42=M42, M42*100/L42, 0)), 0) -> 0 | R42: =+P42-Q42 -> 0 | S42: =IFERROR(IF(R42<>0, P42*100/Q42, IF(P42=Q42, P42*100/Q42, 0)), 0) -> 0 | Y42: =SUM(T42:X42) -> 0 | Z42: =+Y42*100/50 -> 0 | AA42: =+(S42+O42+Z42)/3 -> 0
A43: PROG | B43: RRHH | C43: Lider-Prog-EV2 | D43: Personal | K43: Diseñar plan de formacion virtual-presencial para ET y Red en EV-2 | N43: =+L43-M43 -> 0 | O43: =IFERROR(IF(7<>0, M43*100/L43, IF(L43=M43, M43*100/L43, 0)), 0) -> 0 | R43: =+P43-Q43 -> 0 | S43: =IFERROR(IF(R43<>0, P43*100/Q43, IF(P43=Q43, P43*100/Q43, 0)), 0) -> 0 | Y43: =SUM(T43:X43) -> 0 | Z43: =+Y43*100/50 -> 0 | AA43: =+(S43+O43+Z43)/3 -> 0
A44: PROG | B44: RRHH | C44: Lider-Prog-EV3 | D44: Personal | K44: Diseñar e implementar plan de formacion virtual-presencial para ET y Red en EV-3 | N44: =+L44-M44 -> 0 | O44: =IFERROR(IF(7<>0, M44*100/L44, IF(L44=M44, M44*100/L44, 0)), 0) -> 0 | R44: =+P44-Q44 -> 0 | S44: =IFERROR(IF(R44<>0, P44*100/Q44, IF(P44=Q44, P44*100/Q44, 0)), 0) -> 0 | Y44: =SUM(T44:X44) -> 0 | Z44: =+Y44*100/50 -> 0 | AA44: =+(S44+O44+Z44)/3 -> 0
A45: COMU | B45: PROG | C45: Lider-Prog-EV2 | D45: Personal | K45: Diseñar e implementar plan de formacion virtual-presencial en Comunicaciones | N45: =+L45-M45 -> 0 | O45: =IFERROR(IF(7<>0, M45*100/L45, IF(L45=M45, M45*100/L45, 0)), 0) -> 0 | R45: =+P45-Q45 -> 0 | S45: =IFERROR(IF(R45<>0, P45*100/Q45, IF(P45=Q45, P45*100/Q45, 0)), 0) -> 0 | Y45: =SUM(T45:X45) -> 0 | Z45: =+Y45*100/50 -> 0 | AA45: =+(S45+O45+Z45)/3 -> 0
A46: RRHH | B46: PROG | C46: Lider-Prog-EV1 | D46: Personal | K46: Completar proceso de capacitación EV-1 institucional virtual-presencial | N46: =+L46-M46 -> 0 | O46: =IFERROR(IF(7<>0, M46*100/L46, IF(L46=M46, M46*100/L46, 0)), 0) -> 0 | R46: =+P46-Q46 -> 0 | S46: =IFERROR(IF(R46<>0, P46*100/Q46, IF(P46=Q46, P46*100/Q46, 0)), 0) -> 0 | Y46: =SUM(T46:X46) -> 0 | Z46: =+Y46*100/50 -> 0 | AA46: =+(S46+O46+Z46)/3 -> 0
A47: RRHH | B47: PROG | C47: Lider-Prog-EV2 | D47: Personal | K47: Completar proceso de capacitación EV-2 institucional virtual-presencial | N47: =+L47-M47 -> 0 | O47: =IFERROR(IF(7<>0, M47*100/L47, IF(L47=M47, M47*100/L47, 0)), 0) -> 0 | R47: =+P47-Q47 -> 0 | S47: =IFERROR(IF(R47<>0, P47*100/Q47, IF(P47=Q47, P47*100/Q47, 0)), 0) -> 0 | Y47: =SUM(T47:X47) -> 0 | Z47: =+Y47*100/50 -> 0 | AA47: =+(S47+O47+Z47)/3 -> 0
A48: RRHH | B48: PROG | C48: Lider-Prog-EV3 | D48: Personal | K48: Completar proceso de capacitación EV-3 institucional virtual-presencial | N48: =+L48-M48 -> 0 | O48: =IFERROR(IF(7<>0, M48*100/L48, IF(L48=M48, M48*100/L48, 0)), 0) -> 0 | R48: =+P48-Q48 -> 0 | S48: =IFERROR(IF(R48<>0, P48*100/Q48, IF(P48=Q48, P48*100/Q48, 0)), 0) -> 0 | Y48: =SUM(T48:X48) -> 0 | Z48: =+Y48*100/50 -> 0 | AA48: =+(S48+O48+Z48)/3 -> 0
A49: PROG | C49: Lider-Prog-EV1 | D49: Por Producto | K49: Desarrollar y promover CAP en Red de madres guía | L49: 60 | M49: 55 | N49: =+L49-M49 -> 5 | O49: =IFERROR(IF(7<>0, M49*100/L49, IF(L49=M49, M49*100/L49, 0)), 0) -> 91.666667 | P49: 5 | Q49: 7 | R49: =+P49-Q49 -> -2 | S49: =IFERROR(IF(R49<>0, P49*100/Q49, IF(P49=Q49, P49*100/Q49, 0)), 0) -> 71.428571 | T49: 7 | U49: 4 | V49: 2 | W49: 6 | X49: 5 | Y49: =SUM(T49:X49) -> 24 | Z49: =+Y49*100/50 -> 48 | AA49: =+(S49+O49+Z49)/3 -> 70.365079
A50: PROT | C50: Lider-Prot-Incid | D50: Por Producto | K50: Desarrollar y promover CAP en lideres de MPBC | N50: =+L50-M50 -> 0 | O50: =IFERROR(IF(7<>0, M50*100/L50, IF(L50=M50, M50*100/L50, 0)), 0) -> 0 | R50: =+P50-Q50 -> 0 | S50: =IFERROR(IF(R50<>0, P50*100/Q50, IF(P50=Q50, P50*100/Q50, 0)), 0) -> 0 | Y50: =SUM(T50:X50) -> 0 | Z50: =+Y50*100/50 -> 0 | AA50: =+(S50+O50+Z50)/3 -> 0
A51: PROG | C51: Lider-Prog-EV2 | D51: Por Producto | K51: Desarrollar y promover CAP en Red Educativa-APF y docentes | N51: =+L51-M51 -> 0 | O51: =IFERROR(IF(7<>0, M51*100/L51, IF(L51=M51, M51*100/L51, 0)), 0) -> 0 | R51: =+P51-Q51 -> 0 | S51: =IFERROR(IF(R51<>0, P51*100/Q51, IF(P51=Q51, P51*100/Q51, 0)), 0) -> 0 | Y51: =SUM(T51:X51) -> 0 | Z51: =+Y51*100/50 -> 0 | AA51: =+(S51+O51+Z51)/3 -> 0
A52: PROG | C52: Lider-Prog-EV3 | D52: Por Producto | K52: Desarrollar y promover CAP en Red de apoyo juvenil | N52: =+L52-M52 -> 0 | O52: =IFERROR(IF(7<>0, M52*100/L52, IF(L52=M52, M52*100/L52, 0)), 0) -> 0 | R52: =+P52-Q52 -> 0 | S52: =IFERROR(IF(R52<>0, P52*100/Q52, IF(P52=Q52, P52*100/Q52, 0)), 0) -> 0 | Y52: =SUM(T52:X52) -> 0 | Z52: =+Y52*100/50 -> 0 | AA52: =+(S52+O52+Z52)/3 -> 0
A53: PROT | C53: Lider-Prot-Incid | D53: Personal | K53: Facilitar proceso de formacion sobre politicas de proteccion y salvaguarda | N53: =+L53-M53 -> 0 | O53: =IFERROR(IF(7<>0, M53*100/L53, IF(L53=M53, M53*100/L53, 0)), 0) -> 0 | R53: =+P53-Q53 -> 0 | S53: =IFERROR(IF(R53<>0, P53*100/Q53, IF(P53=Q53, P53*100/Q53, 0)), 0) -> 0 | Y53: =SUM(T53:X53) -> 0 | Z53: =+Y53*100/50 -> 0 | AA53: =+(S53+O53+Z53)/3 -> 0
A54: RRHH | B54: PROT | C54: Lider-Prot-Incid | D54: Personal | K54: Completar proceso de capacitación EV-3 institucional virtual-presencial | N54: =+L54-M54 -> 0 | O54: =IFERROR(IF(7<>0, M54*100/L54, IF(L54=M54, M54*100/L54, 0)), 0) -> 0 | R54: =+P54-Q54 -> 0 | S54: =IFERROR(IF(R54<>0, P54*100/Q54, IF(P54=Q54, P54*100/Q54, 0)), 0) -> 0 | Y54: =SUM(T54:X54) -> 0 | Z54: =+Y54*100/50 -> 0 | AA54: =+(S54+O54+Z54)/3 -> 0
A55: PROT | C55: Equipo Tecnico | D55: Personal | K55: Completar capacitacion y firma de politica de proteccion y salvaguarda de NNAJ | N55: =+L55-M55 -> 0 | O55: =IFERROR(IF(7<>0, M55*100/L55, IF(L55=M55, M55*100/L55, 0)), 0) -> 0 | R55: =+P55-Q55 -> 0 | S55: =IFERROR(IF(R55<>0, P55*100/Q55, IF(P55=Q55, P55*100/Q55, 0)), 0) -> 0 | Y55: =SUM(T55:X55) -> 0 | Z55: =+Y55*100/50 -> 0 | AA55: =+(S55+O55+Z55)/3 -> 0
A56: PROT | B56: PROG | C56: Lider-Prog-EV1 | D56: Por Producto | K56: Actualizar y firmar acuerdos y politicas de proteccion y salvaguarda con lideres EV-1 (apoyos) | N56: =+L56-M56 -> 0 | O56: =IFERROR(IF(7<>0, M56*100/L56, IF(L56=M56, M56*100/L56, 0)), 0) -> 0 | R56: =+P56-Q56 -> 0 | S56: =IFERROR(IF(R56<>0, P56*100/Q56, IF(P56=Q56, P56*100/Q56, 0)), 0) -> 0 | Y56: =SUM(T56:X56) -> 0 | Z56: =+Y56*100/50 -> 0 | AA56: =+(S56+O56+Z56)/3 -> 0
A57: PROT | B57: PROG | C57: Lider-Prog-EV1 | D57: Por Producto | K57: Actualizar y firmar acuerdos y politicas de proteccion y salvaguarda a docentes EV-2 (apoyos) | N57: =+L57-M57 -> 0 | O57: =IFERROR(IF(7<>0, M57*100/L57, IF(L57=M57, M57*100/L57, 0)), 0) -> 0 | R57: =+P57-Q57 -> 0 | S57: =IFERROR(IF(R57<>0, P57*100/Q57, IF(P57=Q57, P57*100/Q57, 0)), 0) -> 0 | Y57: =SUM(T57:X57) -> 0 | Z57: =+Y57*100/50 -> 0 | AA57: =+(S57+O57+Z57)/3 -> 0
A58: PROT | B58: PROG | C58: Lider-Prog-EV3 | D58: Por Producto | K58: Actualizar y firmar acuerdos y politicas de proteccion y salvaguarda con lideres EV-3 (apoyos) | N58: =+L58-M58 -> 0 | O58: =IFERROR(IF(7<>0, M58*100/L58, IF(L58=M58, M58*100/L58, 0)), 0) -> 0 | R58: =+P58-Q58 -> 0 | S58: =IFERROR(IF(R58<>0, P58*100/Q58, IF(P58=Q58, P58*100/Q58, 0)), 0) -> 0 | Y58: =SUM(T58:X58) -> 0 | Z58: =+Y58*100/50 -> 0 | AA58: =+(S58+O58+Z58)/3 -> 0
A59: PROT | B59: MEAL | C59: Lider MEAL | D59: Personal | K59: Actualizar y firmar acuerdos y politicas de proteccion y salvaguarda | N59: =+L59-M59 -> 0 | O59: =IFERROR(IF(7<>0, M59*100/L59, IF(L59=M59, M59*100/L59, 0)), 0) -> 0 | R59: =+P59-Q59 -> 0 | S59: =IFERROR(IF(R59<>0, P59*100/Q59, IF(P59=Q59, P59*100/Q59, 0)), 0) -> 0 | Y59: =SUM(T59:X59) -> 0 | Z59: =+Y59*100/50 -> 0 | AA59: =+(S59+O59+Z59)/3 -> 0
A60: PROT | B60: PATR | C60: Lider-Prot-Incid | D60: Por Producto | K60: Actualizar y firmar acuerdos y politicas de proteccion y salvaguarda con apoyos | N60: =+L60-M60 -> 0 | O60: =IFERROR(IF(7<>0, M60*100/L60, IF(L60=M60, M60*100/L60, 0)), 0) -> 0 | R60: =+P60-Q60 -> 0 | S60: =IFERROR(IF(R60<>0, P60*100/Q60, IF(P60=Q60, P60*100/Q60, 0)), 0) -> 0 | Y60: =SUM(T60:X60) -> 0 | Z60: =+Y60*100/50 -> 0 | AA60: =+(S60+O60+Z60)/3 -> 0
A61: PROT | B61: ADM | C61: Lider Adm-RRHH | D61: Personal | K61: Actualizar y firmar acuerdos y politicas de proteccion y salvaguarda con apoyos | N61: =+L61-M61 -> 0 | O61: =IFERROR(IF(7<>0, M61*100/L61, IF(L61=M61, M61*100/L61, 0)), 0) -> 0 | R61: =+P61-Q61 -> 0 | S61: =IFERROR(IF(R61<>0, P61*100/Q61, IF(P61=Q61, P61*100/Q61, 0)), 0) -> 0 | Y61: =SUM(T61:X61) -> 0 | Z61: =+Y61*100/50 -> 0 | AA61: =+(S61+O61+Z61)/3 -> 0
A62: PROG | C62: Red de Madres guia | D62: Apoyo voluntario | K62: Implementar metodologías y acciones con grupos meta en Centros ADN | N62: =+L62-M62 -> 0 | O62: =IFERROR(IF(7<>0, M62*100/L62, IF(L62=M62, M62*100/L62, 0)), 0) -> 0 | R62: =+P62-Q62 -> 0 | S62: =IFERROR(IF(R62<>0, P62*100/Q62, IF(P62=Q62, P62*100/Q62, 0)), 0) -> 0 | Y62: =SUM(T62:X62) -> 0 | Z62: =+Y62*100/50 -> 0 | AA62: =+(S62+O62+Z62)/3 -> 0
A63: PROG | C63: Red de Docentes | D63: Apoyo voluntario | K63: Implementar metodologías y acciones con grupos meta en Centros Educativos | N63: =+L63-M63 -> 0 | O63: =IFERROR(IF(7<>0, M63*100/L63, IF(L63=M63, M63*100/L63, 0)), 0) -> 0 | R63: =+P63-Q63 -> 0 | S63: =IFERROR(IF(R63<>0, P63*100/Q63, IF(P63=Q63, P63*100/Q63, 0)), 0) -> 0 | Y63: =SUM(T63:X63) -> 0 | Z63: =+Y63*100/50 -> 0 | AA63: =+(S63+O63+Z63)/3 -> 0
A64: PROG | C64: Red de Apoyo Juvenil | D64: Apoyo voluntario | K64: Acompañar el desarrollo de plan de vida y formación en liderazgo a AJ | N64: =+L64-M64 -> 0 | O64: =IFERROR(IF(7<>0, M64*100/L64, IF(L64=M64, M64*100/L64, 0)), 0) -> 0 | R64: =+P64-Q64 -> 0 | S64: =IFERROR(IF(R64<>0, P64*100/Q64, IF(P64=Q64, P64*100/Q64, 0)), 0) -> 0 | Y64: =SUM(T64:X64) -> 0 | Z64: =+Y64*100/50 -> 0 | AA64: =+(S64+O64+Z64)/3 -> 0
A65: PROG | B65: PROT | C65: Lider-Prog-EV1 | D65: Personal | K65: Diseñar Guion Metodologico y protocolo para desarrollo de Feria EV-1 y Proteccion | N65: =+L65-M65 -> 0 | O65: =IFERROR(IF(7<>0, M65*100/L65, IF(L65=M65, M65*100/L65, 0)), 0) -> 0 | R65: =+P65-Q65 -> 0 | S65: =IFERROR(IF(R65<>0, P65*100/Q65, IF(P65=Q65, P65*100/Q65, 0)), 0) -> 0 | Y65: =SUM(T65:X65) -> 0 | Z65: =+Y65*100/50 -> 0 | AA65: =+(S65+O65+Z65)/3 -> 0
A66: PROG | B66: PROT | C66: Lider-Prog-EV2 | D66: Personal | K66: Diseñar Guion Metodologico y protocolo para desarrollo de Feria EV-2 y Proteccion | N66: =+L66-M66 -> 0 | O66: =IFERROR(IF(7<>0, M66*100/L66, IF(L66=M66, M66*100/L66, 0)), 0) -> 0 | R66: =+P66-Q66 -> 0 | S66: =IFERROR(IF(R66<>0, P66*100/Q66, IF(P66=Q66, P66*100/Q66, 0)), 0) -> 0 | Y66: =SUM(T66:X66) -> 0 | Z66: =+Y66*100/50 -> 0 | AA66: =+(S66+O66+Z66)/3 -> 0
A67: PROG | B67: PROT | C67: Lider-Prog-EV3 | D67: Personal | K67: Diseñar Guion Metodologico y protocolo para Encuentros Juveniles y Proteccion | N67: =+L67-M67 -> 0 | O67: =IFERROR(IF(7<>0, M67*100/L67, IF(L67=M67, M67*100/L67, 0)), 0) -> 0 | R67: =+P67-Q67 -> 0 | S67: =IFERROR(IF(R67<>0, P67*100/Q67, IF(P67=Q67, P67*100/Q67, 0)), 0) -> 0 | Y67: =SUM(T67:X67) -> 0 | Z67: =+Y67*100/50 -> 0 | AA67: =+(S67+O67+Z67)/3 -> 0
A68: PROG | B68: PROT | C68: Red de Madres guia | D68: Por Producto | K68: Organizar e implementar en centros ADN, feria promocional de DDNN en EV-1 | N68: =+L68-M68 -> 0 | O68: =IFERROR(IF(7<>0, M68*100/L68, IF(L68=M68, M68*100/L68, 0)), 0) -> 0 | R68: =+P68-Q68 -> 0 | S68: =IFERROR(IF(R68<>0, P68*100/Q68, IF(P68=Q68, P68*100/Q68, 0)), 0) -> 0 | Y68: =SUM(T68:X68) -> 0 | Z68: =+Y68*100/50 -> 0 | AA68: =+(S68+O68+Z68)/3 -> 0
A69: PROG | B69: PROT | C69: Red de Docentes | D69: Por Producto | K69: Organizar e implementar en Escuelas, feria promocional de DDNN en EV-2 | N69: =+L69-M69 -> 0 | O69: =IFERROR(IF(7<>0, M69*100/L69, IF(L69=M69, M69*100/L69, 0)), 0) -> 0 | R69: =+P69-Q69 -> 0 | S69: =IFERROR(IF(R69<>0, P69*100/Q69, IF(P69=Q69, P69*100/Q69, 0)), 0) -> 0 | Y69: =SUM(T69:X69) -> 0 | Z69: =+Y69*100/50 -> 0 | AA69: =+(S69+O69+Z69)/3 -> 0
A70: PROG | B70: PROT | C70: Red de Apoyo Juvenil | D70: Por Producto | K70: Organizar e implementar encuentros juveniles EV-3 en la comunidad | N70: =+L70-M70 -> 0 | O70: =IFERROR(IF(7<>0, M70*100/L70, IF(L70=M70, M70*100/L70, 0)), 0) -> 0 | R70: =+P70-Q70 -> 0 | S70: =IFERROR(IF(R70<>0, P70*100/Q70, IF(P70=Q70, P70*100/Q70, 0)), 0) -> 0 | Y70: =SUM(T70:X70) -> 0 | Z70: =+Y70*100/50 -> 0 | AA70: =+(S70+O70+Z70)/3 -> 0
A71: MEAL | B71: PROG | C71: Lider-Prog-EV1 | D71: Por Producto | K71: Realizar visitas de monitoreo y asistencia tecnica a lideres en Proy- EV-1 (CCIT) | N71: =+L71-M71 -> 0 | O71: =IFERROR(IF(7<>0, M71*100/L71, IF(L71=M71, M71*100/L71, 0)), 0) -> 0 | R71: =+P71-Q71 -> 0 | S71: =IFERROR(IF(R71<>0, P71*100/Q71, IF(P71=Q71, P71*100/Q71, 0)), 0) -> 0 | Y71: =SUM(T71:X71) -> 0 | Z71: =+Y71*100/50 -> 0 | AA71: =+(S71+O71+Z71)/3 -> 0
A72: MEAL | B72: PROG | C72: Lider-Prog-EV2 | D72: Por Producto | K72: Realizar visitas de monitoreo y asistencia tecnica a lideres en Proy- EV-2 (CCIT) | N72: =+L72-M72 -> 0 | O72: =IFERROR(IF(7<>0, M72*100/L72, IF(L72=M72, M72*100/L72, 0)), 0) -> 0 | R72: =+P72-Q72 -> 0 | S72: =IFERROR(IF(R72<>0, P72*100/Q72, IF(P72=Q72, P72*100/Q72, 0)), 0) -> 0 | Y72: =SUM(T72:X72) -> 0 | Z72: =+Y72*100/50 -> 0 | AA72: =+(S72+O72+Z72)/3 -> 0
A73: MEAL | B73: PROG | C73: Lider-Prog-EV3 | D73: Por Producto | K73: Realizar visitas de monitoreo y asistencia tecnica a lideres en Proy- EV-3 (CCIT) | N73: =+L73-M73 -> 0 | O73: =IFERROR(IF(7<>0, M73*100/L73, IF(L73=M73, M73*100/L73, 0)), 0) -> 0 | R73: =+P73-Q73 -> 0 | S73: =IFERROR(IF(R73<>0, P73*100/Q73, IF(P73=Q73, P73*100/Q73, 0)), 0) -> 0 | Y73: =SUM(T73:X73) -> 0 | Z73: =+Y73*100/50 -> 0 | AA73: =+(S73+O73+Z73)/3 -> 0
A74: MEAL | B74: PROT | C74: Lider-Prot-Incid | D74: Por Producto | K74: Realizar visitas de monitoreo y asistencia tecnica a lideres en Proteccion (CCIT) | N74: =+L74-M74 -> 0 | O74: =IFERROR(IF(7<>0, M74*100/L74, IF(L74=M74, M74*100/L74, 0)), 0) -> 0 | R74: =+P74-Q74 -> 0 | S74: =IFERROR(IF(R74<>0, P74*100/Q74, IF(P74=Q74, P74*100/Q74, 0)), 0) -> 0 | Y74: =SUM(T74:X74) -> 0 | Z74: =+Y74*100/50 -> 0 | AA74: =+(S74+O74+Z74)/3 -> 0
A75: MEAL | C75: Lider MEAL | D75: Personal | K75: Diseñar y establecer lineamientos y herramientas para el MEAL | N75: =+L75-M75 -> 0 | O75: =IFERROR(IF(7<>0, M75*100/L75, IF(L75=M75, M75*100/L75, 0)), 0) -> 0 | R75: =+P75-Q75 -> 0 | S75: =IFERROR(IF(R75<>0, P75*100/Q75, IF(P75=Q75, P75*100/Q75, 0)), 0) -> 0 | Y75: =SUM(T75:X75) -> 0 | Z75: =+Y75*100/50 -> 0 | AA75: =+(S75+O75+Z75)/3 -> 0
A76: MEAL | C76: Lider MEAL | D76: Personal | K76: Socializar y capacitar a ET sobre uso y aplicación de herramientas de MEAL | N76: =+L76-M76 -> 0 | O76: =IFERROR(IF(7<>0, M76*100/L76, IF(L76=M76, M76*100/L76, 0)), 0) -> 0 | R76: =+P76-Q76 -> 0 | S76: =IFERROR(IF(R76<>0, P76*100/Q76, IF(P76=Q76, P76*100/Q76, 0)), 0) -> 0 | Y76: =SUM(T76:X76) -> 0 | Z76: =+Y76*100/50 -> 0 | AA76: =+(S76+O76+Z76)/3 -> 0
A77: MEAL | B77: PROG | C77: Lider-Prog-EV1 | D77: Personal | K77: Socializar y capacitar a Red de Madres guia sobre herramientas de MEAL | N77: =+L77-M77 -> 0 | O77: =IFERROR(IF(7<>0, M77*100/L77, IF(L77=M77, M77*100/L77, 0)), 0) -> 0 | R77: =+P77-Q77 -> 0 | S77: =IFERROR(IF(R77<>0, P77*100/Q77, IF(P77=Q77, P77*100/Q77, 0)), 0) -> 0 | Y77: =SUM(T77:X77) -> 0 | Z77: =+Y77*100/50 -> 0 | AA77: =+(S77+O77+Z77)/3 -> 0
A78: MEAL | B78: PROG | C78: Lider-Prog-EV2 | D78: Personal | K78: Socializar y capacitar a Docentes sobre herramientas de MEAL | N78: =+L78-M78 -> 0 | O78: =IFERROR(IF(7<>0, M78*100/L78, IF(L78=M78, M78*100/L78, 0)), 0) -> 0 | R78: =+P78-Q78 -> 0 | S78: =IFERROR(IF(R78<>0, P78*100/Q78, IF(P78=Q78, P78*100/Q78, 0)), 0) -> 0 | Y78: =SUM(T78:X78) -> 0 | Z78: =+Y78*100/50 -> 0 | AA78: =+(S78+O78+Z78)/3 -> 0
A79: MEAL | B79: PROG | C79: Lider-Prog-EV3 | D79: Personal | K79: Socializar y capacitar a Red de Apoyo Juvenil sobre herramientas de MEAL | N79: =+L79-M79 -> 0 | O79: =IFERROR(IF(7<>0, M79*100/L79, IF(L79=M79, M79*100/L79, 0)), 0) -> 0 | R79: =+P79-Q79 -> 0 | S79: =IFERROR(IF(R79<>0, P79*100/Q79, IF(P79=Q79, P79*100/Q79, 0)), 0) -> 0 | Y79: =SUM(T79:X79) -> 0 | Z79: =+Y79*100/50 -> 0 | AA79: =+(S79+O79+Z79)/3 -> 0
A80: MEAL | B80: PROG | C80: Lider-Prog-EV1 | D80: Por Producto | K80: Entregar herramientas de MEAL digitales y fisicas a Red de madres guia (Reunion Mes) | N80: =+L80-M80 -> 0 | O80: =IFERROR(IF(7<>0, M80*100/L80, IF(L80=M80, M80*100/L80, 0)), 0) -> 0 | R80: =+P80-Q80 -> 0 | S80: =IFERROR(IF(R80<>0, P80*100/Q80, IF(P80=Q80, P80*100/Q80, 0)), 0) -> 0 | Y80: =SUM(T80:X80) -> 0 | Z80: =+Y80*100/50 -> 0 | AA80: =+(S80+O80+Z80)/3 -> 0
A81: MEAL | B81: PROG | C81: Lider-Prog-EV2 | D81: Por Producto | K81: Entregar herramientas de MEAL digitales y fisicas a Docentes (Reunion Mes) | N81: =+L81-M81 -> 0 | O81: =IFERROR(IF(7<>0, M81*100/L81, IF(L81=M81, M81*100/L81, 0)), 0) -> 0 | R81: =+P81-Q81 -> 0 | S81: =IFERROR(IF(R81<>0, P81*100/Q81, IF(P81=Q81, P81*100/Q81, 0)), 0) -> 0 | Y81: =SUM(T81:X81) -> 0 | Z81: =+Y81*100/50 -> 0 | AA81: =+(S81+O81+Z81)/3 -> 0
A82: MEAL | B82: PROG | C82: Lider-Prog-EV3 | D82: Por Producto | K82: Entregar herramientas de MEAL digitales y fisicas a Red de Apoyo Juvenil (Reunion) | N82: =+L82-M82 -> 0 | O82: =IFERROR(IF(7<>0, M82*100/L82, IF(L82=M82, M82*100/L82, 0)), 0) -> 0 | R82: =+P82-Q82 -> 0 | S82: =IFERROR(IF(R82<>0, P82*100/Q82, IF(P82=Q82, P82*100/Q82, 0)), 0) -> 0 | Y82: =SUM(T82:X82) -> 0 | Z82: =+Y82*100/50 -> 0 | AA82: =+(S82+O82+Z82)/3 -> 0
A83: MEAL | B83: PROG | C83: Lider-Prog-EV1 | D83: Por Producto | K83: Recolectar, revisar y subir en linea los medios de verificacion de EV-1 completos | N83: =+L83-M83 -> 0 | O83: =IFERROR(IF(7<>0, M83*100/L83, IF(L83=M83, M83*100/L83, 0)), 0) -> 0 | R83: =+P83-Q83 -> 0 | S83: =IFERROR(IF(R83<>0, P83*100/Q83, IF(P83=Q83, P83*100/Q83, 0)), 0) -> 0 | Y83: =SUM(T83:X83) -> 0 | Z83: =+Y83*100/50 -> 0 | AA83: =+(S83+O83+Z83)/3 -> 0
A84: MEAL | B84: PROG | C84: Lider-Prog-EV2 | D84: Por Producto | K84: Recolectar, revisar y subir en linea los medios de verificacion de EV-2 | N84: =+L84-M84 -> 0 | O84: =IFERROR(IF(7<>0, M84*100/L84, IF(L84=M84, M84*100/L84, 0)), 0) -> 0 | R84: =+P84-Q84 -> 0 | S84: =IFERROR(IF(R84<>0, P84*100/Q84, IF(P84=Q84, P84*100/Q84, 0)), 0) -> 0 | Y84: =SUM(T84:X84) -> 0 | Z84: =+Y84*100/50 -> 0 | AA84: =+(S84+O84+Z84)/3 -> 0
A85: MEAL | B85: PROG | C85: Lider-Prog-EV3 | D85: Por Producto | K85: Recolectar, revisar y subir en linea los medios de verificacion de EV-3 completos | N85: =+L85-M85 -> 0 | O85: =IFERROR(IF(7<>0, M85*100/L85, IF(L85=M85, M85*100/L85, 0)), 0) -> 0 | R85: =+P85-Q85 -> 0 | S85: =IFERROR(IF(R85<>0, P85*100/Q85, IF(P85=Q85, P85*100/Q85, 0)), 0) -> 0 | Y85: =SUM(T85:X85) -> 0 | Z85: =+Y85*100/50 -> 0 | AA85: =+(S85+O85+Z85)/3 -> 0
A86: MEAL | C86: Lider MEAL | D86: Por Producto | K86: Revisar y digitalizar en CAMEL los medios de verificacion en linea (Contrato) | N86: =+L86-M86 -> 0 | O86: =IFERROR(IF(7<>0, M86*100/L86, IF(L86=M86, M86*100/L86, 0)), 0) -> 0 | R86: =+P86-Q86 -> 0 | S86: =IFERROR(IF(R86<>0, P86*100/Q86, IF(P86=Q86, P86*100/Q86, 0)), 0) -> 0 | Y86: =SUM(T86:X86) -> 0 | Z86: =+Y86*100/50 -> 0 | AA86: =+(S86+O86+Z86)/3 -> 0
A87: MEAL | C87: Lider MEAL | D87: Personal | K87: Socializar y facilitar a ET lider, herramientas para la elaboracion de informe mensual | N87: =+L87-M87 -> 0 | O87: =IFERROR(IF(7<>0, M87*100/L87, IF(L87=M87, M87*100/L87, 0)), 0) -> 0 | R87: =+P87-Q87 -> 0 | S87: =IFERROR(IF(R87<>0, P87*100/Q87, IF(P87=Q87, P87*100/Q87, 0)), 0) -> 0 | Y87: =SUM(T87:X87) -> 0 | Z87: =+Y87*100/50 -> 0 | AA87: =+(S87+O87+Z87)/3 -> 0
A88: MEAL | B88: PROG | C88: Lider-Prog-EV1 | D88: Personal | K88: Elaborar informe mensual y analisis de resultados en Proy-EV-1 | N88: =+L88-M88 -> 0 | O88: =IFERROR(IF(7<>0, M88*100/L88, IF(L88=M88, M88*100/L88, 0)), 0) -> 0 | R88: =+P88-Q88 -> 0 | S88: =IFERROR(IF(R88<>0, P88*100/Q88, IF(P88=Q88, P88*100/Q88, 0)), 0) -> 0 | Y88: =SUM(T88:X88) -> 0 | Z88: =+Y88*100/50 -> 0 | AA88: =+(S88+O88+Z88)/3 -> 0
A89: MEAL | B89: PROG | C89: Lider-Prog-EV2 | D89: Personal | K89: Elaborar informe mensual y analisis de resultados en Proy-EV-2 | N89: =+L89-M89 -> 0 | O89: =IFERROR(IF(7<>0, M89*100/L89, IF(L89=M89, M89*100/L89, 0)), 0) -> 0 | R89: =+P89-Q89 -> 0 | S89: =IFERROR(IF(R89<>0, P89*100/Q89, IF(P89=Q89, P89*100/Q89, 0)), 0) -> 0 | Y89: =SUM(T89:X89) -> 0 | Z89: =+Y89*100/50 -> 0 | AA89: =+(S89+O89+Z89)/3 -> 0
A90: MEAL | B90: PROG | C90: Lider-Prog-EV3 | D90: Personal | K90: Elaborar informe mensual y analisis de resultados en Proy-EV-3 | N90: =+L90-M90 -> 0 | O90: =IFERROR(IF(7<>0, M90*100/L90, IF(L90=M90, M90*100/L90, 0)), 0) -> 0 | R90: =+P90-Q90 -> 0 | S90: =IFERROR(IF(R90<>0, P90*100/Q90, IF(P90=Q90, P90*100/Q90, 0)), 0) -> 0 | Y90: =SUM(T90:X90) -> 0 | Z90: =+Y90*100/50 -> 0 | AA90: =+(S90+O90+Z90)/3 -> 0
A91: MEAL | B91: PROT | C91: Lider-Prot-Incid | D91: Personal | K91: Elaborar informe mensual y analisis de resultados en Proteccion e incidencia | N91: =+L91-M91 -> 0 | O91: =IFERROR(IF(7<>0, M91*100/L91, IF(L91=M91, M91*100/L91, 0)), 0) -> 0 | R91: =+P91-Q91 -> 0 | S91: =IFERROR(IF(R91<>0, P91*100/Q91, IF(P91=Q91, P91*100/Q91, 0)), 0) -> 0 | Y91: =SUM(T91:X91) -> 0 | Z91: =+Y91*100/50 -> 0 | AA91: =+(S91+O91+Z91)/3 -> 0
A92: MEAL | B92: PATR | C92: Lider-Patrocinio | D92: Personal | K92: Elaborar informe mensual y analisis de resultados en Patrocinio | N92: =+L92-M92 -> 0 | O92: =IFERROR(IF(7<>0, M92*100/L92, IF(L92=M92, M92*100/L92, 0)), 0) -> 0 | R92: =+P92-Q92 -> 0 | S92: =IFERROR(IF(R92<>0, P92*100/Q92, IF(P92=Q92, P92*100/Q92, 0)), 0) -> 0 | Y92: =SUM(T92:X92) -> 0 | Z92: =+Y92*100/50 -> 0 | AA92: =+(S92+O92+Z92)/3 -> 0
A93: MEAL | C93: Lider MEAL | D93: Personal | K93: Revisar, consolidar y enviar a OC en tiempo y forma el informe mensual | N93: =+L93-M93 -> 0 | O93: =IFERROR(IF(7<>0, M93*100/L93, IF(L93=M93, M93*100/L93, 0)), 0) -> 0 | R93: =+P93-Q93 -> 0 | S93: =IFERROR(IF(R93<>0, P93*100/Q93, IF(P93=Q93, P93*100/Q93, 0)), 0) -> 0 | Y93: =SUM(T93:X93) -> 0 | Z93: =+Y93*100/50 -> 0 | AA93: =+(S93+O93+Z93)/3 -> 0
A94: MEAL | B94: PROG | C94: Lider MEAL | D94: Sinergia Equipo | K94: Liderar la capacitacion y organización para levantamiento de Encuesta Global | N94: =+L94-M94 -> 0 | O94: =IFERROR(IF(7<>0, M94*100/L94, IF(L94=M94, M94*100/L94, 0)), 0) -> 0 | R94: =+P94-Q94 -> 0 | S94: =IFERROR(IF(R94<>0, P94*100/Q94, IF(P94=Q94, P94*100/Q94, 0)), 0) -> 0 | Y94: =SUM(T94:X94) -> 0 | Z94: =+Y94*100/50 -> 0 | AA94: =+(S94+O94+Z94)/3 -> 0
A95: MEAL | C95: Lider MEAL | D95: Por Producto | K95: Completar capacitacion y levantamiento de encuesta global según MEAL (Contrato) | N95: =+L95-M95 -> 0 | O95: =IFERROR(IF(7<>0, M95*100/L95, IF(L95=M95, M95*100/L95, 0)), 0) -> 0 | R95: =+P95-Q95 -> 0 | S95: =IFERROR(IF(R95<>0, P95*100/Q95, IF(P95=Q95, P95*100/Q95, 0)), 0) -> 0 | Y95: =SUM(T95:X95) -> 0 | Z95: =+Y95*100/50 -> 0 | AA95: =+(S95+O95+Z95)/3 -> 0
A96: MEAL | C96: Lider MEAL | D96: Personal | K96: Asegurar el cumplimiento y envio de encuesta global según lineamientos | N96: =+L96-M96 -> 0 | O96: =IFERROR(IF(7<>0, M96*100/L96, IF(L96=M96, M96*100/L96, 0)), 0) -> 0 | R96: =+P96-Q96 -> 0 | S96: =IFERROR(IF(R96<>0, P96*100/Q96, IF(P96=Q96, P96*100/Q96, 0)), 0) -> 0 | Y96: =SUM(T96:X96) -> 0 | Z96: =+Y96*100/50 -> 0 | AA96: =+(S96+O96+Z96)/3 -> 0
A97: MEAL | C97: Lider MEAL | D97: Por Producto | K97: Elaborar Reporte de alcance anual o conteo de participantes | N97: =+L97-M97 -> 0 | O97: =IFERROR(IF(7<>0, M97*100/L97, IF(L97=M97, M97*100/L97, 0)), 0) -> 0 | R97: =+P97-Q97 -> 0 | S97: =IFERROR(IF(R97<>0, P97*100/Q97, IF(P97=Q97, P97*100/Q97, 0)), 0) -> 0 | Y97: =SUM(T97:X97) -> 0 | Z97: =+Y97*100/50 -> 0 | AA97: =+(S97+O97+Z97)/3 -> 0
A98: MEAL | C98: Lider MEAL | D98: Personal | K98: Socializar y facilitar a ET lider, herramientas para la elaboracion de informe anual | N98: =+L98-M98 -> 0 | O98: =IFERROR(IF(7<>0, M98*100/L98, IF(L98=M98, M98*100/L98, 0)), 0) -> 0 | R98: =+P98-Q98 -> 0 | S98: =IFERROR(IF(R98<>0, P98*100/Q98, IF(P98=Q98, P98*100/Q98, 0)), 0) -> 0 | Y98: =SUM(T98:X98) -> 0 | Z98: =+Y98*100/50 -> 0 | AA98: =+(S98+O98+Z98)/3 -> 0
A99: MEAL | B99: PROG | C99: Lider-Prog-EV1 | D99: Personal | K99: Elaborar informe anual y analisis de resultados en Proy-EV-1 | N99: =+L99-M99 -> 0 | O99: =IFERROR(IF(7<>0, M99*100/L99, IF(L99=M99, M99*100/L99, 0)), 0) -> 0 | R99: =+P99-Q99 -> 0 | S99: =IFERROR(IF(R99<>0, P99*100/Q99, IF(P99=Q99, P99*100/Q99, 0)), 0) -> 0 | Y99: =SUM(T99:X99) -> 0 | Z99: =+Y99*100/50 -> 0 | AA99: =+(S99+O99+Z99)/3 -> 0
A100: MEAL | B100: PROG | C100: Lider-Prog-EV2 | D100: Personal | K100: Elaborar informe anual y analisis de resultados en Proy-EV-2 | N100: =+L100-M100 -> 0 | O100: =IFERROR(IF(7<>0, M100*100/L100, IF(L100=M100, M100*100/L100, 0)), 0) -> 0 | R100: =+P100-Q100 -> 0 | S100: =IFERROR(IF(R100<>0, P100*100/Q100, IF(P100=Q100, P100*100/Q100, 0)), 0) -> 0 | Y100: =SUM(T100:X100) -> 0 | Z100: =+Y100*100/50 -> 0 | AA100: =+(S100+O100+Z100)/3 -> 0
A101: MEAL | B101: PROG | C101: Lider-Prog-EV3 | D101: Personal | K101: Elaborar informe anual y analisis de resultados en Proy-EV-3 | N101: =+L101-M101 -> 0 | O101: =IFERROR(IF(7<>0, M101*100/L101, IF(L101=M101, M101*100/L101, 0)), 0) -> 0 | R101: =+P101-Q101 -> 0 | S101: =IFERROR(IF(R101<>0, P101*100/Q101, IF(P101=Q101, P101*100/Q101, 0)), 0) -> 0 | Y101: =SUM(T101:X101) -> 0 | Z101: =+Y101*100/50 -> 0 | AA101: =+(S101+O101+Z101)/3 -> 0
A102: MEAL | B102: PROT | C102: Lider-Prot-Incid | D102: Personal | K102: Elaborar informe anual y analisis de resultados en Proteccion e incidencia | N102: =+L102-M102 -> 0 | O102: =IFERROR(IF(7<>0, M102*100/L102, IF(L102=M102, M102*100/L102, 0)), 0) -> 0 | R102: =+P102-Q102 -> 0 | S102: =IFERROR(IF(R102<>0, P102*100/Q102, IF(P102=Q102, P102*100/Q102, 0)), 0) -> 0 | Y102: =SUM(T102:X102) -> 0 | Z102: =+Y102*100/50 -> 0 | AA102: =+(S102+O102+Z102)/3 -> 0
A103: MEAL | B103: PATR | C103: Lider-Patrocinio | D103: Personal | K103: Elaborar informe anual y analisis de resultados en Patrocinio | N103: =+L103-M103 -> 0 | O103: =IFERROR(IF(7<>0, M103*100/L103, IF(L103=M103, M103*100/L103, 0)), 0) -> 0 | R103: =+P103-Q103 -> 0 | S103: =IFERROR(IF(R103<>0, P103*100/Q103, IF(P103=Q103, P103*100/Q103, 0)), 0) -> 0 | Y103: =SUM(T103:X103) -> 0 | Z103: =+Y103*100/50 -> 0 | AA103: =+(S103+O103+Z103)/3 -> 0
...

Sheet David
A1: ACCION HONDURAS
A2: MATRIZ DE EVALUACION DE DESEMPEÑO DEL COLABORADOR
A4: Nombre y cargo del Colaborador: | G4: Jose Adalid Funes - Técnico de Desarrollo Comunitario | I4: David Alonzo Ramos - Técnico de Desarrollo Comunitario | M4: Evaluador: | O4: Edwing Armando Lopez Esteves - Lider de Programa EV-3
M5: VoBo RRHH | O5: Jennifer Sabrina Romero Martínez - Especialista en RRHH
A7: Area | D7: Periodo evaluado | E7: Marco de Resultados | I7: Responsabilidades del colaborador | J7: Cantidad a Lograr | N7: Tiempo Definido (dias) | R7: Estandares de calidad (Escala de 10) | Y7: Nota Final
A8: Principal | B8: Transversal | C8: Responsable | E8: S | F8: SS | G8: ML | H8: Ext | J8: Programada | K8: Entregada | L8: Diferencia | M8: % | N8: Programado | O8: Entregada | P8: Diferencia | Q8: % | R8: Puntualidad | S8: Resolucion de Problemas | T8: Coordinaciión local | U8: Nivel de satisfacción de Grupos meta | V8: Nivel de preparación | W8: Total Estandares (Nota max. 50) | X8: %
A10: PROG | B10: MEAL | C10: Lider-Prog-EV1 | E10: H_Salud | F10: HB_Nutrición | G10: HB041-01_Suplementos_nutricionales_para_niños_con_desnutrición_aguda_grave_o_desnutrición_aguda_moderada | H10: 1 | I10: Diseñar herramientas y protocolo para Dx.situacional de EV-1 | L10: =+J10-K10 -> 0 | M10: =IFERROR(IF(7<>0, K10*100/J10, IF(J10=K10, K10*100/J10, 0)), 0) -> 0 | P10: =+N10-O10 -> 0 | Q10: =IFERROR(IF(P10<>0, N10*100/O10, IF(N10=O10, N10*100/O10, 0)), 0) -> 0 | W10: =SUM(R10:V10) -> 0 | X10: =+W10*100/50 -> 0 | Y10: =+(Q10+M10+X10)/3 -> 0
A11: PROG | B11: MEAL | C11: Lider-Prog-EV2 | E11: H_Salud | F11: HB_Nutrición | G11: HB041-01_Suplementos_nutricionales_para_niños_con_desnutrición_aguda_grave_o_desnutrición_aguda_moderada | H11: 1 | I11: Diseñar herramientas y protocolo para Dx.situacional de EV-2 | L11: =+J11-K11 -> 0 | M11: =IFERROR(IF(7<>0, K11*100/J11, IF(J11=K11, K11*100/J11, 0)), 0) -> 0 | P11: =+N11-O11 -> 0 | Q11: =IFERROR(IF(P11<>0, N11*100/O11, IF(N11=O11, N11*100/O11, 0)), 0) -> 0 | W11: =SUM(R11:V11) -> 0 | X11: =+W11*100/50 -> 0 | Y11: =+(Q11+M11+X11)/3 -> 0
A12: PROG | B12: MEAL | C12: Lider-Prog-EV3 | E12: H_Salud | F12: HB_Nutrición | G12: HB041-01_Suplementos_nutricionales_para_niños_con_desnutrición_aguda_grave_o_desnutrición_aguda_moderada | H12: 1 | I12: Diseñar herramientas y protocolo para Dx.situacional de EV-3 | L12: =+J12-K12 -> 0 | M12: =IFERROR(IF(7<>0, K12*100/J12, IF(J12=K12, K12*100/J12, 0)), 0) -> 0 | P12: =+N12-O12 -> 0 | Q12: =IFERROR(IF(P12<>0, N12*100/O12, IF(N12=O12, N12*100/O12, 0)), 0) -> 0 | W12: =SUM(R12:V12) -> 0 | X12: =+W12*100/50 -> 0 | Y12: =+(Q12+M12+X12)/3 -> 0
A13: PROG | B13: MEAL | C13: Tecn-Prog-EV-1 | E13: H_Salud | F13: HB_Nutrición | G13: HB041-01_Suplementos_nutricionales_para_niños_con_desnutrición_aguda_grave_o_desnutrición_aguda_moderada | H13: 1 | I13: Levantar Diagnostico situacional de primera infancia | J13: 500 | K13: 410 | L13: =+J13-K13 -> 90 | M13: =IFERROR(IF(7<>0, K13*100/J13, IF(J13=K13, K13*100/J13, 0)), 0) -> 82 | N13: 15 | O13: 22 | P13: =+N13-O13 -> -7 | Q13: =IFERROR(IF(P13<>0, N13*100/O13, IF(N13=O13, N13*100/O13, 0)), 0) -> 68.181818 | R13: 9 | S13: 7 | T13: 10 | U13: 8 | V13: 10 | W13: =SUM(R13:V13) -> 44 | X13: =+W13*100/50 -> 88 | Y13: =+(Q13+M13+X13)/3 -> 79.393939
A14: PROG | B14: MEAL | C14: Tecn-Prog-EV-2 | I14: Levantar diagnóstico situacional de NN en el Centro Educativo. | L14: =+J14-K14 -> 0 | M14: =IFERROR(IF(7<>0, K14*100/J14, IF(J14=K14, K14*100/J14, 0)), 0) -> 0 | P14: =+N14-O14 -> 0 | Q14: =IFERROR(IF(P14<>0, N14*100/O14, IF(N14=O14, N14*100/O14, 0)), 0) -> 0 | W14: =SUM(R14:V14) -> 0 | X14: =+W14*100/50 -> 0 | Y14: =+(Q14+M14+X14)/3 -> 0
A15: PROG | B15: MEAL | C15: Tecn-Prog-EV-3 | I15: Levantar diagnóstico aptitudinal y de intereses de AJ en las comunidades | L15: =+J15-K15 -> 0 | M15: =IFERROR(IF(7<>0, K15*100/J15, IF(J15=K15, K15*100/J15, 0)), 0) -> 0 | P15: =+N15-O15 -> 0 | Q15: =IFERROR(IF(P15<>0, N15*100/O15, IF(N15=O15, N15*100/O15, 0)), 0) -> 0 | W15: =SUM(R15:V15) -> 0 | X15: =+W15*100/50 -> 0 | Y15: =+(Q15+M15+X15)/3 -> 0
A16: PROG | B16: MEAL | C16: Lider-Prog-EV1 | I16: Procesar y limpiar datos de Dx para elaborar informe sobre situacion EV-1 | L16: =+J16-K16 -> 0 | M16: =IFERROR(IF(7<>0, K16*100/J16, IF(J16=K16, K16*100/J16, 0)), 0) -> 0 | P16: =+N16-O16 -> 0 | Q16: =IFERROR(IF(P16<>0, N16*100/O16, IF(N16=O16, N16*100/O16, 0)), 0) -> 0 | W16: =SUM(R16:V16) -> 0 | X16: =+W16*100/50 -> 0 | Y16: =+(Q16+M16+X16)/3 -> 0
A17: PROG | B17: MEAL | C17: Lider-Prog-EV2 | I17: Procesar y limpiar datos de Dx para elaborar informe sobre situacion EV-2 | L17: =+J17-K17 -> 0 | M17: =IFERROR(IF(7<>0, K17*100/J17, IF(J17=K17, K17*100/J17, 0)), 0) -> 0 | P17: =+N17-O17 -> 0 | Q17: =IFERROR(IF(P17<>0, N17*100/O17, IF(N17=O17, N17*100/O17, 0)), 0) -> 0 | W17: =SUM(R17:V17) -> 0 | X17: =+W17*100/50 -> 0 | Y17: =+(Q17+M17+X17)/3 -> 0
A18: PROG | B18: MEAL | C18: Lider-Prog-EV3 | I18: Procesar y limpiar datos de Dx para elaborar informe sobre situacion EV-3 | L18: =+J18-K18 -> 0 | M18: =IFERROR(IF(7<>0, K18*100/J18, IF(J18=K18, K18*100/J18, 0)), 0) -> 0 | P18: =+N18-O18 -> 0 | Q18: =IFERROR(IF(P18<>0, N18*100/O18, IF(N18=O18, N18*100/O18, 0)), 0) -> 0 | W18: =SUM(R18:V18) -> 0 | X18: =+W18*100/50 -> 0 | Y18: =+(Q18+M18+X18)/3 -> 0
A19: PROG | B19: MEAL | C19: Tecn-Prog-EV-1 | I19: Organizar evento de socialización de resultados de Dx.situacional EV-1 | L19: =+J19-K19 -> 0 | M19: =IFERROR(IF(7<>0, K19*100/J19, IF(J19=K19, K19*100/J19, 0)), 0) -> 0 | P19: =+N19-O19 -> 0 | Q19: =IFERROR(IF(P19<>0, N19*100/O19, IF(N19=O19, N19*100/O19, 0)), 0) -> 0 | W19: =SUM(R19:V19) -> 0 | X19: =+W19*100/50 -> 0 | Y19: =+(Q19+M19+X19)/3 -> 0
A20: PROG | B20: MEAL | C20: Tecn-Prog-EV-2 | I20: Organizar evento de socialización de resultados de Dx.situacional EV-2 | L20: =+J20-K20 -> 0 | M20: =IFERROR(IF(7<>0, K20*100/J20, IF(J20=K20, K20*100/J20, 0)), 0) -> 0 | P20: =+N20-O20 -> 0 | Q20: =IFERROR(IF(P20<>0, N20*100/O20, IF(N20=O20, N20*100/O20, 0)), 0) -> 0 | W20: =SUM(R20:V20) -> 0 | X20: =+W20*100/50 -> 0 | Y20: =+(Q20+M20+X20)/3 -> 0
A21: PROG | B21: MEAL | C21: Tecn-Prog-EV-3 | I21: Organizar evento de socialización de resultados de Dx.situacional EV-3 | L21: =+J21-K21 -> 0 | M21: =IFERROR(IF(7<>0, K21*100/J21, IF(J21=K21, K21*100/J21, 0)), 0) -> 0 | P21: =+N21-O21 -> 0 | Q21: =IFERROR(IF(P21<>0, N21*100/O21, IF(N21=O21, N21*100/O21, 0)), 0) -> 0 | W21: =SUM(R21:V21) -> 0 | X21: =+W21*100/50 -> 0 | Y21: =+(Q21+M21+X21)/3 -> 0
A22: PROG | B22: MEAL | C22: Lider-Prog-EV1 | I22: Desarrollar evento de socialización de resultados de Dx.situacional EV-1 | L22: =+J22-K22 -> 0 | M22: =IFERROR(IF(7<>0, K22*100/J22, IF(J22=K22, K22*100/J22, 0)), 0) -> 0 | P22: =+N22-O22 -> 0 | Q22: =IFERROR(IF(P22<>0, N22*100/O22, IF(N22=O22, N22*100/O22, 0)), 0) -> 0 | W22: =SUM(R22:V22) -> 0 | X22: =+W22*100/50 -> 0 | Y22: =+(Q22+M22+X22)/3 -> 0
A23: PROG | B23: MEAL | C23: Lider-Prog-EV2 | I23: Desarrollar evento de socialización de resultados de Dx.situacional EV-2 | L23: =+J23-K23 -> 0 | M23: =IFERROR(IF(7<>0, K23*100/J23, IF(J23=K23, K23*100/J23, 0)), 0) -> 0 | P23: =+N23-O23 -> 0 | Q23: =IFERROR(IF(P23<>0, N23*100/O23, IF(N23=O23, N23*100/O23, 0)), 0) -> 0 | W23: =SUM(R23:V23) -> 0 | X23: =+W23*100/50 -> 0 | Y23: =+(Q23+M23+X23)/3 -> 0
A24: PROG | B24: MEAL | C24: Lider-Prog-EV3 | I24: Desarrollar evento de socialización de resultados de Dx.situacional EV-3 | L24: =+J24-K24 -> 0 | M24: =IFERROR(IF(7<>0, K24*100/J24, IF(J24=K24, K24*100/J24, 0)), 0) -> 0 | P24: =+N24-O24 -> 0 | Q24: =IFERROR(IF(P24<>0, N24*100/O24, IF(N24=O24, N24*100/O24, 0)), 0) -> 0 | W24: =SUM(R24:V24) -> 0 | X24: =+W24*100/50 -> 0 | Y24: =+(Q24+M24+X24)/3 -> 0
A25: PROG | C25: Lider-Prog-EV1 | I25: Buscar y representar a AH en alianzas de coordinacion con socios Proy-EV-1 | L25: =+J25-K25 -> 0 | M25: =IFERROR(IF(7<>0, K25*100/J25, IF(J25=K25, K25*100/J25, 0)), 0) -> 0 | P25: =+N25-O25 -> 0 | Q25: =IFERROR(IF(P25<>0, N25*100/O25, IF(N25=O25, N25*100/O25, 0)), 0) -> 0 | W25: =SUM(R25:V25) -> 0 | X25: =+W25*100/50 -> 0 | Y25: =+(Q25+M25+X25)/3 -> 0
A26: PROG | C26: Lider-Prog-EV2 | I26: Buscar y representar a AH en alianzas de coordinacion con socios Proy-EV-2 | L26: =+J26-K26 -> 0 | M26: =IFERROR(IF(7<>0, K26*100/J26, IF(J26=K26, K26*100/J26, 0)), 0) -> 0 | P26: =+N26-O26 -> 0 | Q26: =IFERROR(IF(P26<>0, N26*100/O26, IF(N26=O26, N26*100/O26, 0)), 0) -> 0 | W26: =SUM(R26:V26) -> 0 | X26: =+W26*100/50 -> 0 | Y26: =+(Q26+M26+X26)/3 -> 0
A27: PROG | C27: Lider-Prog-EV3 | I27: Buscar y representar a AH en alianzas de coordinacion con socios Proy-EV-3 | L27: =+J27-K27 -> 0 | M27: =IFERROR(IF(7<>0, K27*100/J27, IF(J27=K27, K27*100/J27, 0)), 0) -> 0 | P27: =+N27-O27 -> 0 | Q27: =IFERROR(IF(P27<>0, N27*100/O27, IF(N27=O27, N27*100/O27, 0)), 0) -> 0 | W27: =SUM(R27:V27) -> 0 | X27: =+W27*100/50 -> 0 | Y27: =+(Q27+M27+X27)/3 -> 0
A28: PROT | C28: Lider-Prot-Incid | I28: Buscar y representar a AH en alianzas de coordinacion con socios Proteccion e Inc | L28: =+J28-K28 -> 0 | M28: =IFERROR(IF(7<>0, K28*100/J28, IF(J28=K28, K28*100/J28, 0)), 0) -> 0 | P28: =+N28-O28 -> 0 | Q28: =IFERROR(IF(P28<>0, N28*100/O28, IF(N28=O28, N28*100/O28, 0)), 0) -> 0 | W28: =SUM(R28:V28) -> 0 | X28: =+W28*100/50 -> 0 | Y28: =+(Q28+M28+X28)/3 -> 0
A29: PROG | C29: Lider-Prog-EV1 | I29: Definir contenidos y lineamientos para organizar y coordinar red de madres guia | L29: =+J29-K29 -> 0 | M29: =IFERROR(IF(7<>0, K29*100/J29, IF(J29=K29, K29*100/J29, 0)), 0) -> 0 | P29: =+N29-O29 -> 0 | Q29: =IFERROR(IF(P29<>0, N29*100/O29, IF(N29=O29, N29*100/O29, 0)), 0) -> 0 | W29: =SUM(R29:V29) -> 0 | X29: =+W29*100/50 -> 0 | Y29: =+(Q29+M29+X29)/3 -> 0
A30: PROT | C30: Lider-Prot-Incid | I30: Definir contenidos y lineamientos para organizar y coordinar MPBC | L30: =+J30-K30 -> 0 | M30: =IFERROR(IF(7<>0, K30*100/J30, IF(J30=K30, K30*100/J30, 0)), 0) -> 0 | P30: =+N30-O30 -> 0 | Q30: =IFERROR(IF(P30<>0, N30*100/O30, IF(N30=O30, N30*100/O30, 0)), 0) -> 0 | W30: =SUM(R30:V30) -> 0 | X30: =+W30*100/50 -> 0 | Y30: =+(Q30+M30+X30)/3 -> 0
A31: PROG | C31: Lider-Prog-EV2 | I31: Definir contenidos y lineamientos para organizar y coordinar red Educativa | L31: =+J31-K31 -> 0 | M31: =IFERROR(IF(7<>0, K31*100/J31, IF(J31=K31, K31*100/J31, 0)), 0) -> 0 | P31: =+N31-O31 -> 0 | Q31: =IFERROR(IF(P31<>0, N31*100/O31, IF(N31=O31, N31*100/O31, 0)), 0) -> 0 | W31: =SUM(R31:V31) -> 0 | X31: =+W31*100/50 -> 0 | Y31: =+(Q31+M31+X31)/3 -> 0
A32: PROG | C32: Lider-Prog-EV3 | I32: Definir contenidos y lineamientos para organizar y coordinar red de apoyo juvenil | L32: =+J32-K32 -> 0 | M32: =IFERROR(IF(7<>0, K32*100/J32, IF(J32=K32, K32*100/J32, 0)), 0) -> 0 | P32: =+N32-O32 -> 0 | Q32: =IFERROR(IF(P32<>0, N32*100/O32, IF(N32=O32, N32*100/O32, 0)), 0) -> 0 | W32: =SUM(R32:V32) -> 0 | X32: =+W32*100/50 -> 0 | Y32: =+(Q32+M32+X32)/3 -> 0
A33: PROG | C33: Lider-Prog-EV1 | I33: Elaboracion de material didactico para Proy- EV-1, según Branding | L33: =+J33-K33 -> 0 | M33: =IFERROR(IF(7<>0, K33*100/J33, IF(J33=K33, K33*100/J33, 0)), 0) -> 0 | P33: =+N33-O33 -> 0 | Q33: =IFERROR(IF(P33<>0, N33*100/O33, IF(N33=O33, N33*100/O33, 0)), 0) -> 0 | W33: =SUM(R33:V33) -> 0 | X33: =+W33*100/50 -> 0 | Y33: =+(Q33+M33+X33)/3 -> 0
A34: PROG | C34: Lider-Prog-EV2 | I34: Elaboracion de material didactico para Proy- EV-2, según Branding | L34: =+J34-K34 -> 0 | M34: =IFERROR(IF(7<>0, K34*100/J34, IF(J34=K34, K34*100/J34, 0)), 0) -> 0 | P34: =+N34-O34 -> 0 | Q34: =IFERROR(IF(P34<>0, N34*100/O34, IF(N34=O34, N34*100/O34, 0)), 0) -> 0 | W34: =SUM(R34:V34) -> 0 | X34: =+W34*100/50 -> 0 | Y34: =+(Q34+M34+X34)/3 -> 0
A35: PROG | C35: Lider-Prog-EV3 | I35: Elaboracion de material didactico para Proy- EV-3, según Branding | L35: =+J35-K35 -> 0 | M35: =IFERROR(IF(7<>0, K35*100/J35, IF(J35=K35, K35*100/J35, 0)), 0) -> 0 | P35: =+N35-O35 -> 0 | Q35: =IFERROR(IF(P35<>0, N35*100/O35, IF(N35=O35, N35*100/O35, 0)), 0) -> 0 | W35: =SUM(R35:V35) -> 0 | X35: =+W35*100/50 -> 0 | Y35: =+(Q35+M35+X35)/3 -> 0
A36: PROT | C36: Lider-Prot-Incid | I36: Elaboracion de material didactico para Proteccion e Incidencia según Branding | L36: =+J36-K36 -> 0 | M36: =IFERROR(IF(7<>0, K36*100/J36, IF(J36=K36, K36*100/J36, 0)), 0) -> 0 | P36: =+N36-O36 -> 0 | Q36: =IFERROR(IF(P36<>0, N36*100/O36, IF(N36=O36, N36*100/O36, 0)), 0) -> 0 | W36: =SUM(R36:V36) -> 0 | X36: =+W36*100/50 -> 0 | Y36: =+(Q36+M36+X36)/3 -> 0
A37: PROG | C37: Tecn-Prog-EV-1 | I37: Organizar, coordinar y dar asistencia tecnica a Red de madres guía. | J37: 4 | K37: 4 | L37: =+J37-K37 -> 0 | M37: =IFERROR(IF(7<>0, K37*100/J37, IF(J37=K37, K37*100/J37, 0)), 0) -> 100 | N37: 5 | O37: 5 | P37: =+N37-O37 -> 0 | Q37: =IFERROR(IF(P37<>0, N37*100/O37, IF(N37=O37, N37*100/O37, 0)), 0) -> 100 | R37: 8 | S37: 6 | T37: 6 | U37: 8 | V37: 8 | W37: =SUM(R37:V37) -> 36 | X37: =+W37*100/50 -> 72 | Y37: =+(Q37+M37+X37)/3 -> 90.666667
A38: PROT | B38: PROG | C38: Tecn-Prog-EV-1 | I38: Organizar, capacitar y monitorear plan de acción de los MPBC | L38: =+J38-K38 -> 0 | M38: =IFERROR(IF(7<>0, K38*100/J38, IF(J38=K38, K38*100/J38, 0)), 0) -> 0 | P38: =+N38-O38 -> 0 | Q38: =IFERROR(IF(P38<>0, N38*100/O38, IF(N38=O38, N38*100/O38, 0)), 0) -> 0 | W38: =SUM(R38:V38) -> 0 | X38: =+W38*100/50 -> 0 | Y38: =+(Q38+M38+X38)/3 -> 0
A39: PROG | C39: Tecn-Prog-EV-2 | I39: Organizar, coordinar y dar asistencia tecnica a Red Educativa-APF y docente. | L39: =+J39-K39 -> 0 | M39: =IFERROR(IF(7<>0, K39*100/J39, IF(J39=K39, K39*100/J39, 0)), 0) -> 0 | P39: =+N39-O39 -> 0 | Q39: =IFERROR(IF(P39<>0, N39*100/O39, IF(N39=O39, N39*100/O39, 0)), 0) -> 0 | W39: =SUM(R39:V39) -> 0 | X39: =+W39*100/50 -> 0 | Y39: =+(Q39+M39+X39)/3 -> 0
A40: PROG | C40: Tecn-Prog-EV-3 | I40: Organizar, coordinar y dar asistencia tecnica a Red de Apoyo Juvenil | L40: =+J40-K40 -> 0 | M40: =IFERROR(IF(7<>0, K40*100/J40, IF(J40=K40, K40*100/J40, 0)), 0) -> 0 | P40: =+N40-O40 -> 0 | Q40: =IFERROR(IF(P40<>0, N40*100/O40, IF(N40=O40, N40*100/O40, 0)), 0) -> 0 | W40: =SUM(R40:V40) -> 0 | X40: =+W40*100/50 -> 0 | Y40: =+(Q40+M40+X40)/3 -> 0
A41: PROG | B41: RRHH | C41: Lider-Prog-EV1 | I41: Diseñar e implementar plan de formacion virtual-presencial para ET y red en EV-1 | L41: =+J41-K41 -> 0 | M41: =IFERROR(IF(7<>0, K41*100/J41, IF(J41=K41, K41*100/J41, 0)), 0) -> 0 | P41: =+N41-O41 -> 0 | Q41: =IFERROR(IF(P41<>0, N41*100/O41, IF(N41=O41, N41*100/O41, 0)), 0) -> 0 | W41: =SUM(R41:V41) -> 0 | X41: =+W41*100/50 -> 0 | Y41: =+(Q41+M41+X41)/3 -> 0
A42: PROT | C42: Lider-Prot-Incid | I42: Diseñar e implementar plan de formacion virtual-presencial para ET y MPBC | L42: =+J42-K42 -> 0 | M42: =IFERROR(IF(7<>0, K42*100/J42, IF(J42=K42, K42*100/J42, 0)), 0) -> 0 | P42: =+N42-O42 -> 0 | Q42: =IFERROR(IF(P42<>0, N42*100/O42, IF(N42=O42, N42*100/O42, 0)), 0) -> 0 | W42: =SUM(R42:V42) -> 0 | X42: =+W42*100/50 -> 0 | Y42: =+(Q42+M42+X42)/3 -> 0
A43: PROG | B43: RRHH | C43: Lider-Prog-EV2 | I43: Diseñar e implementar plan de formacion virtual-presencial para ET y Red en EV-2 | L43: =+J43-K43 -> 0 | M43: =IFERROR(IF(7<>0, K43*100/J43, IF(J43=K43, K43*100/J43, 0)), 0) -> 0 | P43: =+N43-O43 -> 0 | Q43: =IFERROR(IF(P43<>0, N43*100/O43, IF(N43=O43, N43*100/O43, 0)), 0) -> 0 | W43: =SUM(R43:V43) -> 0 | X43: =+W43*100/50 -> 0 | Y43: =+(Q43+M43+X43)/3 -> 0
A44: PROG | B44: RRHH | C44: Lider-Prog-EV3 | I44: Diseñar e implementar plan de formacion virtual-presencial para ET y Red en EV-3 | L44: =+J44-K44 -> 0 | M44: =IFERROR(IF(7<>0, K44*100/J44, IF(J44=K44, K44*100/J44, 0)), 0) -> 0 | P44: =+N44-O44 -> 0 | Q44: =IFERROR(IF(P44<>0, N44*100/O44, IF(N44=O44, N44*100/O44, 0)), 0) -> 0 | W44: =SUM(R44:V44) -> 0 | X44: =+W44*100/50 -> 0 | Y44: =+(Q44+M44+X44)/3 -> 0
A45: COMU | B45: PROG | C45: PF-Comunicac | I45: Diseñar e implementar plan de formacion virtual-presencial en Comunicaciones | L45: =+J45-K45 -> 0 | M45: =IFERROR(IF(7<>0, K45*100/J45, IF(J45=K45, K45*100/J45, 0)), 0) -> 0 | P45: =+N45-O45 -> 0 | Q45: =IFERROR(IF(P45<>0, N45*100/O45, IF(N45=O45, N45*100/O45, 0)), 0) -> 0 | W45: =SUM(R45:V45) -> 0 | X45: =+W45*100/50 -> 0 | Y45: =+(Q45+M45+X45)/3 -> 0
A46: RRHH | B46: PROG | C46: Tecn-Prog-EV-1 | I46: Completar proceso de capacitación EV-1 virtual-presencial | L46: =+J46-K46 -> 0 | M46: =IFERROR(IF(7<>0, K46*100/J46, IF(J46=K46, K46*100/J46, 0)), 0) -> 0 | P46: =+N46-O46 -> 0 | Q46: =IFERROR(IF(P46<>0, N46*100/O46, IF(N46=O46, N46*100/O46, 0)), 0) -> 0 | W46: =SUM(R46:V46) -> 0 | X46: =+W46*100/50 -> 0 | Y46: =+(Q46+M46+X46)/3 -> 0
A47: RRHH | B47: PROG | C47: Tecn-Prog-EV-2 | I47: Completar proceso de capacitación EV-2 institucional virtual-presencial | L47: =+J47-K47 -> 0 | M47: =IFERROR(IF(7<>0, K47*100/J47, IF(J47=K47, K47*100/J47, 0)), 0) -> 0 | P47: =+N47-O47 -> 0 | Q47: =IFERROR(IF(P47<>0, N47*100/O47, IF(N47=O47, N47*100/O47, 0)), 0) -> 0 | W47: =SUM(R47:V47) -> 0 | X47: =+W47*100/50 -> 0 | Y47: =+(Q47+M47+X47)/3 -> 0
A48: RRHH | B48: PROG | C48: Tecn-Prog-EV-3 | I48: Completar proceso de capacitación EV-3 institucional virtual-presencial | L48: =+J48-K48 -> 0 | M48: =IFERROR(IF(7<>0, K48*100/J48, IF(J48=K48, K48*100/J48, 0)), 0) -> 0 | P48: =+N48-O48 -> 0 | Q48: =IFERROR(IF(P48<>0, N48*100/O48, IF(N48=O48, N48*100/O48, 0)), 0) -> 0 | W48: =SUM(R48:V48) -> 0 | X48: =+W48*100/50 -> 0 | Y48: =+(Q48+M48+X48)/3 -> 0
A49: PROG | C49: Lider-Prog-EV1 | I49: Desarrollar y promover CAP en Red de madres guía | J49: 60 | K49: 55 | L49: =+J49-K49 -> 5 | M49: =IFERROR(IF(7<>0, K49*100/J49, IF(J49=K49, K49*100/J49, 0)), 0) -> 91.666667 | N49: 5 | O49: 7 | P49: =+N49-O49 -> -2 | Q49: =IFERROR(IF(P49<>0, N49*100/O49, IF(N49=O49, N49*100/O49, 0)), 0) -> 71.428571 | R49: 7 | S49: 4 | T49: 2 | U49: 6 | V49: 5 | W49: =SUM(R49:V49) -> 24 | X49: =+W49*100/50 -> 48 | Y49: =+(Q49+M49+X49)/3 -> 70.365079
A50: PROT | C50: Lider-Prot-Incid | I50: Desarrollar y promover CAP en lideres de MPBC | L50: =+J50-K50 -> 0 | M50: =IFERROR(IF(7<>0, K50*100/J50, IF(J50=K50, K50*100/J50, 0)), 0) -> 0 | P50: =+N50-O50 -> 0 | Q50: =IFERROR(IF(P50<>0, N50*100/O50, IF(N50=O50, N50*100/O50, 0)), 0) -> 0 | W50: =SUM(R50:V50) -> 0 | X50: =+W50*100/50 -> 0 | Y50: =+(Q50+M50+X50)/3 -> 0
A51: PROG | C51: Lider-Prog-EV2 | I51: Desarrollar y promover CAP en Red Educativa-APF y docentes | L51: =+J51-K51 -> 0 | M51: =IFERROR(IF(7<>0, K51*100/J51, IF(J51=K51, K51*100/J51, 0)), 0) -> 0 | P51: =+N51-O51 -> 0 | Q51: =IFERROR(IF(P51<>0, N51*100/O51, IF(N51=O51, N51*100/O51, 0)), 0) -> 0 | W51: =SUM(R51:V51) -> 0 | X51: =+W51*100/50 -> 0 | Y51: =+(Q51+M51+X51)/3 -> 0
A52: PROG | C52: Lider-Prog-EV3 | I52: Desarrollar y promover CAP en Red de apoyo juvenil | L52: =+J52-K52 -> 0 | M52: =IFERROR(IF(7<>0, K52*100/J52, IF(J52=K52, K52*100/J52, 0)), 0) -> 0 | P52: =+N52-O52 -> 0 | Q52: =IFERROR(IF(P52<>0, N52*100/O52, IF(N52=O52, N52*100/O52, 0)), 0) -> 0 | W52: =SUM(R52:V52) -> 0 | X52: =+W52*100/50 -> 0 | Y52: =+(Q52+M52+X52)/3 -> 0
A53: PROT | C53: Lider-Prot-Incid | I53: Facilitar proceso de formacion sobre politicas de proteccion y salvaguarda | L53: =+J53-K53 -> 0 | M53: =IFERROR(IF(7<>0, K53*100/J53, IF(J53=K53, K53*100/J53, 0)), 0) -> 0 | P53: =+N53-O53 -> 0 | Q53: =IFERROR(IF(P53<>0, N53*100/O53, IF(N53=O53, N53*100/O53, 0)), 0) -> 0 | W53: =SUM(R53:V53) -> 0 | X53: =+W53*100/50 -> 0 | Y53: =+(Q53+M53+X53)/3 -> 0
A54: PROT | C54: Equipo Tecnico | I54: Completar capacitacion y firma de politica de proteccion y salvaguarda de NNAJ | L54: =+J54-K54 -> 0 | M54: =IFERROR(IF(7<>0, K54*100/J54, IF(J54=K54, K54*100/J54, 0)), 0) -> 0 | P54: =+N54-O54 -> 0 | Q54: =IFERROR(IF(P54<>0, N54*100/O54, IF(N54=O54, N54*100/O54, 0)), 0) -> 0 | W54: =SUM(R54:V54) -> 0 | X54: =+W54*100/50 -> 0 | Y54: =+(Q54+M54+X54)/3 -> 0
A55: PROT | B55: PROG | C55: Lider-Prog-EV1 | I55: Actualizar y firmar acuerdos y politicas de proteccion y salvaguarda con lideres EV-1 | L55: =+J55-K55 -> 0 | M55: =IFERROR(IF(7<>0, K55*100/J55, IF(J55=K55, K55*100/J55, 0)), 0) -> 0 | P55: =+N55-O55 -> 0 | Q55: =IFERROR(IF(P55<>0, N55*100/O55, IF(N55=O55, N55*100/O55, 0)), 0) -> 0 | W55: =SUM(R55:V55) -> 0 | X55: =+W55*100/50 -> 0 | Y55: =+(Q55+M55+X55)/3 -> 0
A56: PROT | B56: PROG | C56: Lider-Prog-EV2 | I56: Actualizar y firmar acuerdos y politicas de proteccion y salvaguarda a docentes EV-2 | L56: =+J56-K56 -> 0 | M56: =IFERROR(IF(7<>0, K56*100/J56, IF(J56=K56, K56*100/J56, 0)), 0) -> 0 | P56: =+N56-O56 -> 0 | Q56: =IFERROR(IF(P56<>0, N56*100/O56, IF(N56=O56, N56*100/O56, 0)), 0) -> 0 | W56: =SUM(R56:V56) -> 0 | X56: =+W56*100/50 -> 0 | Y56: =+(Q56+M56+X56)/3 -> 0
A57: PROT | B57: PROG | C57: Lider-Prog-EV3 | I57: Actualizar y firmar acuerdos y politicas de proteccion y salvaguarda con lideres EV-3 | L57: =+J57-K57 -> 0 | M57: =IFERROR(IF(7<>0, K57*100/J57, IF(J57=K57, K57*100/J57, 0)), 0) -> 0 | P57: =+N57-O57 -> 0 | Q57: =IFERROR(IF(P57<>0, N57*100/O57, IF(N57=O57, N57*100/O57, 0)), 0) -> 0 | W57: =SUM(R57:V57) -> 0 | X57: =+W57*100/50 -> 0 | Y57: =+(Q57+M57+X57)/3 -> 0
A58: PROT | C58: Lider-Prot-Incid | I58: Actualizar y firmar acuerdos y politicas de proteccion y salvaguarda con MPBC | L58: =+J58-K58 -> 0 | M58: =IFERROR(IF(7<>0, K58*100/J58, IF(J58=K58, K58*100/J58, 0)), 0) -> 0 | P58: =+N58-O58 -> 0 | Q58: =IFERROR(IF(P58<>0, N58*100/O58, IF(N58=O58, N58*100/O58, 0)), 0) -> 0 | W58: =SUM(R58:V58) -> 0 | X58: =+W58*100/50 -> 0 | Y58: =+(Q58+M58+X58)/3 -> 0
A59: PROT | B59: MEAL | C59: Lider MEAL | I59: Actualizar y firmar acuerdos y politicas de proteccion y salvaguarda con apoyos | L59: =+J59-K59 -> 0 | M59: =IFERROR(IF(7<>0, K59*100/J59, IF(J59=K59, K59*100/J59, 0)), 0) -> 0 | P59: =+N59-O59 -> 0 | Q59: =IFERROR(IF(P59<>0, N59*100/O59, IF(N59=O59, N59*100/O59, 0)), 0) -> 0 | W59: =SUM(R59:V59) -> 0 | X59: =+W59*100/50 -> 0 | Y59: =+(Q59+M59+X59)/3 -> 0
A60: PROT | B60: PATR | C60: Lider-Patrocinio | I60: Actualizar y firmar acuerdos y politicas de proteccion y salvaguarda con apoyos | L60: =+J60-K60 -> 0 | M60: =IFERROR(IF(7<>0, K60*100/J60, IF(J60=K60, K60*100/J60, 0)), 0) -> 0 | P60: =+N60-O60 -> 0 | Q60: =IFERROR(IF(P60<>0, N60*100/O60, IF(N60=O60, N60*100/O60, 0)), 0) -> 0 | W60: =SUM(R60:V60) -> 0 | X60: =+W60*100/50 -> 0 | Y60: =+(Q60+M60+X60)/3 -> 0
A61: PROT | B61: ADM | C61: Lider Adm-RRHH | I61: Actualizar y firmar acuerdos y politicas de proteccion y salvaguarda con apoyos | L61: =+J61-K61 -> 0 | M61: =IFERROR(IF(7<>0, K61*100/J61, IF(J61=K61, K61*100/J61, 0)), 0) -> 0 | P61: =+N61-O61 -> 0 | Q61: =IFERROR(IF(P61<>0, N61*100/O61, IF(N61=O61, N61*100/O61, 0)), 0) -> 0 | W61: =SUM(R61:V61) -> 0 | X61: =+W61*100/50 -> 0 | Y61: =+(Q61+M61+X61)/3 -> 0
A62: PROG | C62: Tecn-Prog-EV-1 | I62: Implementar metodologías y acciones con grupos meta en Centros ADN | L62: =+J62-K62 -> 0 | M62: =IFERROR(IF(7<>0, K62*100/J62, IF(J62=K62, K62*100/J62, 0)), 0) -> 0 | P62: =+N62-O62 -> 0 | Q62: =IFERROR(IF(P62<>0, N62*100/O62, IF(N62=O62, N62*100/O62, 0)), 0) -> 0 | W62: =SUM(R62:V62) -> 0 | X62: =+W62*100/50 -> 0 | Y62: =+(Q62+M62+X62)/3 -> 0
A63: PROG | C63: Tecn-Prog-EV-2 | I63: Implementar metodologías y acciones con grupos meta en Centros Educativos | L63: =+J63-K63 -> 0 | M63: =IFERROR(IF(7<>0, K63*100/J63, IF(J63=K63, K63*100/J63, 0)), 0) -> 0 | P63: =+N63-O63 -> 0 | Q63: =IFERROR(IF(P63<>0, N63*100/O63, IF(N63=O63, N63*100/O63, 0)), 0) -> 0 | W63: =SUM(R63:V63) -> 0 | X63: =+W63*100/50 -> 0 | Y63: =+(Q63+M63+X63)/3 -> 0
A64: PROG | C64: Tecn-Prog-EV-3 | I64: Acompañar el desarrollo de plan de vida y formación en liderazgo a AJ | L64: =+J64-K64 -> 0 | M64: =IFERROR(IF(7<>0, K64*100/J64, IF(J64=K64, K64*100/J64, 0)), 0) -> 0 | P64: =+N64-O64 -> 0 | Q64: =IFERROR(IF(P64<>0, N64*100/O64, IF(N64=O64, N64*100/O64, 0)), 0) -> 0 | W64: =SUM(R64:V64) -> 0 | X64: =+W64*100/50 -> 0 | Y64: =+(Q64+M64+X64)/3 -> 0
A65: PROG | B65: PROT | C65: Lider-Prog-EV1 | I65: Diseñar Guion Metodologico y protocolo para desarrollo de Feria EV-1 y Proteccion | L65: =+J65-K65 -> 0 | M65: =IFERROR(IF(7<>0, K65*100/J65, IF(J65=K65, K65*100/J65, 0)), 0) -> 0 | P65: =+N65-O65 -> 0 | Q65: =IFERROR(IF(P65<>0, N65*100/O65, IF(N65=O65, N65*100/O65, 0)), 0) -> 0 | W65: =SUM(R65:V65) -> 0 | X65: =+W65*100/50 -> 0 | Y65: =+(Q65+M65+X65)/3 -> 0
A66: PROG | B66: PROT | C66: Lider-Prog-EV2 | I66: Diseñar Guion Metodologico y protocolo para desarrollo de Feria EV-2 y Proteccion | L66: =+J66-K66 -> 0 | M66: =IFERROR(IF(7<>0, K66*100/J66, IF(J66=K66, K66*100/J66, 0)), 0) -> 0 | P66: =+N66-O66 -> 0 | Q66: =IFERROR(IF(P66<>0, N66*100/O66, IF(N66=O66, N66*100/O66, 0)), 0) -> 0 | W66: =SUM(R66:V66) -> 0 | X66: =+W66*100/50 -> 0 | Y66: =+(Q66+M66+X66)/3 -> 0
A67: PROG | B67: PROT | C67: Lider-Prog-EV3 | I67: Diseñar Guion Metodologico y protocolo para Encuentros Juveniles y Proteccion | L67: =+J67-K67 -> 0 | M67: =IFERROR(IF(7<>0, K67*100/J67, IF(J67=K67, K67*100/J67, 0)), 0) -> 0 | P67: =+N67-O67 -> 0 | Q67: =IFERROR(IF(P67<>0, N67*100/O67, IF(N67=O67, N67*100/O67, 0)), 0) -> 0 | W67: =SUM(R67:V67) -> 0 | X67: =+W67*100/50 -> 0 | Y67: =+(Q67+M67+X67)/3 -> 0
A68: PROG | B68: PROT | C68: Tecn-Prog-EV-1 | I68: Organizar e implementar en centros ADN, feria promocional de DDNN en EV-1 | L68: =+J68-K68 -> 0 | M68: =IFERROR(IF(7<>0, K68*100/J68, IF(J68=K68, K68*100/J68, 0)), 0) -> 0 | P68: =+N68-O68 -> 0 | Q68: =IFERROR(IF(P68<>0, N68*100/O68, IF(N68=O68, N68*100/O68, 0)), 0) -> 0 | W68: =SUM(R68:V68) -> 0 | X68: =+W68*100/50 -> 0 | Y68: =+(Q68+M68+X68)/3 -> 0
A69: PROG | B69: PROT | C69: Tecn-Prog-EV-2 | I69: Organizar e implementar en Escuelas, feria promocional de DDNN en EV-2 | L69: =+J69-K69 -> 0 | M69: =IFERROR(IF(7<>0, K69*100/J69, IF(J69=K69, K69*100/J69, 0)), 0) -> 0 | P69: =+N69-O69 -> 0 | Q69: =IFERROR(IF(P69<>0, N69*100/O69, IF(N69=O69, N69*100/O69, 0)), 0) -> 0 | W69: =SUM(R69:V69) -> 0 | X69: =+W69*100/50 -> 0 | Y69: =+(Q69+M69+X69)/3 -> 0
A70: PROG | B70: PROT | C70: Tecn-Prog-EV-3 | I70: Organizar e implementar encuentros juveniles EV-3 en la comunidad | L70: =+J70-K70 -> 0 | M70: =IFERROR(IF(7<>0, K70*100/J70, IF(J70=K70, K70*100/J70, 0)), 0) -> 0 | P70: =+N70-O70 -> 0 | Q70: =IFERROR(IF(P70<>0, N70*100/O70, IF(N70=O70, N70*100/O70, 0)), 0) -> 0 | W70: =SUM(R70:V70) -> 0 | X70: =+W70*100/50 -> 0 | Y70: =+(Q70+M70+X70)/3 -> 0
A71: MEAL | B71: PROG | C71: Lider-Prog-EV1 | I71: Realizar visitas de monitoreo y asistencia tecnica a lideres en Proy- EV-1 | L71: =+J71-K71 -> 0 | M71: =IFERROR(IF(7<>0, K71*100/J71, IF(J71=K71, K71*100/J71, 0)), 0) -> 0 | P71: =+N71-O71 -> 0 | Q71: =IFERROR(IF(P71<>0, N71*100/O71, IF(N71=O71, N71*100/O71, 0)), 0) -> 0 | W71: =SUM(R71:V71) -> 0 | X71: =+W71*100/50 -> 0 | Y71: =+(Q71+M71+X71)/3 -> 0
A72: MEAL | B72: PROG | C72: Lider-Prog-EV2 | I72: Realizar visitas de monitoreo y asistencia tecnica a lideres en Proy- EV-2 | L72: =+J72-K72 -> 0 | M72: =IFERROR(IF(7<>0, K72*100/J72, IF(J72=K72, K72*100/J72, 0)), 0) -> 0 | P72: =+N72-O72 -> 0 | Q72: =IFERROR(IF(P72<>0, N72*100/O72, IF(N72=O72, N72*100/O72, 0)), 0) -> 0 | W72: =SUM(R72:V72) -> 0 | X72: =+W72*100/50 -> 0 | Y72: =+(Q72+M72+X72)/3 -> 0
A73: MEAL | B73: PROG | C73: Lider-Prog-EV3 | I73: Realizar visitas de monitoreo y asistencia tecnica a lideres en Proy- EV-3 | L73: =+J73-K73 -> 0 | M73: =IFERROR(IF(7<>0, K73*100/J73, IF(J73=K73, K73*100/J73, 0)), 0) -> 0 | P73: =+N73-O73 -> 0 | Q73: =IFERROR(IF(P73<>0, N73*100/O73, IF(N73=O73, N73*100/O73, 0)), 0) -> 0 | W73: =SUM(R73:V73) -> 0 | X73: =+W73*100/50 -> 0 | Y73: =+(Q73+M73+X73)/3 -> 0
A74: MEAL | B74: PROT | C74: Lider-Prot-Incid | I74: Realizar visitas de monitoreo y asistencia tecnica a lideres en Proteccion | L74: =+J74-K74 -> 0 | M74: =IFERROR(IF(7<>0, K74*100/J74, IF(J74=K74, K74*100/J74, 0)), 0) -> 0 | P74: =+N74-O74 -> 0 | Q74: =IFERROR(IF(P74<>0, N74*100/O74, IF(N74=O74, N74*100/O74, 0)), 0) -> 0 | W74: =SUM(R74:V74) -> 0 | X74: =+W74*100/50 -> 0 | Y74: =+(Q74+M74+X74)/3 -> 0
A75: PROG | B75: PROG | C75: Tecn-Prog-EV-1 | I75: Convocar jardineras de Centros Pre-escolares para socializar acuerdos | L75: =+J75-K75 -> 0 | M75: =IFERROR(IF(7<>0, K75*100/J75, IF(J75=K75, K75*100/J75, 0)), 0) -> 0 | P75: =+N75-O75 -> 0 | Q75: =IFERROR(IF(P75<>0, N75*100/O75, IF(N75=O75, N75*100/O75, 0)), 0) -> 0 | W75: =SUM(R75:V75) -> 0 | X75: =+W75*100/50 -> 0 | Y75: =+(Q75+M75+X75)/3 -> 0
A76: MEAL | C76: Lider MEAL | I76: Diseñar y establecer lineamientos y herramientas para el MEAL | L76: =+J76-K76 -> 0 | M76: =IFERROR(IF(7<>0, K76*100/J76, IF(J76=K76, K76*100/J76, 0)), 0) -> 0 | P76: =+N76-O76 -> 0 | Q76: =IFERROR(IF(P76<>0, N76*100/O76, IF(N76=O76, N76*100/O76, 0)), 0) -> 0 | W76: =SUM(R76:V76) -> 0 | X76: =+W76*100/50 -> 0 | Y76: =+(Q76+M76+X76)/3 -> 0
A77: MEAL | C77: Lider MEAL | I77: Socializar y capacitar a ET sobre uso y aplicación de herramientas de MEAL | L77: =+J77-K77 -> 0 | M77: =IFERROR(IF(7<>0, K77*100/J77, IF(J77=K77, K77*100/J77, 0)), 0) -> 0 | P77: =+N77-O77 -> 0 | Q77: =IFERROR(IF(P77<>0, N77*100/O77, IF(N77=O77, N77*100/O77, 0)), 0) -> 0 | W77: =SUM(R77:V77) -> 0 | X77: =+W77*100/50 -> 0 | Y77: =+(Q77+M77+X77)/3 -> 0
A78: MEAL | B78: PROG | C78: Lider-Prog-EV1 | I78: Socializar y capacitar a Red de Madres guia sobre herramientas de MEAL | L78: =+J78-K78 -> 0 | M78: =IFERROR(IF(7<>0, K78*100/J78, IF(J78=K78, K78*100/J78, 0)), 0) -> 0 | P78: =+N78-O78 -> 0 | Q78: =IFERROR(IF(P78<>0, N78*100/O78, IF(N78=O78, N78*100/O78, 0)), 0) -> 0 | W78: =SUM(R78:V78) -> 0 | X78: =+W78*100/50 -> 0 | Y78: =+(Q78+M78+X78)/3 -> 0
A79: MEAL | B79: PROG | C79: Lider-Prog-EV2 | I79: Socializar y capacitar a Docentes sobre herramientas de MEAL | L79: =+J79-K79 -> 0 | M79: =IFERROR(IF(7<>0, K79*100/J79, IF(J79=K79, K79*100/J79, 0)), 0) -> 0 | P79: =+N79-O79 -> 0 | Q79: =IFERROR(IF(P79<>0, N79*100/O79, IF(N79=O79, N79*100/O79, 0)), 0) -> 0 | W79: =SUM(R79:V79) -> 0 | X79: =+W79*100/50 -> 0 | Y79: =+(Q79+M79+X79)/3 -> 0
A80: MEAL | B80: PROG | C80: Lider-Prog-EV3 | I80: Socializar y capacitar a Red de Apoyo Juvenil sobre herramientas de MEAL | L80: =+J80-K80 -> 0 | M80: =IFERROR(IF(7<>0, K80*100/J80, IF(J80=K80, K80*100/J80, 0)), 0) -> 0 | P80: =+N80-O80 -> 0 | Q80: =IFERROR(IF(P80<>0, N80*100/O80, IF(N80=O80, N80*100/O80, 0)), 0) -> 0 | W80: =SUM(R80:V80) -> 0 | X80: =+W80*100/50 -> 0 | Y80: =+(Q80+M80+X80)/3 -> 0
A81: MEAL | B81: PROG | C81: Tecn-Prog-EV-1 | I81: Entregar herramientas de MEAL digitales y fisicas a Red de madres guia | L81: =+J81-K81 -> 0 | M81: =IFERROR(IF(7<>0, K81*100/J81, IF(J81=K81, K81*100/J81, 0)), 0) -> 0 | P81: =+N81-O81 -> 0 | Q81: =IFERROR(IF(P81<>0, N81*100/O81, IF(N81=O81, N81*100/O81, 0)), 0) -> 0 | W81: =SUM(R81:V81) -> 0 | X81: =+W81*100/50 -> 0 | Y81: =+(Q81+M81+X81)/3 -> 0
A82: MEAL | B82: PROG | C82: Tecn-Prog-EV-2 | I82: Entregar herramientas de MEAL digitales y fisicas a Docentes | L82: =+J82-K82 -> 0 | M82: =IFERROR(IF(7<>0, K82*100/J82, IF(J82=K82, K82*100/J82, 0)), 0) -> 0 | P82: =+N82-O82 -> 0 | Q82: =IFERROR(IF(P82<>0, N82*100/O82, IF(N82=O82, N82*100/O82, 0)), 0) -> 0 | W82: =SUM(R82:V82) -> 0 | X82: =+W82*100/50 -> 0 | Y82: =+(Q82+M82+X82)/3 -> 0
A83: MEAL | B83: PROG | C83: Tecn-Prog-EV-3 | I83: Entregar herramientas de MEAL digitales y fisicas a Red de Apoyo Juvenil | L83: =+J83-K83 -> 0 | M83: =IFERROR(IF(7<>0, K83*100/J83, IF(J83=K83, K83*100/J83, 0)), 0) -> 0 | P83: =+N83-O83 -> 0 | Q83: =IFERROR(IF(P83<>0, N83*100/O83, IF(N83=O83, N83*100/O83, 0)), 0) -> 0 | W83: =SUM(R83:V83) -> 0 | X83: =+W83*100/50 -> 0 | Y83: =+(Q83+M83+X83)/3 -> 0
A84: MEAL | B84: PROG | C84: Tecn-Prog-EV-1 | I84: Recolectar, revisar y subir en linea los medios de verificacion de EV-1 completos | L84: =+J84-K84 -> 0 | M84: =IFERROR(IF(7<>0, K84*100/J84, IF(J84=K84, K84*100/J84, 0)), 0) -> 0 | P84: =+N84-O84 -> 0 | Q84: =IFERROR(IF(P84<>0, N84*100/O84, IF(N84=O84, N84*100/O84, 0)), 0) -> 0 | W84: =SUM(R84:V84) -> 0 | X84: =+W84*100/50 -> 0 | Y84: =+(Q84+M84+X84)/3 -> 0
A85: MEAL | B85: PROG | C85: Tecn-Prog-EV-2 | I85: Recolectar, revisar y subir en linea los medios de verificacion de EV-2 completos | L85: =+J85-K85 -> 0 | M85: =IFERROR(IF(7<>0, K85*100/J85, IF(J85=K85, K85*100/J85, 0)), 0) -> 0 | P85: =+N85-O85 -> 0 | Q85: =IFERROR(IF(P85<>0, N85*100/O85, IF(N85=O85, N85*100/O85, 0)), 0) -> 0 | W85: =SUM(R85:V85) -> 0 | X85: =+W85*100/50 -> 0 | Y85: =+(Q85+M85+X85)/3 -> 0
A86: MEAL | B86: PROG | C86: Tecn-Prog-EV-3 | I86: Recolectar, revisar y subir en linea los medios de verificacion de EV-3 completos | L86: =+J86-K86 -> 0 | M86: =IFERROR(IF(7<>0, K86*100/J86, IF(J86=K86, K86*100/J86, 0)), 0) -> 0 | P86: =+N86-O86 -> 0 | Q86: =IFERROR(IF(P86<>0, N86*100/O86, IF(N86=O86, N86*100/O86, 0)), 0) -> 0 | W86: =SUM(R86:V86) -> 0 | X86: =+W86*100/50 -> 0 | Y86: =+(Q86+M86+X86)/3 -> 0
A87: MEAL | C87: Lider MEAL | I87: Revisar y digitalizar en CAMEL los medios de verificacion en linea | L87: =+J87-K87 -> 0 | M87: =IFERROR(IF(7<>0, K87*100/J87, IF(J87=K87, K87*100/J87, 0)), 0) -> 0 | P87: =+N87-O87 -> 0 | Q87: =IFERROR(IF(P87<>0, N87*100/O87, IF(N87=O87, N87*100/O87, 0)), 0) -> 0 | W87: =SUM(R87:V87) -> 0 | X87: =+W87*100/50 -> 0 | Y87: =+(Q87+M87+X87)/3 -> 0
A88: MEAL | C88: Lider MEAL | I88: Socializar y facilitar a ET lider, herramientas para la elaboracion de informe mensual | L88: =+J88-K88 -> 0 | M88: =IFERROR(IF(7<>0, K88*100/J88, IF(J88=K88, K88*100/J88, 0)), 0) -> 0 | P88: =+N88-O88 -> 0 | Q88: =IFERROR(IF(P88<>0, N88*100/O88, IF(N88=O88, N88*100/O88, 0)), 0) -> 0 | W88: =SUM(R88:V88) -> 0 | X88: =+W88*100/50 -> 0 | Y88: =+(Q88+M88+X88)/3 -> 0
A89: MEAL | B89: PROG | C89: Lider-Prog-EV1 | I89: Elaborar informe mensual y analisis de resultados en Proy-EV-1 | L89: =+J89-K89 -> 0 | M89: =IFERROR(IF(7<>0, K89*100/J89, IF(J89=K89, K89*100/J89, 0)), 0) -> 0 | P89: =+N89-O89 -> 0 | Q89: =IFERROR(IF(P89<>0, N89*100/O89, IF(N89=O89, N89*100/O89, 0)), 0) -> 0 | W89: =SUM(R89:V89) -> 0 | X89: =+W89*100/50 -> 0 | Y89: =+(Q89+M89+X89)/3 -> 0
A90: MEAL | B90: PROG | C90: Lider-Prog-EV2 | I90: Elaborar informe mensual y analisis de resultados en Proy-EV-2 | L90: =+J90-K90 -> 0 | M90: =IFERROR(IF(7<>0, K90*100/J90, IF(J90=K90, K90*100/J90, 0)), 0) -> 0 | P90: =+N90-O90 -> 0 | Q90: =IFERROR(IF(P90<>0, N90*100/O90, IF(N90=O90, N90*100/O90, 0)), 0) -> 0 | W90: =SUM(R90:V90) -> 0 | X90: =+W90*100/50 -> 0 | Y90: =+(Q90+M90+X90)/3 -> 0
A91: MEAL | B91: PROG | C91: Lider-Prog-EV3 | I91: Elaborar informe mensual y analisis de resultados en Proy-EV-3 | L91: =+J91-K91 -> 0 | M91: =IFERROR(IF(7<>0, K91*100/J91, IF(J91=K91, K91*100/J91, 0)), 0) -> 0 | P91: =+N91-O91 -> 0 | Q91: =IFERROR(IF(P91<>0, N91*100/O91, IF(N91=O91, N91*100/O91, 0)), 0) -> 0 | W91: =SUM(R91:V91) -> 0 | X91: =+W91*100/50 -> 0 | Y91: =+(Q91+M91+X91)/3 -> 0
A92: MEAL | B92: PROT | C92: Lider-Prot-Incid | I92: Elaborar informe mensual y analisis de resultados en Proteccion e incidencia | L92: =+J92-K92 -> 0 | M92: =IFERROR(IF(7<>0, K92*100/J92, IF(J92=K92, K92*100/J92, 0)), 0) -> 0 | P92: =+N92-O92 -> 0 | Q92: =IFERROR(IF(P92<>0, N92*100/O92, IF(N92=O92, N92*100/O92, 0)), 0) -> 0 | W92: =SUM(R92:V92) -> 0 | X92: =+W92*100/50 -> 0 | Y92: =+(Q92+M92+X92)/3 -> 0
A93: MEAL | B93: PATR | C93: Lider-Patrocinio | I93: Elaborar informe mensual y analisis de resultados en Patrocinio | L93: =+J93-K93 -> 0 | M93: =IFERROR(IF(7<>0, K93*100/J93, IF(J93=K93, K93*100/J93, 0)), 0) -> 0 | P93: =+N93-O93 -> 0 | Q93: =IFERROR(IF(P93<>0, N93*100/O93, IF(N93=O93, N93*100/O93, 0)), 0) -> 0 | W93: =SUM(R93:V93) -> 0 | X93: =+W93*100/50 -> 0 | Y93: =+(Q93+M93+X93)/3 -> 0
A94: MEAL | C94: Lider MEAL | I94: Revisar, consolidar y enviar a OC en tiempo y forma el informe mensual | L94: =+J94-K94 -> 0 | M94: =IFERROR(IF(7<>0, K94*100/J94, IF(J94=K94, K94*100/J94, 0)), 0) -> 0 | P94: =+N94-O94 -> 0 | Q94: =IFERROR(IF(P94<>0, N94*100/O94, IF(N94=O94, N94*100/O94, 0)), 0) -> 0 | W94: =SUM(R94:V94) -> 0 | X94: =+W94*100/50 -> 0 | Y94: =+(Q94+M94+X94)/3 -> 0
A95: MEAL | B95: PROG | C95: Lider MEAL | I95: Liderar la capacitacion y organización para levantamiento de Encuesta Global | L95: =+J95-K95 -> 0 | M95: =IFERROR(IF(7<>0, K95*100/J95, IF(J95=K95, K95*100/J95, 0)), 0) -> 0 | P95: =+N95-O95 -> 0 | Q95: =IFERROR(IF(P95<>0, N95*100/O95, IF(N95=O95, N95*100/O95, 0)), 0) -> 0 | W95: =SUM(R95:V95) -> 0 | X95: =+W95*100/50 -> 0 | Y95: =+(Q95+M95+X95)/3 -> 0
A96: MEAL | C96: Equipo Tecnico | I96: Completar capacitacion y levantamiento de encuesta global según plan de MEAL | L96: =+J96-K96 -> 0 | M96: =IFERROR(IF(7<>0, K96*100/J96, IF(J96=K96, K96*100/J96, 0)), 0) -> 0 | P96: =+N96-O96 -> 0 | Q96: =IFERROR(IF(P96<>0, N96*100/O96, IF(N96=O96, N96*100/O96, 0)), 0) -> 0 | W96: =SUM(R96:V96) -> 0 | X96: =+W96*100/50 -> 0 | Y96: =+(Q96+M96+X96)/3 -> 0
A97: MEAL | C97: Lider MEAL | I97: Asegurar el cumplimiento y envio de encuesta global según lineamientos | L97: =+J97-K97 -> 0 | M97: =IFERROR(IF(7<>0, K97*100/J97, IF(J97=K97, K97*100/J97, 0)), 0) -> 0 | P97: =+N97-O97 -> 0 | Q97: =IFERROR(IF(P97<>0, N97*100/O97, IF(N97=O97, N97*100/O97, 0)), 0) -> 0 | W97: =SUM(R97:V97) -> 0 | X97: =+W97*100/50 -> 0 | Y97: =+(Q97+M97+X97)/3 -> 0
A98: MEAL | C98: Lider MEAL | I98: Elaborar Reporte de alcance anual o conteo de participantes | L98: =+J98-K98 -> 0 | M98: =IFERROR(IF(7<>0, K98*100/J98, IF(J98=K98, K98*100/J98, 0)), 0) -> 0 | P98: =+N98-O98 -> 0 | Q98: =IFERROR(IF(P98<>0, N98*100/O98, IF(N98=O98, N98*100/O98, 0)), 0) -> 0 | W98: =SUM(R98:V98) -> 0 | X98: =+W98*100/50 -> 0 | Y98: =+(Q98+M98+X98)/3 -> 0
A99: MEAL | C99: Lider MEAL | I99: Socializar y facilitar a ET lider, herramientas para la elaboracion de informe anual | L99: =+J99-K99 -> 0 | M99: =IFERROR(IF(7<>0, K99*100/J99, IF(J99=K99, K99*100/J99, 0)), 0) -> 0 | P99: =+N99-O99 -> 0 | Q99: =IFERROR(IF(P99<>0, N99*100/O99, IF(N99=O99, N99*100/O99, 0)), 0) -> 0 | W99: =SUM(R99:V99) -> 0 | X99: =+W99*100/50 -> 0 | Y99: =+(Q99+M99+X99)/3 -> 0
A100: MEAL | B100: PROG | C100: Lider-Prog-EV1 | I100: Elaborar informe anual y analisis de resultados en Proy-EV-1 | L100: =+J100-K100 -> 0 | M100: =IFERROR(IF(7<>0, K100*100/J100, IF(J100=K100, K100*100/J100, 0)), 0) -> 0 | P100: =+N100-O100 -> 0 | Q100: =IFERROR(IF(P100<>0, N100*100/O100, IF(N100=O100, N100*100/O100, 0)), 0) -> 0 | W100: =SUM(R100:V100) -> 0 | X100: =+W100*100/50 -> 0 | Y100: =+(Q100+M100+X100)/3 -> 0
A101: MEAL | B101: PROG | C101: Lider-Prog-EV2 | I101: Elaborar informe anual y analisis de resultados en Proy-EV-2 | L101: =+J101-K101 -> 0 | M101: =IFERROR(IF(7<>0, K101*100/J101, IF(J101=K101, K101*100/J101, 0)), 0) -> 0 | P101: =+N101-O101 -> 0 | Q101: =IFERROR(IF(P101<>0, N101*100/O101, IF(N101=O101, N101*100/O101, 0)), 0) -> 0 | W101: =SUM(R101:V101) -> 0 | X101: =+W101*100/50 -> 0 | Y101: =+(Q101+M101+X101)/3 -> 0
A102: MEAL | B102: PROG | C102: Lider-Prog-EV3 | I102: Elaborar informe anual y analisis de resultados en Proy-EV-3 | L102: =+J102-K102 -> 0 | M102: =IFERROR(IF(7<>0, K102*100/J102, IF(J102=K102, K102*100/J102, 0)), 0) -> 0 | P102: =+N102-O102 -> 0 | Q102: =IFERROR(IF(P102<>0, N102*100/O102, IF(N102=O102, N102*100/O102, 0)), 0) -> 0 | W102: =SUM(R102:V102) -> 0 | X102: =+W102*100/50 -> 0 | Y102: =+(Q102+M102+X102)/3 -> 0
A103: MEAL | B103: PROT | C103: Lider-Prot-Incid | I103: Elaborar informe anual y analisis de resultados en Proteccion e incidencia | L103: =+J103-K103 -> 0 | M103: =IFERROR(IF(7<>0, K103*100/J103, IF(J103=K103, K103*100/J103, 0)), 0) -> 0 | P103: =+N103-O103 -> 0 | Q103: =IFERROR(IF(P103<>0, N103*100/O103, IF(N103=O103, N103*100/O103, 0)), 0) -> 0 | W103: =SUM(R103:V103) -> 0 | X103: =+W103*100/50 -> 0 | Y103: =+(Q103+M103+X103)/3 -> 0
...

Sheet Lista desplegable
A1: Sector | B1: H_Salud | C1: D_Desarrollo_de_la_primera_infancia | D1: U_Educación | E1: R_Protección | F1: L_Medios_de_vida | G1: B_Construyendo_Sostenibilidad | H1: C_Niños_en_crisis | I1: A_Transversal_Incidencia | J1: M_Transversal_Salud_mental | K1: Y_Transversal_Agencia | L1: Z_Administración | M1: X_Patrocinio | N1: ML_Monitoreo | O1: HA_WASH | P1: HB_Nutrición | Q1: HC_Salud_maternoinfantil | R1: HD_Salud_reproductiva | S1: HE__Enfermedad_infecciosa | T1: DA_Cuidado_receptivo | U1: DB_Atención_y_educación_de_la_primera_infancia_en_centros__ECCE | V1: UA_Educación_Holística | W1: UB_Aprendizaje_fundamental | X1: UC_Aprendizaje_socioemocional_(SEL) | Y1: UD_Acceso_y_retención | Z1: RA_Seguridad_en_línea | AA1: RB_Trabajo_infantil | AB1: RC_Prevención_y_respuesta_a_prácticas_nocivas | AC1: RD_Protección_infantil_basada_en_la_comunidad | AD1: LA_Empoderamiento_económico_para_las_familias | AE1: LB_Empoderamiento_económico_para_los_jóvenes | AF1: LC_Seguridad_alimentaria | AG1: BA_Adaptación_climática | AH1: BB_Cuidado_del_medio_ambiente | AI1: BC_Reducción_del_Riesgo_de_Desastres__RRD | AJ1: CA_Niños_desplazados_en_crisis_protegidas | AK1: AA_Incidencia | AL1: MA_Salud_mental_y_apoyo_psicosocial | AM1: YA_Agencia_Infantil_y_Juvenil | AN1: ZA_Gestión_Administrativa | AO1: XA_Gestión_de_Patrocinios | AP1: ML_Monitoreo_y_soporte_técnico_del_programa | AQ1: subsector_code | AR1: subsector_name | AS1: Fuente_de_Financiamiento_ | AT1: Categoría_de_Gastos_ | AU1: type_of_participants | AV1: type_of_activitites | AW1: GFC_Fondo_Global_para_la_Niñez | AX1: GFC | AY1: PMA_Programa_Mundial_de_Alimentos | AZ1: PMA
A2: H_Salud | B2: HA_WASH | C2: DA_Cuidado_receptivo | D2: UA_Educación_Holística | E2: RA_Seguridad_en_línea | F2: LA_Empoderamiento_económico_para_las_familias | G2: BA_Adaptación_climática | H2: CA_Niños_desplazados_en_crisis_protegidas | I2: AA_Incidencia | J2: MA_Salud_mental_y_apoyo_psicosocial | K2: YA_Agencia_Infantil_y_Juvenil | L2: ZA_Gestión_Administrativa | M2: XA_Gestión_de_Patrocinios | N2: ML_Monitoreo_y_soporte_técnico_del_programa | O2: HA011-01_Acceso_a_fuentes_de_agua_potable_segura | P2: HB041-01_Suplementos_nutricionales_para_niños_con_desnutrición_aguda_grave_o_desnutrición_aguda_moderada | Q2: HC061-01_Campañas_de_sensibilización_para_promover_la_prestación_de_servicios_de_salud_y_el_uso_de_profesionales_sanitarios_cualificados | R2: HD091-01_Campañas_de_sensibilización_sobre_la_salud_y_los_derechos_sexuales_y_reproductivos_de_los_jóvenes. | S2: HE121-01_Campañas_de_concienciación_sobre_la_prevención_de_la_malaria_durante_la_temporada_alta | T2: DA141-01_Sesiones_de_capacitación_para_cuidadores_sobre_las_necesidades_y_los_hitos_del_desarrollo_de_la_primera_infancia_en_los_dominios_del_aprendizaje,_la_salud_y_el_bienestar_psicosocial_para_niños_de_0_a_5_años. | U2: DB141-01_Capacitación_para_facilitadores/maestros_del_Centro_ECCE_sobre_las_necesidades,_hitos_y_evaluación_del_desarrollo_de_la_primera_infancia_en_los_dominios_del_aprendizaje,_la_salud_y_el_bienestar_psicosocial. | V2: UA191-01_Maestros_y_facilitadores_capacitados_en_el_currículo_de_Aprendizaje_Socioemocional_(SEL)_y_protección_infantil | W2: UB171-01_Currículos_de_alfabetización_y_aritmética_basados_en_evidencia_identificados_y_adaptados_para_su_uso_en_el_desarrollo_de_currículos_y_materiales | X2: UC191-01_Identificar_y_adaptar_el_contenido_de_aprendizaje_socioemocional_(SEL)_al_contexto_local_y_a_los_grupos_de_edad. | Y2: UD171-01_Rehabilitar_la_infraestructura_escolar_sensible_al_género_y_que_incluya_a_las_personas_con_discapacidad | Z2: RA351-01_Integración_de_actividades_de_aprendizaje_socioemocional_(SEL)_en_entornos_de_aula_relacionados_con_la_promoción_de_la_seguridad_en_línea_para_niños_y_jóvenes | AA2: RB251-01_Proporcionar_habilidades_para_la_vida_apropiadas_para_cada_edad,_alfabetización_financiera_y_capacitación_en_habilidades_vocacionales_integradas_con_habilidades_blandas_y_alfabetización_digital_para_la_transición_de_los_niños_mayores_y_los_jóvenes_al_trabajo_decente. | AB2: RC251-01_Diálogos_comunitarios_para_facilitar_debates_abiertos_con_hombres_y_mujeres_adultos,_ancianos,_líderes_religiosos_y_familias_para_abordar_las_causas_fundamentales_de_las_prácticas_nocivas. | AC2: RD271-01_Sesión_de_concientización_y_taller_de_capacitación_para_niños,_jóvenes,_padres,_líderes_comunitarios_y_voluntarios_sobre_los_derechos_del_niño,_los_principios_de_protección,_la_gestión_de_casos_y_las_vías_de_derivación. | AD2: LA411-01_Transferencia_de_efectivo_para_apoyar_la_compra_de_alimentos_de_los_hogares_con_inseguridad_alimentaria | AE2: LB391-01_Capacitación_modular_en_habilidades_vocacionales,_digitales_y_blandas_(por_ejemplo,_comunicación,_liderazgo,_adaptabilidad) | AF2: LC411-01_Transferencias_de_efectivo_y_vales_para_apoyar_la_compra_de_alimentos_de_hogares_con_inseguridad_alimentaria | AG2: BA441-01_Talleres,_pasantías_y_tutorías_para_que_niños_y_jóvenes_desarrollen_conocimientos_y_habilidades_circulares_verdes_centrándose_en_la_acción_climática,_la_sostenibilidad_y_la_gestión_ambiental. | AH2: BB471-01_Capacitación_de_voluntarios_comunitarios_en_tecnologías_de_energía_renovable_y_de_bajo_consumo_energético_(como_cocinas_de_bajo_consumo_de_combustible_y_otras_fuentes_de_energía_renovable_como_lámparas_solares,_bombas_de_agua_solares,_energía_eólica,_biogás,_energía_hidroeléctrica)_para_reducir_las_emisiones_de_gases_de_efecto_invernadero. | AI2: BC481-01_Talleres_de_evaluación_de_riesgos_y_resiliencia_en_comunidades_objetivo_para_ayudar_en_el_proceso_de_toma_de_decisiones_informadas_sobre_el_riesgo. | AJ2: CA271-01_Planificar_y_mantener_consultas_periódicas_con_las_estructuras_formales_de_protección_infantil_y_migración_(P1.1.1) | AK2: AA501-01_Cabildeo | AL2: MA321-01_Rutinas_estructuradas_y_predecibles_que_integran_actividades_lúdicas,_expresivas_y_socioemocionales_para_promover_la_seguridad_emocional,_la_resiliencia_y_el_desarrollo_cognitivo_y_psicosocial_de_los_niños,_diseñadas_e_implementadas. | AM2: YA231-01_Jóvenes_capacitados_en_liderazgo,_defensa_y_oratoria_para_prepararlos_para_roles_cívicos. | AN2: ZA101-01_Mantenimiento_de_hardware_y_software | AO2: XA101-01_Gestión_de_inscripciones_(incluido_el_análisis) | AP2: MA101-01_Monitoreo_y_seguimiento_continuo | AQ2: HA | AR2: HA_WASH | AS2: 1001-_Patrocinio_ChildFund | AT2: 50101-G.de_personal:Salarios | AU2: Niñez y juventudes | AV2: Formación de Formadores (ToT) | AW2: GFC | AX2: TA214-23-01--Transporte y Alimentacion GFC | AY2: PMA | AZ2: TA213-01-Consultorias-PMA
A3: D_Desarrollo_de_la_primera_infancia | B3: HB_Nutrición | C3: DB_Atención_y_educación_de_la_primera_infancia_en_centros__ECCE | D3: UB_Aprendizaje_fundamental | E3: RB_Trabajo_infantil | F3: LB_Empoderamiento_económico_para_los_jóvenes | G3: BB_Cuidado_del_medio_ambiente | H3: CA_Proteccion_y_respuesta_lideradas _localmente | O3: HA012-01_Esfuerzos_de_promoción_para_promover_el_acceso_a_servicios_de_lavado_y_salud | P3: HB042-01_Rehabilitación_nutricional_comunitaria_para_niños_desnutridos | Q3: HC062-01_Sesiones_de_desarrollo_de_capacidades_para_trabajadores_de_la_salud_y_trabajadores_de_salud_comunitarios_sobre_atención_prenatal,_durante_el_parto_y_posparto | R3: HD092-01_Diálogos_intergeneracionales_sobre_salud_sexual_y_reproductiva_para_padres_y_jóvenes | S3: HE121-02__Talleres_comunitarios_sobre_la_prevención_de_la_malaria_y_el_tratamiento_adecuado_de_la_malaria | T3: DA141-02_Sesión_de_capacitación_para_cuidadores_sobre_cómo_monitorear_el_comportamiento_de_sus_hijos_(de_0_a_5_años)_y_las_habilidades_que_han_adquirido_en_situaciones_cotidianas. | U3: DB141-02_Capacitación_para_facilitadores/maestros_del_Centro_ECCE_sobre_cómo_monitorear_el_comportamiento_de_los_niños_y_las_habilidades_que_han_adquirido_en_situaciones_cotidianas. | V3: UA191-02_Capacitación_de_docentes_sobre_la_incorporación_del_aprendizaje_socioemocional_(SEL)_en_las_lecciones_de_alfabetización_y_aritmética | W3: UB171-02_Libros_de_cuentos_y_materiales_multilingües_para_apoyar_el_aprendizaje_fundamental_desarrollados_y_difundidos_entre_niños_y_adolescentes. | X3: UC191-02_Capacitar_a_docentes_y_facilitadores_en_Aprendizaje_Socioemocional_(SEL)_y_autoprotección | Y3: UD171-02_Defensa_comunitaria_para_la_construcción_y_el_mantenimiento_de_escuelas | Z3: RA351-02_Integración_de_actividades_de_aprendizaje_socioemocional_(SEL)_en_entornos_extracurriculares_relacionados_con_la_promoción_de_la_seguridad_en_línea_para_niños_y_jóvenes | AA3: RB251-02_Capacitar_y_apoyar_a_los_cuidadores_sobre_medios_de_vida_alternativos_para_reducir_la_dependencia_del_trabajo_infantil | AB3: RC251-02_Campañas_de_sensibilización_y_educación_para_jóvenes_y_cuidadores_sobre_las_normas_sociales_que_sustentan_las_prácticas_nocivas_y_las_leyes_nacionales_que_las_prohíben. | AC3: RD271-02_Establecer_y_fortalecer_la_capacidad_de_las_estructuras_formales_e_informales_de_protección_comunitaria_de_la_infancia_(CBCP)_en_materia_de_derechos_del_niño,_principios_de_protección,_gestión_de_casos_y_vías_de_derivación. | AD3: LA412-01_Programa_de_alimentación_escolar | AE3: LB391-02_Sesiones_de_habilidades_para_la_vida_y_planificación_profesional_(incluido_el_desarrollo_y_revisión_de_planes_de_vida) | AF3: LC412-01_Programa_de_alimentación_escolar | AG3: BA441-02_Desarrollo_y_uso_de_módulos_y_aplicaciones_de_aprendizaje_basados_en_dispositivos_móviles_para_el_acceso_continuo_al_conocimiento_entre_niños_y_jóvenes | AH3: BB471-02__Sesiones_de_capacitación_comunitaria_sobre_el_diseño,_la_producción_y_la_instalación/aplicación_de_tecnologías_de_energía_renovable_y_de_bajo_consumo_energético_(como_cocinas_de_bajo_consumo_de_combustible_y_otras_fuentes_de_energía_renovable_como_lámparas_solares,_bombas_de_agua_solares,_energía_eólica,_biogás_e_hidroeléctrica)_para_reducir_las_emisiones_de_gases_de_efecto_invernadero_y_promover_prácticas_energéticas_sostenibles. | AI3: BC481-02_Asistencia_integral_para_salvar_vidas_y_redes_de_seguridad_(incluidos_kits_familiares_de_preparación_para_desastres_personalizados)_durante_y_después_de_la_recuperación_para_las_personas_afectadas_por_desastres:_Asistencia_vital;_albergue,_búsqueda_y_rescate,_asistencia_alimentaria,_agua,_saneamiento_e_higiene_(WASH),_atención_médica,_protección,_salud_mental_y_apoyo_psicosocial._Redes_de_seguridad;_transferencias_de_efectivo,_cupones,_asistencia_alimentaria,_medios_de_vida,_continuidad_educativa,_salud_mental_y_apoyo_psicosocial. | AJ3: CA271-02_Brindar_asistencia_técnica_(ver_definición)_a_los_actores_gubernamentales_en_el_fortalecimiento_del_sistema_de_protección_infantil_(P1.1.2) | AK3: AA501-02_Campaña | AL3: MA321-02_Métodos_de_enseñanza_multisensoriales,_basados_en_el_juego_y_centrados_en_el_alumno_utilizados_por_los_docentes | AM3: YA231-02_Jóvenes_capacitados_sobre_sus_derechos_cívicos,_responsabilidades_y_procesos_democráticos_a_través_de_talleres,_medios_de_comunicación_y_programas_escolares. | AN3: ZA101-02_Servicios_básicos_para_la_implementación_programática | AO3: XA101-02_Gestión_de_información_sobre_niños_matriculados | AP3: MA101-02_Evaluación_de_resultados_de_programas/proyectos | AQ3: HB | AR3: HB_Nutrición | AS3: 1003-_Patrocinio_Local_ChildFund | AT3: 50102-G.de_personal:Beneficio_complem | AU3: Cuidadores | AV3: Actividades locales-Talleres-Formaciones | AX3: TA214-23-02--Material Didactico GFC | AZ3: TA213-02-Incentivo a Voluntarios-PMA
A4: U_Educación | B4: HC_Salud_maternoinfantil | D4: UC_Aprendizaje_socioemocional__SEL | E4: RC_Prevención_y_respuesta_a_prácticas_nocivas | F4: LC_Seguridad_alimentaria | G4: BC_Reducción_del_Riesgo_de_Desastres__RRD | O4: HA021-01_Dotación_de_instalaciones_de_higiene_en_la_comunidad | P4: HB043-01_Monitoreo_del_peso_y_el_crecimiento_y_reporte_de_datos_de_salud_y_nutrición_para_niños_menores_de_6_años | Q4: HC063-01_Kits_esenciales_para_el_parto_y_la_atención_del_recién_nacido_a_los_proveedores_de_atención_médica | R4: HD093-01_Talleres_de_educación_sexual_integral_para_niños_y_niñas | S4: HE122-01_Pruebas_de_diagnóstico_rápido_para_casos_sospechosos_de_malaria | T4: DA151-01_Capacitación_para_cuidadores_sobre_cómo_crear_espacios_seguros_para_el_aprendizaje_en_su_hogar_para_niños_de_0_a_5_años. | U4: DB141-03_Observación_infantil_y_evaluación_del_desarrollo_integradas_en_las_rutinas_diarias_del_centro. | V4: UA191-03__Sesiones_de_coaching_y_aprendizaje_entre_pares_para_docentes_para_reforzar_las_prácticas_de_aprendizaje_socioemocional_(SEL) | W4: UB171-03_Maestros/facilitadores_capacitados_para_crear_materiales_de_enseñanza_y_aprendizaje_de_bajo_costo_y_de_origen_local_para_niños_y_adolescentes | X4: UC191-03_Maestros_y_facilitadores_capacitados_en_el_currículo_de_Aprendizaje_Socioemocional_(SEL)_y_protección_infantil | Y4: UD171-03_Las_comunidades_están_vinculadas_al_financiamiento_y_apoyo_técnico_para_iniciativas_educativas | Z4: RA351-03_Talleres_de_desarrollo_de_capacidades_sobre_habilidades_socioemocionales_relacionadas_con_la_promoción_de_la_seguridad_en_línea_para_niños_y_jóvenes | AA4: RB252-01__Identificación_y_derivación_de_casos_de_trabajo_infantil_(o_abusos_infantiles)_a_los_servicios_de_apoyo_necesarios | AB4: RC252-01_Capacitar_y_equipar_a_legisladores,_agentes_del_orden_y_al_poder_judicial_para_implementar_leyes_sobre_prevención_y_respuesta_a_prácticas_nocivas | AC4: RD272-01_Establecer_sistemas_de_identificación_y_derivación_de_casos,_y_capacitar_a_las_estructuras_de_protección_comunitarias,_a_los_voluntarios_y_líderes_comunitarios_en_el_sistema_de_derivación. | AD4: LA413-01_Distribución_de_alimentos_en_situaciones_de_emergencia | AE4: LB392-01_Cursos_cortos_certificados,_pasantías_estructuradas,_aprendizajes_y_observación_laboral_a_través_de_asociaciones_con_empresas_y_sectores_de_alta_demanda. | AF4: LC413-01_Distribución_de_alimentos_en_situaciones_de_emergencia | AG4: BA441-03_Formación_en_emprendimiento_y_habilidades_vocacionales_para_oportunidades_económicas_verdes,_azules_y_circulares_y_soluciones_basadas_en_la_naturaleza. | AH4: BB471-03_Incentivos_y/o_subsidios_para_que_los_hogares_utilicen_tecnologías/prácticas_de_energía_renovable_y_eficiente_y_sostenible_(como_cocinas_de_bajo_consumo_de_combustible_y_fuentes_de_energía_renovables_como_lámparas_solares,_bombas_de_agua_solares,_biogás,_energía_eólica_e_hidroeléctrica)_para_reducir_las_emisiones_de_gases_de_efecto_invernadero. | AI4: BC482-01_Instalación_de_un_sistema_de_alerta_temprana_basado_en_la_comunidad_para_monitorear_el_desarrollo_de_desastres_(pronosticar_eventos_climáticos_y_meteorológicos_extremos)_en_áreas_de_alto_riesgo. | AJ4: CA271-03_Fortalecer_la_capacidad_profesional_local_para_brindar_servicios_adecuados_de_protección_infantil,_centrados_en_la_gestión_de_casos_y_los_sistemas_de_protección_infantil._(P1.1.3) | AK4: AA501-03_Asociación_y_creación_de_coaliciones | AL4: MA321-03_Maestros_capacitados_en_cuidados_sensibles_al_trauma,_desarrollo_emocional_y_educación_inclusiva | AM4: YA232-01_Participación_de_los_jóvenes_en_el_diseño_e_implementación_de_iniciativas_locales_que_aborden_las_necesidades_de_la_comunidad_(por_ejemplo,_saneamiento,_educación,_acción_climática) | AN4: ZA101-03_Gestión_de_activos_fijos | AO4: XA101-03_Gestión_de_la_desafiliación | AP4: MA101-03_Procesos_de_recopilación_de_datos_de_M&E_(encuesta_global_de_M&E) | AQ4: HC | AR4: HC_Salud_maternoinfantil | AS4: 2001-_Children's_DFCs | AT4: 50103-G.de_personal:imp._de_nomina | AU4: Miembros de la Sociedad Civil | AV4: Actividades, formación-talleres en escuelas/centros | AX4: TA214-23-03--Capacitaciones- GFC | AZ4: TA213-03-Otros Gastos-PMA
A5: R_Protección | B5: HD_Salud_reproductiva | D5: UD_Acceso_y_retención | E5: RD_Protección_infantil_basada_en_la_comunidad | O5: HA031-01_Campañas_de_sensibilización_sobre_higiene_y_saneamiento_en_la_comunidad | P5: HB044-01_Comidas_escolares | Q5: HC071-01_Campañas_de_concienciación_para_promover_el_número_recomendado_de_visitas_prenatales | R5: HD093-02_Talleres_de_educación_sexual_integral_para_padres_y_cuidadores | S5: HE123-01__Suministro_de_mosquiteros_tratados_con_insecticidas_de_larga_duración | T5: DA151-02_Capacitación_para_cuidadores_sobre_cómo_crear_juguetes_hechos_a_mano_y_otros_materiales_de_aprendizaje_en_el_hogar_para_niños_de_0_a_5_años. | U5: DB151-01_Evaluaciones_de_la_calidad_estructural_(las_características_de_los_educadores_y_los_entornos,_como_el_acceso_a_la_formación_y_los_niveles_educativos)_de_los_centros_ECCE | V5: UA191-04_Monitorear_la_integración_del_aprendizaje_socioemocional_(SEL)_a_través_de_observaciones_y_retroalimentación_en_el_aula. | W5: UB172-01_Docentes_capacitados_en_prácticas_instruccionales_y_evaluación_formativa | X5: UC191-04_Capacitación_de_docentes_sobre_la_incorporación_del_aprendizaje_socioemocional_(SEL)_en_las_lecciones_de_alfabetización_y_aritmética | Y5: UD172-01_Actividades_de_promoción_de_programas_de_educación_alternativa_y_actividades_de_enriquecimiento | Z5: RA361-01_Equipar_a_niños_y_jóvenes_con_habilidades_en_tecnologías_de_la_información_y_la_comunicación_(TIC) | AA5: RB253-01_Diálogos_comunitarios_que_involucran_a_padres,_líderes_y_empleadores_sobre_los_daños_del_trabajo_infantil | AB5: RC253-01__Realizar_evaluaciones_de_riesgos_y_denuncia_de_prácticas_nocivas_a_través_de_las_vías_de_derivación_de_protección | AC5: RD281-01_Desarrollar_la_capacidad_de_los_cuidadores_en_materia_de_disciplina_positiva,_comunicación_no_violenta_(positiva),_iniciativas_de_entornos_domésticos_seguros,_desarrollo_infantil_y_para_reconocer_y_responder_a_señales_de_abuso,_negligencia_o_explotación. | AD5: LA414-01_Suministro_de_suministros_(por_ejemplo,_semillas,_fertilizantes,_tracción,_riego,_etc.)_y_capacitación_para_iniciativas_de_huertos_familiares,_aves_de_corral_y_ganado_menor. | AE5: LB401-01_Capacitación_sobre_derechos_laborales,_seguridad_en_el_trabajo_y_prevención_de_la_explotación | AF5: LC414-01_Suministro_de_suministros_(por_ejemplo,_semillas,_fertilizantes,_tracción_con_bueyes,_etc.)_y_capacitación_para_iniciativas_de_huertos_familiares,_aves_de_corral_y_ganado_menor. | AG5: BA442-01_Formación_de_plataformas_dirigidas_por_niños_y_jóvenes,_como_clubes_escolares,_clubes_juveniles,_consejos_juveniles_y_comités_verdes_en_marcos_de_gobernanza_locales,_nacionales_e_internacionales_de_medio_ambiente,_sostenibilidad_y_adaptación_climática. | AH5: BB472-01_Campañas_de_concientización_comunitaria,_talleres_y_sesiones_de_capacitación_sobre_prácticas_sostenibles_de_conservación_del_agua,_como_el_uso_eficiente_del_agua,_la_protección_de_las_fuentes_de_agua,_los_humedales,_la_recolección_de_agua_de_lluvia,_el_reciclaje_de_agua,_etc. | AI5: BC482-02__Servicios_de_información_climática_oportunos_y_basados_en_la_demanda_para_ayudar_en_el_proceso_de_toma_de_decisiones_basadas_en_riesgos:_Servicios_de_información_climática_como_pronósticos_hidrometeorológicos_y_basados_en_impactos_que_incluyen_conocimiento_local_e_indígena_de_(o_información_sobre)_tendencias_e_impactos_climáticos | AJ5: CA272-01_Realizar_sesiones_de_capacitación_para_los_trabajadores_de_primera_línea_(incluido_el_personal_sanitario,_jurídico_y_de_refugios)_sobre_la_identificación_segura_de_problemas_de_protección_infantil,_como_la_trata,_el_abuso,_la_explotación_y_la_negligencia_(P1.2.1) | AK5: AA501-04_Ejecución_de_eventos | AL5: MA322-01_Espacios_seguros_(espacios_amigables_para_los_niños)_creados_en_la_comunidad_para_que_los_cuidadores_y_los_niños_se_reúnan_y_participen_en_actividades_psicosociales_que_incluyen_acciones_grupales_que_adaptan_las_prácticas_de_afrontamiento_locales_y_los_valores_culturales. | AM5: YA233-01_Plataformas_formales_para_jóvenes_(foros_dirigidos_por_jóvenes)_para_abogar_ante_los_responsables_de_políticas,_los_gobiernos_locales,_las_ONG_o_las_instituciones_sobre_políticas_y_cuestiones_que_les_afectan. | AN5: ZA101-04_Salarios_del_personal_administrativo | AO5: XA101-04_Gestión_de_correspondencia | AP5: MA101-04_Salarios_y_beneficios_del_personal_del_programa_(personal_técnico_y_de_implementación) | AQ5: HD | AR5: HD_Salud_reproductiva | AS5: 2002-_DFC_para_Proy./Comm. | AT5: 50104-G.de_personal:_Indemnizacion | AU5: Líderes comunitarios | AV5: Ferias locales o comunitarias | AX5: TA214-23-04--Gastos de Viaje - GFC | AZ5: TA213-04-Salarios y Beneficios-PMA
A6: L_Medios_de_vida | B6: HE__Enfermedad_infecciosa | O6: HA031-02_Campañas_de_sensibilización_sobre_higiene_y_salud_para_niños_en_edad_escolar_y_padres | P6: HB051-01_Talleres_para_padres_sobre_nutrición_y_alimentación_adecuada_para_cuidadores | Q6: HC072-01_Sesiones_de_desarrollo_de_capacidades_para_trabajadores_de_la_salud_y_trabajadores_de_salud_comunitarios_sobre_atención_prenatal,_durante_el_parto_y_posparto | R6: HD094-01_Talleres_sobre_prácticas_pedagógicas_de_educación_sexual_integral_para_educadores | S6: HE124-01_Terapia_de_quimioprevención_de_la_malaria_estacional_durante_la_temporada_de_transmisión | T6: DA151-03_Materiales_de_juego_y_aprendizaje_apropiados_según_la_edad_(para_niños_de_0_a_5_años)_desarrollados_y_distribuidos_para_familias_necesitadas. | U6: DB151-02_Centros_ECCE_que_cumplen_con_estándares_de_calidad_estructural_(por_ejemplo,_las_características_de_los_educadores_y_entornos_como_el_acceso_a_la_capacitación_y_los_niveles_educativos)_abiertos/disponibles_en_las_comunidades. | V6: UA171-01_Docentes_capacitados_en_prácticas_instruccionales_y_evaluación_formativa | W6: UB172-02_Docentes_capacitados_en_metodologías_inclusivas_y_centradas_en_el_niño | X6: UC191-05_Sesiones_de_coaching_y_aprendizaje_entre_pares_para_docentes_para_reforzar_las_prácticas_SEL | Y6: UD172-02_Escuelas_dirigidas_por_la_comunidad_establecidas_en_zonas_marginadas | Z6: RA361-02_Equipar_a_los_docentes_en_el_uso_de_las_tecnologías_de_la_información_y_la_comunicación_(TIC) | AA6: RB254-01_Campañas_de_concientización_sobre_derechos_laborales,_seguridad_en_el_lugar_de_trabajo,_mecanismos_de_denuncia_y_legislación_para_jóvenes,_padres,_cuidadores_y_miembros_de_la_comunidad. | AB6: RC254-01_Defensa_dirigida_por_jóvenes_para_hacer_cumplir_el_desarrollo_y_la_implementación_de_políticas_para_abordar_prácticas_nocivas. | AC6: RD281-02__Difusión_de_mensajes_sobre_prevención_y_protección_contra_la_violencia_dirigidos_a_los_cuidadores | AD6: LA414-02_Capacitación_en_prácticas_agrícolas_sostenibles_(por_ejemplo,_agronomía,_agroecología,_agroforestería,_agricultura_climáticamente_inteligente) | AE6: LB401-02_Campañas_de_concientización_comunitaria_sobre_derechos_laborales_y_empleo_no_explotador | AF6: LC414-02_Capacitación_en_prácticas_agrícolas_sostenibles_(por_ejemplo,_agronomía,_agroecología,_agroforestería,_agricultura_climáticamente_inteligente) | AG6: BA442-02_Inclusión_de_plataformas_lideradas_por_niños_y_jóvenes_en_el_desarrollo_e_implementación_de_planes_de_sostenibilidad,_medio_ambiente,_clima_y_reducción_del_riesgo_de_desastres. | AH6: BB472-02__Esfuerzos_locales_de_conservación_para_implementar_prácticas_sostenibles_de_conservación_del_agua,_como_el_uso_eficiente_del_agua,_la_protección_de_las_fuentes_de_agua,_la_recolección_de_agua_de_lluvia,_la_purificación_de_agua_con_energía_solar,_el_reciclaje_de_agua,_etc. | AI6: BC482-03_Establecimiento_de_sistemas_que_monitoreen_y_evalúen_las_acciones_de_adaptación_de_la_comunidad_a_los_riesgos_de_desastres:_Sistema_que_dé_seguimiento_al_progreso,_identifique_desafíos_y_realice_los_ajustes_necesarios. | AJ6: CA272-02_Desarrollar_y_difundir_vías_de_derivación_fáciles_de_usar_y_procedimientos_operativos_estándar_(POE)_adaptados_a_los_contextos_locales_y_la_dinámica_migratoria_(P1.2.2) | AK6: AA501-05_Análisis_de_políticas_y_presupuestos | AL6: MA323-01_Los_programas_de_educación_ambiental_en_las_escuelas_combinan_la_ciencia_ambiental,_las_prácticas_SEL_(control_emocional,_narración_de_historias_y_desarrollo_de_resiliencia)_y_el_desarrollo_de_resiliencia. | AM6: YA233-02_Espacios_formales_para_que_los_jóvenes_contribuyan_a_los_procesos_de_toma_de_decisiones_a_nivel_comunitario_o_institucional | AN6: ZA101-05_Fortalecimiento_institucional_de_los_socios_locales | AQ6: HE | AR6: HE__Enfermedad_infecciosa | AS6: 2003-_DFCs_locales_para_Children | AT6: 50201-Pago_capacitador-facilitador | AU6: Voluntariados | AV6: Campañas comunitarias | AX6: TA214-23-05--Mejoras Infraestructura- GFC
A7: B_Construyendo_Sostenibilidad | P7: HB052-01_Campañas_de_sensibilización_sobre_la_lactancia_materna_exclusiva_y_la_alimentación_complementaria | Q7: HC073-01_Suplementos_esenciales_para_las_mujeres_durante_el_embarazo_(como_hierro_y_ácido_fólico) | R7: HD095-01_Talleres_para_líderes_comunitarios_en_educación_integral_en_sexualidad,_igualdad_de_género_y_prevención_de_la_violencia_sexual | S7: HE131-01_Monitoreo_regular_de_tuberculosis_activa_e_infección_de_tuberculosis_para_aquellos_en_contacto_con_pacientes_con_tuberculosis | T7: DA201-01_Capacitación_en_cuidado_receptivo_para_cuidadores_de_niños_de_0_a_5_años_a_través_de_sesiones_de_entrega_de_contenido_presenciales_y/o_remotas | U7: DB152-01_Evaluación_de_la_calidad_del_proceso_(la_calidad_de_las_interacciones_y_actividades_que_experimentan_los_niños_mientras_asisten_a_un_entorno_ECCE)_en_los_centros_ECCE | V7: UA171-02_Docentes_capacitados_en_metodologías_inclusivas_y_centradas_en_el_niño | W7: UB172-03_Maestros_y_asociaciones_de_padres_y_maestros_(PTAs)_capacitados_en_enseñanza_inclusiva_y_transformadora_de_género | X7: UC191-06_Sesiones_de_coaching_y_aprendizaje_entre_pares_para_docentes_para_apoyar_la_autoeficacia_de_los_estudiantes | Y7: UD172-03_Asociaciones_de_padres_y_maestros_(PTAs)_y_autoridades_educativas_capacitadas_para_monitorear_la_asistencia_mediante_tecnología | Z7: RA361-03_Capacitación_de_cuidadores_en_habilidades_en_Tecnologías_de_la_Información_y_la_Comunicación_(TIC) | AA7: RB254-02_Campañas_de_concientización_dirigidas_a_empleadores_y_socios_del_sector_privado_sobre_derechos_laborales,_seguridad_en_el_lugar_de_trabajo,_mecanismos_de_denuncia_y_otras_prácticas_laborales_éticas_(prevención_y_respuesta). | AB7: RC271-01_Desarrollar_la_capacidad_de_las_estructuras_de_protección_infantil_comunitarias_(incluidas_las_redes_de_asistentes_jurídicos)_en_materia_de_prevención_de_prácticas_nocivas,_mecanismos_de_denuncia_y_derivación. | AC7: RD281-03_Realizar_sesiones_de_Millas_de_Manos_(MdM)_con_cuidadores | AD7: LA414-03_Sistemas_de_producción_de_alimentos_basados_​​en_la_familia_y_la_comunidad,_como_huertos_compartidos_y_cooperativas | AE7: LB402-01_Asociaciones_con_empleadores_para_pasantías_y_colocaciones_en_el_primer_empleo | AF7: LC414-03_Sistemas_de_producción_de_alimentos_basados_​​en_la_familia_y_la_comunidad,_como_huertos_compartidos_y_cooperativas | AG7: BA443-01_Integración_del_cambio_climático_y_la_educación_ambiental_en_los_programas_escolares,_incluidas_actividades_intracurriculares,_cocurriculares_y_extracurriculares_como_educación_climática_y_ambiental_en_las_asignaturas,_orientación_profesional_sobre_oportunidades_agrícolas,_proyectos_de_ecoarte_y_actividades_sostenibles_como_el_reciclaje_y_la_conservación_de_la_energía,_ecoescuelas_y_plan_de_estudios_de_restauración_de_ecosistemas_para_jóvenes. | AH7: BB472-03_Desarrollo_de_sistemas_de_agua_de_uso_múltiple_(infraestructura)_para_uso_doméstico,_producción_agrícola_y_ganadera:_aprovechamiento_de_aguas_subterráneas,_presas_de_valles,_aguas_superficiales_y_atmosféricas. | AI7: BC483-01_Campañas_de_concientización,_talleres,_sesiones_de_capacitación_para_educar_a_las_comunidades_(involucrando_a_grupos_vulnerables_y_subrepresentados)_sobre_las_causas_del_riesgo_de_desastres,_los_impactos,_los_mitigantes,_las_estrategias_de_afrontamiento,_reducción_de_riesgos_y_respuesta. | AJ7: CA273-01_Realizar_evaluaciones_comunitarias_participativas_para_identificar_las_estructuras_y_brechas_existentes_en_materia_de_protección_infantil_y_las_necesidades_de_protección_infantil_de_la_comunidad_(P1.3.1) | AK7: AA501-06_Empoderando_a_los_jóvenes_defensores | AL7: MA324-01_Se_desarrollaron_y_distribuyeron_materiales_educativos_adaptados_culturalmente_sobre_salud_mental_infantil,_signos_tempranos_de_angustia_y_trauma. | AM7: YA234-01_Espacios_digitales_seguros_y_centros_de_innovación_donde_los_jóvenes_pueden_usar_la_tecnología_para_la_acción_cívica_(como_la_defensa_de_derechos),_la_narración_de_historias_y_el_cambio_social. | AN7: ZA101-06_Reuniones_para_coordinar_actividades_programáticas_y_de_patrocinio | AQ7: DA | AR7: DA_Cuidado_receptivo | AS7: 3001-_Programa_de_No_patrocinio | AT7: 50202-Material_de_capacitacion | AU7: Educadores | AV7: Campañas locales
A8: C_Niños_en_crisis | Q8: HC081-01_Campañas_de_vacunación,_desparasitación_y_salud | R8: HD096-01_Sesiones_de_SSR_en_las_escuelas_a_través_de_docentes | S8: HE132-01__Servicios_de_terapia_preventiva_y_tratamiento_para_pacientes_con_tuberculosis_activa_e_infectados_por_tuberculosis | T8: DA201-02_Talleres_de_crianza_receptiva_para_cuidadores_de_niños_de_0_a_5_años_centrados_en_la_conexión_emocional,_la_comunicación_y_la_estimulación. | U8: DB152-02_Facilitadores_de_ECCE_capacitados_en_el_marco_de_ECCE_adaptado_y_métodos_de_enseñanza_inclusivos | V8: UA172-01_Educación_comunitaria_sobre_el_derecho_a_la_educación_gratuita_y_las_alternativas_disponibles | W8: UB173-01_Oportunidades_de_aprendizaje_correctivo_(por_ejemplo,_tutorías,_campamentos_de_lectura) | X8: UC192-01_Proceso_de_reconocimiento_del_progreso_del_aprendizaje_socioemocional_(SEL)_de_los_estudiantes_establecido_a_través_de_eventos_escolares_y_mecanismos_de_retroalimentación. | Y8: UD173-01_Proceso_de_reconocimiento_de_logros_estudiantiles_establecido_a_través_de_eventos_y_premios_escolares | Z8: RA362-01_Desarrollar_la_resiliencia_para_prevenir,_identificar,_denunciar_y_responder_al_daño_en_línea | AA8: RB255-01_Desarrollo_e_implementación_de_programas_de_reintegración_inclusivos_para_niños_fuera_de_la_escuela_y_niños_trabajadores,_incorporando_atención_psicosocial_y_aprendizaje_personalizado_o_capacitación_en_habilidades. | AB8: RC271-02_Capacitar_y_equipar_a_legisladores,_agentes_del_orden_y_al_poder_judicial_para_implementar_leyes_sobre_prevención_y_respuesta_a_prácticas_nocivas | AC8: RD291-01_Trabajar_con_el_gobierno_para_desarrollar_e_institucionalizar_códigos_de_conducta_de_protección_infantil_para_las_escuelas,_garantizando_la_alineación_con_los_estándares_de_protección_infantil. | AD8: LA421-01_Provisión_de_capital_inicial_y_apoyo_en_especie_(por_ejemplo,_kits_de_herramientas,_ganado,_insumos_agrícolas)_para_micro,_pequeñas_y_medianas_empresas | AE8: LB402-02_Plataformas_de_participación_entre_jóvenes_y_empleadores_para_promover_prácticas_de_contratación_éticas. | AF8: LC421-01__Provisión_de_capital_inicial,_apoyo_en_especie_(por_ejemplo,_kits_de_herramientas,_ganado,_insumos_agrícolas)_y/o_activos_productivos_(por_ejemplo,_semillas,_sistemas_de_riego,_tierras,_plataformas_digitales)_y_vínculos_de_mercado. | AG8: BA443-02_Integración_de_la_agroindustria,_la_agricultura_digital_y_el_desarrollo_de_la_cadena_de_valor_(incluidos_los_certificados_en_agronomía/agricultura_climáticamente_inteligente)_en_los_programas_de_formación_profesional | AH8: BB473-01_Campañas_de_concientización,_talleres_y_sesiones_de_capacitación_sobre_gestión_sostenible_de_residuos_para_reducir_la_generación_de_residuos,_promover_el_reciclaje_y_hacer_cumplir_la_eliminación_adecuada. | AI8: BC484-01_Desarrollo_e_implementación_de_planes/estrategias_de_gestión_del_riesgo_de_desastres_para_la_mitigación,_preparación,_reducción_de_riesgos_y_respuesta_ante_desastres_por_parte_de_las_comunidades_(involucrando_a_grupos_vulnerables_y_subrepresentados):_Los_mitigantes_incluyen_la_evaluación_de_riesgos,_la_zonificación,_los_estándares_de_infraestructura,_las_soluciones_basadas_en_la_naturaleza_y_la_AbE;_la_preparación_incluye_un_sistema_de_alerta_temprana,_concientización,_simulacros/simulaciones,_almacenamiento,_capacitación_y_un_plan_de_respuesta;_la_reducción_de_riesgos_incluye_la_integración_de_la_DRM_en_los_planes_de_desarrollo,_la_CBDRM,_las_redes_de_seguridad_y_los_enfoques_inclusivos;_la_respuesta_incluye_la_búsqueda_y_el_rescate,_las_redes_de_seguridad_y_salvamento,_la_coordinación_de_actores_y_el_intercambio_de_información_en_tiempo_real. | AJ8: CA273-02_Desarrollar_las_capacidades_de_las_comunidades_—incluidos_los_jóvenes_y_los_actores_locales—_para_identificar,_responder_y_remitir_de_forma_segura_las_preocupaciones_sobre_protección_infantil,_al_tiempo_que_se_promueven_soluciones_lideradas_localmente_que_reduzcan_los_riesgos_migratorios_y_apoyen_la_reintegración_(P1.3.2) | AK8: AA501-07_Investigación/generación_de_evidencia_para_respaldar_la_formulación_de_políticas | AL8: MA324-02_Concienciación_y_capacitación_de_estructuras_comunitarias,_cuidadores,_niños_y/o_jóvenes_sobre_salud_mental_y_vías_de_derivación. | AM8: YA235-01_Jóvenes_vinculados_con_mentores_y_compañeros_para_compartir_experiencias,_desarrollar_habilidades_y_fomentar_el_diálogo_intergeneracional. | AQ8: DB | AR8: DB_Atención_y_educación_de_la_primera_infancia_en_centros__ECCE | AS8: 4001-_Donaciones_/_Proyectos_de_subvenciones | AT8: 50203-Capacitacion:Transporte | AU8: Trabajadores formales de la Salud | AV8: Campañas nacionales
A9: A_Transversal_Incidencia | Q9: HC082-01_Taller_sobre_cuidado_cariñoso_con_cuidadores_(salud_infantil,_nutrición_adecuada,_cuidados_receptivos,_oportunidades_para_el_aprendizaje_temprano,_seguridad_y_protección) | R9: HD101-01_Depósitos_de_anticonceptivos_y_otros_materiales_sanitarios_(salud_e_higiene_menstrual,_etc.) | S9: HE133-01__Campañas_de_concienciación_sobre_la_transmisión_de_la_tuberculosis | T9: DA201-03_Grupos_de_aprendizaje_entre_pares_para_cuidadores_de_niños_de_0_a_5_años_para_compartir_experiencias_y_estrategias | U9: DB152-03_Sesiones_de_coaching_y_tutoría_para_el_personal_de_ECCE_sobre_gestión_del_aula_y_enseñanza_receptiva | V9: UA172-02_Campañas_de_concientización_comunitaria_sobre_la_importancia_de_la_educación_infantil/juvenil_y/o_el_derecho_a_la_educación_gratuita_y_las_alternativas_disponibles | W9: UB173-02_Apoyar_a_las_bibliotecas_escolares_y_móviles | X9: UC193-01_Talleres_para_cuidadores_sobre_aprendizaje_socioemocional_(SEL)_y_crianza_positiva | Z9: RA362-02_Identificación_y_derivación_de_casos_de_abuso_en_línea_a_los_servicios_sociales | AA9: RB256-01_Evaluaciones_de_riesgos_y_denuncia_de_explotación_o_abuso_de_jóvenes_trabajadores | AB9: RC272-01__Campañas_de_sensibilización_de_líderes_comunitarios_sobre_prevención_y_respuesta_a_prácticas_nocivas | AC9: RD292-01_Desarrollo_de_capacidades_de_educadores_(maestros)_y_estudiantes_en_el_aprendizaje_socioemocional_(SEL)_y_el_currículo_de_autoprotección | AD9: LA422-01_Capacitación_en_emprendimiento,_incluyendo_planificación_empresarial,_análisis_de_mercado_y_gestión_financiera. | AE9: LB402-03_Realizar_exposiciones_profesionales_y_ferias_móviles_de_habilidades,_generando_conciencia_y_oportunidades_de_inscripción. | AF9: LC422-01__Capacitación_para_jóvenes_en_agronegocios,_desarrollo_de_cadenas_de_valor_y_herramientas_agrícolas_digitales_(incluyendo_planificación_empresarial,_análisis_de_mercado_y_gestión_financiera) | AG9: BA444-01_Capacitación_en_mentoría_y_liderazgo_para_jóvenes_defensores_ambientales_sobre_acción_climática_y_cuidado_del_medio_ambiente. | AH9: BB473-02_Esfuerzos_locales_de_conservación_para_reducir_la_generación_de_residuos,_promover_el_reciclaje_y_garantizar_la_eliminación_adecuada | AI9: BC485-01_Establecimiento_y_capacitación_de_un_equipo_de_respuesta_rápida_ante_desastres_en_gestión_de_riesgos_de_desastres;_mitigantes_(incluida_la_evaluación_de_necesidades_en_situaciones_de_emergencia),_preparación,_reducción_de_riesgos_y_respuestas | AJ9: CA273-03_Facilitar_y_dotar_de_recursos_el_diseño,_la_implementación_y_el_desarrollo_de_iniciativas_de_protección_infantil_lideradas_por_la_comunidad_y_por_refugiados,_incluyendo_el_apoyo_personalizado_para_el_desarrollo_organizacional_y_la_participación_de_niños,_niñas_y_cuidadores._(P1.3.3) | AK9: AA501-08_Movilización_de_jóvenes_y_niños | AL9: MA331-01_Sesiones_de_cuidado_para_la_salud_emocional_de_padres_y_cuidadores | AM9: YA241-01_Foros_inclusivos_formales_donde_los_líderes_comunitarios_y_los_jóvenes_colaboran_para_identificar_preocupaciones_prioritarias_y_diseñar_soluciones_en_conjunto. | AQ9: UA | AR9: UA_Educación_Holística | AS9: 5001-_Contribuciones_de_la_Comunidad | AT9: 50204-Capacitacion:alimentos,_hosped | AU9: Proveedores de salud no certificados | AV9: Teatro debate
A10: M_Transversal_Salud_mental | R10: HD111-01_Encuentros_de_niñas,_niños,_adolescentes_y_jóvenes_para_formular_propuestas_sobre_derechos_sexuales_y_reproductivos | S10: HE133-02_Talleres_comunitarios_sobre_prevención_de_la_tuberculosis_y_tratamiento_adecuado_de_la_tuberculosis | T10: DA201-04_Capacitación_para_estructuras_de_apoyo_comunitario_para_orientar_y_ayudar_a_los_cuidadores_(de_niños_de_0_a_5_años) | U10: DB152-04_Sesiones_de_juego_y_aprendizaje_estructuradas_utilizando_materiales_apropiados_para_el_desarrollo. | V10: UA211-01_Realizar_talleres_para_cuidadores_sobre_aprendizaje_socioemocional_(SEL)_y_crianza_positiva. | W10: UB173-03_Programas_extracurriculares_y_de_recuperación_(por_ejemplo,_tutorías,_clubes) | X10: UC193-02_Aprendizaje_socioemocional_(SEL)_y_mensajes_de_protección_difundidos_a_través_de_medios_y_eventos_comunitarios | Z10: RA371-01_Capacitación_a_cuidadores_sobre_crianza_positiva_y_autoconciencia_sobre_los_riesgos_en_línea | AA10: RB271-01_Fortalecimiento_de_la_capacidad_de_las_estructuras_de_protección_infantil_comunitaria_(CBCP)_en_materia_de_prevención_y_respuesta_al_trabajo_infantil_y_la_explotación_laboral_juvenil | AB10: RC311-01_Asociación_entre_jóvenes,_líderes_comunitarios_y_personas_influyentes_para_defender_prácticas_equitativas_y_tolerancia_cero_hacia_la_violencia_de_género_(VG). | AC10: RD293-01_Crear_y_fortalecer_la_capacidad_de_los_clubes_escolares_en_materia_de_derechos_y_responsabilidades_del_niño,_principios_de_protección,_gestión_de_casos_y_derivación_para_promover_iniciativas_y_actividades_de_defensa_dirigidas_por_niños_y_jóvenes. | AD10: LA422-02_Capacitación_comunitaria_sobre_transformación_de_la_producción_orgánica | AE10: LB403-01_Promoción_por_parte_de_líderes_locales_y_jóvenes_ante_el_gobierno_para_promulgar_e_implementar_políticas_que_aborden_el_trabajo_explotador_y_el_desempleo_de_los_jóvenes. | AF10: LC422-02_Mentoría_y_coaching_para_agronegocios,_desarrollo_de_cadenas_de_valor_y_herramientas_agrícolas_digitales | AG10: BA444-02_Desarrollo_de_materiales_de_promoción_centrados_en_niños_y_jóvenes_con_OSC,_socios_implementadores_y_niños_y_jóvenes_para_influir_en_las_políticas_gubernamentales_sobre_medio_ambiente_y/o_cambio_climático. | AH10: BB474-01_Campañas_de_concientización,_talleres_y_sesiones_de_capacitación_sobre_soluciones_basadas_en_la_naturaleza,_como_la_conservación,_gestión_y_restauración_de_bosques,_manglares,_turberas_y_ecosistemas_con_alto_contenido_de_carbono. | AI10: BC485-02_Campañas_de_concientización_y_talleres_de_capacitación_para_líderes_locales_y_personal_de_respuesta_a_emergencias_sobre_gestión_del_riesgo_de_desastres;_causas_del_riesgo_de_desastres,_impactos,_mitigantes,_afrontamiento,_reducción_de_riesgos_y_estrategias_de_respuesta. | AJ10: CA281-01_Realizar_consultas_participativas_con_niños_y_jóvenes_para_captar_sus_opiniones_para_establecer/mejorar_espacios_seguros_(P2.1.1) | AK10: AA501-09_Movilización_comunitaria | AL10: MA331-02_Talleres_grupales_de_apoyo_psicosocial_y_manejo_del_estrés_para_cuidadores | AM10: YA242-01_Talleres_de_sensibilización_comunitaria_sobre_la_importancia_de_la_participación_de_los_jóvenes | AQ10: UB | AR10: UB_Aprendizaje_fundamental | AS10: 6001-_Financiación_del_gobierno/departamento_local. | AT10: 50205-Capacitacion:Instalaciones | AU10: Miembros del Sector Privado | AV10: Foros
A11: Y_Transversal_Agencia | C11: MODELO 1 | D11: 0 | E11: Personal | R11: HD112-01_Jornada_clínica_amigable_para_adolescentes_en_centros_de_salud_primarios_o_centros_de_salud_comunitarios | T11: DA202-01_Visitas_domiciliarias_para_evaluar_necesidades,_modelar_un_cuidado_receptivo_y_brindar_contenido_de_capacitación_(para_niños_de_0_a_5_años) | U11: DB152-05_Talleres_de_desarrollo_profesional_para_docentes_sobre_aprendizaje_temprano_y_bienestar_infantil | V11: UA211-02_Realizar_sesiones_para_cuidadores_sobre_cómo_apoyar_el_aprendizaje_en_el_hogar. | W11: UB173-04_Programas_de_alfabetización_de_adultos_para_empoderar_a_los_cuidadores_en_su_propia_educación | X11: UC193-03_Eventos_escolares-comunitarios_para_mostrar_el_aprendizaje_socioemocional_(SEL)_y_los_protocolos_de_protección_infantil. | Z11: RA371-02_Implementación_de_sesiones_de_desarrollo_socioemocional_y_autocuidado_relacionadas_con_la_seguridad_en_línea_para_niños,_niñas_y_jóvenes | AA11: RB272-01_Implementación_de_la_política_pública_sobre_trabajo_infantil_y_explotación_y_abuso_sexual_vinculados_a_la_explotación_laboral | AB11: RC311-02_Fortalecer_los_clubes,_las_campañas_y_la_promoción_dirigidos_por_jóvenes_que_promueven_la_equidad_de_género_y_la_concientización_sobre_la_prevención_de_la_violencia_de_género. | AC11: RD301-01_Campañas_de_sensibilización_sobre_la_protección_infantil_para_cuidadores | AD11: LA422-03_Aprendizaje,_tutoría_y_coaching_para_empresas_y_cooperativas | AE11: LB551-01_Proporcionar_capital_semilla_y_kits_de_inicio_de_negocios_a_jóvenes_emprendedores. | AF11: LC423-01_Evaluación_de_mercado_e_integración_digital_para_proporcionar_información_de_mercado_en_tiempo_real_para_la_selección_y_el_desarrollo_de_empresas. | AG11: BA444-03_Incidencia_liderada_por_niños_y_jóvenes_ante_el_gobierno_para_reducir_las_emisiones_de_la_industria,_los_edificios_y_el_transporte_mediante_el_cambio_a_fuentes_de_energía_limpia | AH11: BB474-02_Actividades_locales_de_conservación,_gestión_y_restauración_de_ecosistemas_con_alto_contenido_de_carbono,_como_bosques_y_manglares,_mediante_la_plantación_de_árboles,_incluida_la_regeneración_a_partir_de_tocones_de_árboles_vivos_y_plántulas_silvestres. | AI11: BC485-03_Talleres_bianuales_para_ONG_locales_y_grupos_comunitarios_para_colaborar_en_la_movilización_de_recursos_y_la_planificación_de_respuestas_a_emergencias | AJ11: CA281-02_Establecer_espacios_de_protección_con_medidas_de_seguridad_(P2.1.2_) | AK11: AA501-10_Compromiso_con_los_medios | AL11: MA331-03_Intervenciones_grupales_para_cuidadores_que_reflejen_prácticas_curativas_locales_y_valores_culturales. | AM11: YA242-02_Movilización_de_padres,_ancianos_y_jóvenes_en_diálogos_intergeneracionales,_mediación_y_consolidación_de_la_paz_para_fortalecer_la_cohesión_social_y_la_responsabilidad_compartida_de_la_participación_de_los_jóvenes. | AQ11: UC | AR11: UC_Aprendizaje_socioemocional_(SEL) | AS11: 7001-_Otra_Organización_Asociada | AT11: 50206-Tarifa_capacitacion(cost_glob) | AU11: Autoridades gubernamentales | AV11: Reuniones interinstitucionales
A12: Z_Administración | C12: Director Ejecutivo | D12: 1 | E12: Por Producto | R12: HD113-01_Centros_de_salud_comunitarios_para_adolescentes_en_la_comunidad | T12: DA203-01_Campañas_comunitarias_para_desafiar_las_normas_de_género_y_promover_responsabilidades_compartidas_de_cuidado_para_niños_de_0_a_5_años | U12: DB152-06_Suministro_de_guías_para_docentes_y_conjuntos_de_herramientas_de_actividades_(algunos_de_los_cuales_pueden_incluir_un_enfoque_en_el_aprendizaje_basado_en_el_juego_y_planes_de_estudio_adaptados_al_idioma_y_la_cultura_locales) | W12: UB174-01_Competencias_académicas_y_sesiones_de_aprendizaje_interactivo | X12: UC193-04__Aprendizaje_socioemocional_(SEL)_integrado_en_los_planes_de_rutinas_diarias_del_aula_y_actividades_extracurriculares | Z12: RA371-03_Equipar_a_niños_y_jóvenes_con_habilidades_en_tecnologías_de_la_información_y_la_comunicación_(TIC) | AA12: RB272-02_Involucrar_a_personas_influyentes_locales,_líderes_religiosos_y_sobrevivientes_como_defensores_del_cambio. | AB12: RC312-01_Capacitar_y_equipar_a_legisladores,_fuerzas_del_orden_y_el_poder_judicial_para_implementar_leyes_de_protección_infantil_sobre_prevención_y_respuesta_a_prácticas_nocivas. | AC12: RD301-02_Desarrollar_la_capacidad_de_los_líderes_comunitarios_y_los_trabajadores_de_la_salud_sobre_los_derechos_del_niño,_los_principios_de_protección_y_la_gestión_de_casos. | AD12: LA423-01_Evaluación_de_mercado_e_integración_digital_para_proporcionar_información_de_mercado_en_tiempo_real_para_la_selección_y_el_desarrollo_de_empresas. | AE12: LB552-01_Capacitación_en_emprendimiento_que_abarca_la_ideación,_planificación_empresarial_y_análisis_de_mercado. | AF12: LC424-01_Exposiciones_y_ferias_agrícolas_dirigidas_por_jóvenes_para_promover_la_innovación_y_el_emprendimiento | AG12: BA445-01_Programas_de_capacitación_para_niños,_jóvenes,_padres,_trabajadores_de_la_salud,_maestros,_trabajadores_comunitarios,_comités_de_protección_infantil_sobre_riesgos_para_la_salud_relacionados_con_el_clima,_vulnerabilidades_específicas_de_los_niños,_apoyo_psicosocial_básico_(PSS),_atención_informada_sobre_el_trauma_y_protección_infantil_comunitaria_en_áreas_afectadas_por_el_clima. | AH12: BB474-03_Esfuerzos_locales_de_conservación_para_conservar_y_restaurar_humedales_degradados,_como_la_demarcación_de_humedales_mediante_el_establecimiento_de_una_zona_de_amortiguación. | AI12: BC486-01_Espacios_Adaptados_a_la_Infancia_(CFS)_y_servicios_de_apoyo_social_dirigidos_por_jóvenes_para_ayudar_a_los_niños_y_jóvenes_a_afrontar_los_factores_estresantes_debido_a_la_variabilidad_climática;_salud_mental_y_apoyo_psicosocial,_protección,_asesoramiento,_servicios_médicos_y_otros_servicios_sociales. | AJ12: CA281-03_Brindar_capacitación_al_personal_de_espacios_seguros_sobre_protección_infantil,_inclusión_y_métodos_participativos_(P2.1.3) | AK12: AA501-11_Desarrollo_de_recursos_de_promoción | AL12: MA331-04_Evaluación_y_derivaciones_de_salud_mental_integradas_en_visitas_domiciliarias_y_programas_de_crianza | AM12: YA243-01_Identificación_y_vinculación_de_las_comunidades_con_oportunidades_de_financiamiento_que_respalden_proyectos_liderados_por_jóvenes | AQ12: UD | AR12: UD_Acceso_y_retención | AT12: 50301-Servicios_contratados | AU12: Socias implementadoras | AV12: Reuniones locales y asambleas
A13: X_Patrocinio | B13: JUL | C13: Lider-Prog-Desarrollo PI | D13: 2 | E13: Sinergia Equipo | N13: José Orlando Osorto Pérez - Director General | O13: José Orlando Osorto Pérez - Director General | P13: 0610-1980-00214 | R13: HD114-01_Sesiones_educativas_sobre_los_derechos_sexuales_y_reproductivos_de_los_jóvenes_para_proveedores_de_servicios_de_salud | T13: DA203-02_Campañas_y_eventos_comunitarios_para_promover_la_crianza_positiva_y_reconocer_los_esfuerzos_de_los_cuidadores_de_niños_de_0_a_5_años. | U13: DB153-01_Maestros/facilitadores_de_ECCE,_maestros_de_primeros_grados_y_cuidadores_capacitados_en_la_transición_de_ECCE_a_primeros_grados_(primaria). | W13: UB174-02_Campañas_de_cambio_de_comportamiento_social_para_promover_la_participación_escolar | X13: UC194-01_Actividades_de_aprendizaje_socioemocional_(SEL)_implementadas_en_aulas_y_entornos_extracurriculares_utilizando_métodos_apropiados_para_la_edad_(mín._2_veces_por_semana) | Z13: RA372-01_Trabajar_con_empresas_tecnológicas_y_personas_influyentes_clave_para_implementar_entornos_en_línea_seguros | AA13: RB273-01_Mapeo_de_los_mecanismos_de_protección_infantil_comunitarios_(MPCI)_formales_e_informales_para_identificar_brechas_y_fortalecer_la_prevención_y_respuesta_comunitaria_a_la_violencia_contra_los_niños | AB13: RC313-01_Establecer_espacios_seguros,_programas_de_tutoría_e_integrar_la_igualdad_de_género_y_los_derechos_del_niño_en_las_escuelas_y_entornos_comunitarios. | AC13: RD302-01_Creación_de_espacios_interiores_y_exteriores_seguros_para_niños_y_jóvenes | AD13: LA431-01_Grupos_de_ahorro_y_préstamo_y_vínculos_con_instituciones_financieras | AE13: LB552-02_Programas_de_mentoría,_aprendizaje_e_incubación_para_nuevas_empresas_lideradas_por_jóvenes. | AF13: LC431-01_Grupos_de_ahorro_y_préstamo_centrados_en_la_inversión_agrícola_y_la_seguridad_alimentaria | AG13: BA445-02_Campañas_de_concientización,_talleres,_sesiones_de_capacitación_para_educar_a_las_comunidades_(involucrando_a_grupos_vulnerables_y_subrepresentados)_sobre_las_causas_del_riesgo_de_desastres,_los_impactos,_los_mitigantes,_las_estrategias_de_afrontamiento,_reducción_de_riesgos_y_respuesta. | AH13: BB474-04_Incentivos_para_esfuerzos_de_conservación_local,_como_subsidios_para_productos_ecológicos_como_abono_orgánico,_productos_energéticamente_eficientes_y_recompensas_para_esfuerzos_de_conservación_locales_innovadores,_etc. | AI13: BC487-01_Campañas_de_educación_y_concientización_comunitaria_sobre_infraestructura_resiliente_para_proteger_a_los_hogares_de_eventos_climáticos_y_meteorológicos_extremos_(por_ejemplo,_viviendas_resistentes_a_inundaciones_y_sequías_o_a_prueba_del_clima) | AJ13: CA301-01_Diseñar_y_ofrecer_sesiones_grupales_de_MHPSS_apropiadas_para_la_edad_de_niños_y_jóvenes_(P2.2.1) | AK13: AA501-12_Desarrollo_de_capacidades_para_los_responsables_de_los_derechos | AL13: MA331-05_Cuidadores_vinculados_a_grupos_de_apoyo_como_círculos_de_padres,_clubes_de_cuidadores_adolescentes,_grupos_de_abuelos_pares,_asociaciones_de_ahorro_y_préstamo_de_aldeas_con_objetivos_psicosociales. | AM13: YA243-02_Colaboración_de_las_partes_interesadas_locales_(incluidos_los_sectores_público_y_privado)_para_proporcionar_recursos_(tiempo,_espacio,_financiación_o_tutoría)_para_apoyar_iniciativas_lideradas_por_jóvenes | AQ13: RA | AR13: RA_Seguridad_en_línea | AT13: 50302-Servicios_profesionales | AV13: Reuniones internas
A14: ML_Monitoreo | B14: AGO | C14: Lider-Prog-Educacion | D14: 3 | E14: Apoyo voluntario | N14: Edwing Armando Lopez Esteves - Lider de Programa EV-3 | O14: Edwing Armando Lopez Esteves - Coordinador de Programas | P14: 0801-1968-05630 | R14: HD115-01_Mapeo_de_los_servicios_de_salud_sexual_y_reproductiva_en_la_comunidad | T14: DA204-01__Grupos_de_apoyo_para_padres_cuidadores_varones_de_niños_de_0_a_5_años_para_fomentar_el_aprendizaje_entre_pares_y_el_apoyo_emocional | W14: UB174-03_Iniciativas_de_motivación_y_bienestar_docente | X14: UC181-01_Capacitación_en_habilidades_para_la_vida_integrada_en_los_planes_de_estudio_y_programas_extracurriculares_existentes_para_adolescentes_y_jóvenes | Z14: RA381-01_Equipar_a_niños_y_jóvenes_con_habilidades_en_tecnologías_de_la_información_y_la_comunicación_(TIC) | AA14: RB311-01_Implementación_de_la_política_pública_sobre_trabajo_infantil_y_explotación_y_abuso_sexual_vinculados_a_la_explotación_laboral | AB14: RC313-02_Implementación_de_programas_escolares_y_comunitarios_que_eduquen_a_los_jóvenes_y_cuidadores_sobre_la_igualdad_de_género,_las_relaciones_respetuosas,_el_consentimiento_y_la_salud_y_los_derechos_sexuales_y_reproductivos_(SDSR) | AC14: RD311-01_Líderes_comunitarios_capacitados_en_defensa_y_gobernanza_para_mejorar_su_capacidad_de_promover_un_liderazgo_responsable_y_proteger_el_bienestar_de_los_niños_dentro_de_sus_comunidades. | AD14: LA431-02_Talleres_de_educación_financiera_que_cubren_presupuestos,_ahorro,_crédito_y_banca_móvil. | AE14: LB552-03_Acceso_a_laboratorios_de_innovación_compartidos,_centros_comunitarios_o_unidades_de_equipos_móviles_en_zonas_rurales_o_periurbanas | AF14: LC431-02_Asociación_con_instituciones_financieras_para_ofrecer_productos_de_microcrédito_y_seguros_adaptados_a_los_pequeños_agricultores | AG14: BA445-03_Campañas_de_concientización,_talleres,_sesiones_de_capacitación_en_las_escuelas_para_educar_a_los_estudiantes_(grupos_vulnerables_y_subrepresentados)_sobre_las_causas_del_cambio_climático,_los_impactos,_las_estrategias_de_afrontamiento_y_cómo_prevenir_o_minimizar_las_pérdidas,_proteger_el_medio_ambiente_del_impacto_de_los_peligros_naturales:_a_través_de_días_de_concientización,_concursos_de_carteles_y_debates,_etc. | AH14: BB475-01_Campañas_de_concienciación_ambiental_dirigidas_por_niños,_jóvenes_y_la_comunidad_sobre_responsabilidad_compartida,_cambio_de_sistemas_para_acciones_sostenibles_y_prácticas_sostenibles. | AI14: BC491-01_Integración_de_la_educación_en_gestión_de_riesgos_de_desastres_(mitigadores,_preparación_y_respuesta)_en_las_actividades_curriculares_escolares_(actividades_intracurriculares,_cocurriculares_y_extracurriculares):_Integración_como_la_incorporación_de_la_gestión_de_riesgos_de_desastres_en_las_materias,_el_aprendizaje_basado_en_proyectos,_el_arte,_el_teatro,_los_clubes,_los_simulacros,_la_capacitación_de_docentes_y_no_docentes,_el_plan_de_seguridad_escolar | AJ14: CA301-02_Facilitar_grupos_de_apoyo_(incluidos_padres,_maestros_y_otros)_para_abordar_el_estrés,_los_desafíos_de_la_crianza_y_la_resiliencia_emocional_(P2.2.2) | AK14: AA501-13_CBCPM_y_planificación_de_acciones | AL14: MA332-01_Programas_de_generación_de_ingresos_(medios_de_vida)_desarrollados_para_incluir_manejo_del_estrés,_apoyo_grupal_y_educación_psicosocial_básica_para_cuidadores | AM14: YA243-03_Eventos_comunitarios_de_recaudación_de_fondos_para_apoyar_iniciativas_lideradas_por_jóvenes | AQ14: RB | AR14: RB_Trabajo_infantil | AT14: 50303-Mano_obra_personal_no_regular | AV14: Asistencia técnica
A15: PMA_Programa_Mundial_de_Alimentos | B15: SEP | C15: Lider-Prog-Medios Vida | D15: 4 | E15: Consultoria | N15: Eduardo Hernandez Servellon - Oficial Administrativo y RRHH | O15: Patricia Carolina Vásquez Martínez - Contador General | P15: 0809-1985-00011 | T15: DA204-02_Sesiones_de_capacitación_centradas_en_el_padre_para_cuidadores_varones_de_niños_de_0_a_5_años_sobre_el_cuidado,_el_vínculo_y_el_desarrollo_infantil. | W15: UB174-04_Campañas_de_sensibilización_para_promover_la_educación_inclusiva | X15: UC181-02_Talleres_para_adolescentes_y_jóvenes_sobre_autoconciencia/reflexión,_regulación_emocional_y_establecimiento_de_metas. | AA15: RB311-02_Facilitación_de_clubes,_campañas_y_actividades_de_promoción_dirigidos_por_jóvenes_que_promuevan_la_equidad_de_género_y_la_concienciación_sobre_el_trabajo_infantil_y_la_prevención_de_la_violencia_de_género. | AB15: RC314-01_Facilitación_de_la_coordinación_y_colaboración_intersectoriales_entre_los_sistemas_de_salud,_educación,_justicia_y_protección_infantil_para_prevenir_y_abordar_eficazmente_las_prácticas_nocivas | AC15: RD311-02_Voluntarios_y_líderes_capacitados_sobre_los_derechos_del_niño_para_mejorar_su_capacidad_de_promover_un_liderazgo_responsable_y_proteger_el_bienestar_de_los_niños_dentro_de_sus_comunidades. | AD15: LA431-03_Asociación_con_proveedores_de_tecnología_financiera_para_implementar_productos_y_servicios_financieros_móviles_en_áreas_desatendidas | AE15: LB553-01_Capacitación_y_alianzas_que_vinculan_a_los_jóvenes_con_las_cadenas_de_valor_de_la_agroindustria_y_la_economía_digital | AF15: LC431-03_Capacitación_en_alfabetización_financiera_con_énfasis_en_la_presupuestación_para_la_producción_de_alimentos_y_la_nutrición_del_hogar | AG15: BA445-04_Campañas_de_concienciación_dirigidas_por_niños_y_jóvenes_sobre_biodiversidad,_prácticas_sostenibles_de_conservación_del_agua,_restauración_de_humedales_degradados,_gestión_sostenible_de_residuos_y_soluciones_basadas_en_la_naturaleza. | AH15: BB475-02_Intercambios_de_conocimientos_locales_e_indígenas_e_intercambios_de_conocimientos_intergeneracionales_para_fortalecer_las_soluciones_basadas_en_la_naturaleza_y_la_movilización_comunitaria_para_la_restauración_de_ecosistemas. | AI15: BC491-02_Campañas_de_concientización,_talleres_y_sesiones_de_capacitación_en_las_escuelas_para_educar_a_los_estudiantes_(grupos_vulnerables_y_subrepresentados)_sobre_las_causas_del_cambio_climático,_los_impactos,_las_estrategias_de_afrontamiento_y_cómo_prevenir_o_minimizar_las_pérdidas,_proteger_el_medio_ambiente_del_impacto_de_los_peligros_naturales:_a_través_de_días_de_concientización,_concursos_de_carteles_y_debates,_etc. | AJ15: CA301-03_Capacitar_a_los_trabajadores_de_primera_línea_en_primeros_auxilios_psicológicos_(PAP)_y_apoyo_psicosocial_básico._(P2.1.3) | AK15: AA501-14_Apoyo_institucional_al_gobierno_(humano_o_financiero) | AL15: MA341-01_Protocolos_y_herramientas_de_detección_estandarizados_de_MHPSS_(por_ejemplo,_PHQ-9,_GAD-7,_WHO-5_o_SRQ-20)_desarrollados_y_utilizados_en_escuelas,_centros_de_salud_y/o_entornos_comunitarios_para_identificar_y_derivar_casos_de_salud_mental,_signos_tempranos_de_angustia,_trauma,_ansiedad,_abuso_de_sustancias_para_primeros_auxilios_psicológicos_(PFA),_asesoramiento_y/u_otros_servicios_sociales. | AM15: YA244-01_Participación_de_los_jóvenes_en_auditorías_sociales,_periodismo_ciudadano_y/o_cuadros_de_mando_comunitarios_para_exigir_responsabilidades_a_las_instituciones | AQ15: RC | AR15: RC_Prevención_y_respuesta_a_prácticas_nocivas | AT15: 50401-Suministros_y_Materiales | AV15: Recolección de datos
A16: GFC_Fondo_Global_para_la_Niñez | B16: OCT | C16: Lider-Prog-Proteccion | D16: 5 | N16: Carlos Eduardo Martínez - Oficial de MEAL | O16: Eduardo Hernandez Servellon - Oficial Administrativo y RRHH | P16: 0809-2001-00112 | T16: DA205-01_Mensajes_de_estimulación_temprana_integrados_en_los_servicios_de_salud_infantil_y_otros_servicios_sociales. | W16: UB175-01_Proceso_de_reconocimiento_de_logros_estudiantiles_establecido_a_través_de_eventos_y_premios_escolares | X16: UC181-03_Sesiones_dirigidas_por_pares_y_clubes_juveniles_para_reforzar_las_habilidades_para_la_vida_de_adolescentes_y_jóvenes. | AC16: RD312-01_Facilitación_de_plataformas_de_diálogo_entre_representantes_de_la_comunidad_y_actores_gubernamentales_para_desarrollar_y_monitorear_conjuntamente_políticas_de_protección_infantil,_garantizando_que_las_voces_de_la_comunidad_informen_el_diseño_de_políticas,_la_implementación_y_los_mecanismos_de_rendición_de_cuentas. | AE16: LB554-01_Acceso_a_activos_productivos_(por_ejemplo,_herramientas,_tierras,_plataformas_digitales)_y_modelos_cooperativos. | AG16: BA446-01_Espacios_Adaptados_a_la_Infancia_(CFS)_y_servicios_de_apoyo_social_dirigidos_por_jóvenes_para_ayudar_a_los_niños_y_jóvenes_a_afrontar_los_factores_estresantes_debido_a_la_variabilidad_climática;_salud_mental_y_apoyo_psicosocial,_protección,_asesoramiento,_servicios_médicos_y_otros_servicios_sociales. | AH16: BB475-03_Foros_y_plataformas_inclusivos_de_gestión_del_clima_y_el_medio_ambiente,_como_clubes_escolares,_clubes_juveniles,_comités_verdes,_consejos_asesores_juveniles,_COP_(por_ejemplo,_verde,_eco-embajador,_eco-scouts)_para_la_colaboración_en_proyectos_ecológicos. | AI16: BC491-03_Iniciativas_y_estrategias_dirigidas_por_niños_y_jóvenes,_como_simulacros_periódicos_(inundaciones,_sequías_y_olas_de_calor),_simulación_de_escenarios_de_desastres_locales_y_capacitación_de_estudiantes_y_personal_docente_y_no_docente. | AJ16: CA302-01_Capacitar_a_los_trabajadores_de_primera_línea_sobre_las_normas_y_procedimientos_de_gestión_de_casos_de_protección_infantil._(P3.1.1) | AK16: AA511-01_Diálogos_y_consultas_sobre_políticas_entre_múltiples_partes_interesadas_facilitados | AL16: MA342-01_Se_establecieron_puntos_focales_de_MHPSS_y_redes_de_apoyo_entre_pares_(incluidos_clubes_SEL) | AQ16: RD | AR16: RD_Protección_infantil_basada_en_la_comunidad | AT16: 50402-Otros_suministros_y_materiales | AV16: Discusión de focus group
B17: NOV | C17: Lider-Patrocinio | D17: 6 | N17: Beyquer Odan Maldonado - Lider de Programa EV-1 | O17: William Misael Martínez Chévez - Auxiliar Administrativo | T17: DA206-01__Materiales_digitales_e_impresos_culturalmente_relevantes_desarrollados_y_difundidos_para_cuidadores_sobre_atención_receptiva_a_niños_de_0_a_5_años | X17: UC182-01_Sesiones_de_capacitación_para_docentes_y_facilitadores_sobre_el_desarrollo_de_habilidades_para_la_vida_de_adolescentes_y_jóvenes | AC17: RD261-01_Participación_de_niños_y_jóvenes_en_la_vida_cívica,_como_sesiones_de_planificación,_votaciones_y_otros_discursos_públicos. | AE17: LB555-01_Ferias_y_exposiciones_empresariales_dirigidas_por_jóvenes_para_mostrar_innovaciones_y_atraer_inversiones. | AG17: BA447-01_Intercambios_de_conocimientos_locales_e_indígenas_e_intercambios_de_conocimientos_intergeneracionales_para_fortalecer_las_soluciones_basadas_en_la_naturaleza_y_la_movilización_comunitaria_para_la_restauración_de_ecosistemas. | AH17: BB476-01_Desarrollo_de_políticas_y_planes_sostenibles,_políticas_de_compras_y_adquisiciones_éticas_y_planes_de_acción_por_parte_de_los_socios_implementadores_locales_y_las_escuelas | AI17: BC491-04_Iniciativas_y_estrategias_dirigidas_por_niños_y_jóvenes,_como_simulacros_periódicos_(inundaciones,_sequías_y_olas_de_calor),_simulación_de_escenarios_de_desastres_locales_y_capacitación_de_estudiantes_y_personal_docente_y_no_docente. | AJ17: CA302-02_Establecer_vías_de_derivación_y_mapeo_de_servicios_con_actores_locales_de_todos_los_sectores._(P3.1.2) | AK17: AA511-02__Generación_y_difusión_de_evidencia_para_informar_el_desarrollo_de_políticas | AL17: MA343-01_Se_establecen_vías_de_derivación_adaptadas_a_los_niños | AQ17: LA | AR17: LA_Empoderamiento_económico_para_las_familias | AT17: 50403-Impresiones | AV17: Reuniones de rendición de cuentas
B18: DIC | C18: Lider MEAL | D18: 7 | N18: Carmen Suyapa Pavón Almendarez - Oficial de Patrocinio | O18: Carlos Eduardo Martínez - Oficial de MEAL | P18: 0809-1992-00056 | X18: UC182-02_Capacitación_y_tutoría_para_docentes_sobre_cómo_impartir_educación_en_habilidades_para_la_vida_a_adolescentes_y_jóvenes. | AC18: RD261-02_Iniciativas_de_defensa_lideradas_por_jóvenes,_como_campañas,_peticiones,_protestas_pacíficas_o_presentaciones_comunitarias_en_foros_subnacionales,_nacionales_o_de_intervención. | AE18: LB555-02_Producción_y_distribución_de_programas_o_series_de_podcasts_en_línea,_de_televisión_o_de_radio_que_presenten_historias_de_éxito_de_jóvenes_y_consejos_profesionales_prácticos. | AG18: BA448-01_Actividades_ambientales_y_sostenibles_dirigidas_por_niños_y_jóvenes_en_la_escuela_(agua,_tierra,_gestión_de_residuos,_plantación_de_árboles,_caminatas_por_la_naturaleza,_excursiones_a_parques_locales,_viajes_de_campamento,_reservas_naturales,_centros_ambientales_y_observación_de_vida_silvestre_para_fomentar_la_conexión_con_la_naturaleza,_etc.) | AI18: BC492-01_Establecimiento_de_foros_y_plataformas_de_RRD,_como_clubes_escolares,_clubes_juveniles,_consejos_juveniles,_comités_verdes_y_consejos_asesores_juveniles_en_escuelas_seleccionadas | AJ18: CA302-03_Examinar_y_derivar_casos_de_protección_(incluidos_los_de_localización_y_reunificación_familiar_(FTR)_(P3.1.3) | AK18: AA511-03_Asistencia_técnica_a_organismos_gubernamentales_en_la_elaboración_e_implementación_de_políticas | AL18: MA343-02_Reuniones_periódicas_de_coordinación_entre_las_estructuras_del_CBCP,_las_escuelas,_las_clínicas_comunitarias_y_otros_proveedores_de_servicios_sociales | AQ18: LB | AR18: LB_Empoderamiento_económico_para_los_jóvenes | AT18: 50501-Hospedaje | AV18: Acciones de incidencia
B19: ENE | C19: Lider Adm-RRHH | D19: 8 | N19: Eliberth Fabricio Galileo García Martínez - Lider de Programa EV-2 | O19: Beyquer Odan Maldonado - Coordinador de Área | P19: 1211-1981-00305 | AC19: RD261-03_Formación_de_foros_y_redes_liderados_por_jóvenes_y_apoyo_a_sus_actividades_para_fomentar_el_compromiso_cívico_y_la_acción_colectiva. | AE19: LB555-03_Involucrar_a_personas_influyentes,_líderes_religiosos_y_exalumnos_para_respaldar_las_trayectorias_vocacionales | AG19: BA448-02_Iniciativas_y_estrategias_dirigidas_por_niños_y_jóvenes,_como_simulacros_periódicos_(inundaciones,_sequías_y_olas_de_calor),_simulación_de_escenarios_de_desastres_locales_y_capacitación_de_estudiantes_y_personal_docente_y_no_docente. | AI19: BC492-02_Capacitación_para_foros_y_plataformas_escolares_sobre_causas_de_desastres,_mitigantes,_preparación,_reducción_de_riesgos_y_respuesta,_incluidos_liderazgo,_promoción_y_educación_entre_pares. | AJ19: CA302-04_Proporcionar_supervisión_y_capacitación_periódicas_a_los_trabajadores_sociales_para_garantizar_la_calidad_y_la_rendición_de_cuentas._(P3.1.4) | AK19: AA512-01_Campañas_de_promoción_para_crear_conciencia_sobre_las_leyes_y_los_derechos | AL19: MA343-03_Se_desarrollaron_procedimientos_operativos_estándar_interinstitucionales_para_responder_a_casos_de_abuso_con_necesidades_de_MHPSS | AQ19: LC | AR19: LC_Seguridad_alimentaria | AT19: 50502-Alimentos | AV19: Visitas domiciliarias
B20: FEM | C20: Lider Contabil | D20: 9 | N20: Jennifer Sabrina Romero Martínez - Especialista en RRHH | O20: Carmen Suyapa Pavón Almendarez - Oficial de Patrocinio | P20: 0816-1975-00222 | AE20: LB421-01_Proporcionar_capital_semilla_y_kits_de_inicio_de_negocios_a_jóvenes_emprendedores. | AG20: BA448-03_Evaluación_de_sostenibilidad_y_medio_ambiente_dirigida_por_niños_y_jóvenes_(a_través_de_encuestas_y_entrevistas)_para_recopilar_comentarios_sobre_los_riesgos_y_peligros_climáticos_en_la_comunidad_y_las_escuelas_para_crear_entornos_de_aprendizaje_sostenibles_dentro_de_la_escuela. | AI20: BC493-01_Desarrollo_e_implementación_de_la_Gestión_del_Riesgo_de_Desastres_relacionada_con_el_clima_por_parte_de_las_escuelas_objetivo_(incluidos_los_grupos_vulnerables_y_subrepresentados)_para_la_mitigación_de_desastres,_la_preparación,_la_reducción_de_riesgos,_la_respuesta_y_los_planes_de_recuperación_pertinentes_al_contexto:_Planes_como_CB-DRR,_planes_de_respuesta_y_recuperación,_y_EPP,_incluidos_los_planes_de_DRR_para_la_comunidad,_los_adolescentes_y_los_jóvenes. | AJ20: CA303-01_Capacitar_al_personal_de_primera_línea_sobre_protocolos_seguros_de_localización_y_reunificación_familiar_(FTR)_y_estándares_de_cuidado_alternativo_(P3.2.1) | AK20: AA512-02_Garantes_de_deberes_capacitados_en_mandatos_legales | AL20: MA343-04_Detección_de_SMAPS_y_psicoeducación_integradas_en_los_servicios_de_los_centros_de_salud_(atención_prenatal_y_posnatal),_apoyo_a_la_subsistencia_y_otros_servicios_sociales_para_adolescentes,_padres_y_cuidadores_adultos. | AQ20: BA | AR20: BA_Adaptación_climática | AT20: 50503-Pasajes_Aereos | AV20: Actividades WASH
B21: MAR | C21: Asist-Admin | D21: 10 | N21: Junta Directiva-Accion Honduras | O21: Yessenia Milixa Amador - Técnico de Desarrollo Comunitario | P21: 0809-1977-00223 | AE21: LB422-01_Capacitación_en_emprendimiento_que_abarca_la_ideación,_planificación_empresarial_y_análisis_de_mercado. | AG21: BA451-01_Capacitación_de_voluntarios_comunitarios_en_tecnologías_de_energía_renovable_y_de_bajo_consumo_energético_(como_cocinas_de_bajo_consumo_de_combustible_y_otras_fuentes_de_energía_renovable_como_lámparas_solares,_bombas_de_agua_solares,_energía_eólica,_biogás,_energía_hidroeléctrica)_para_reducir_las_emisiones_de_gases_de_efecto_invernadero. | AI21: BC493-02_Suministro_de_recursos_necesarios_para_la_gestión_del_riesgo_de_desastres,_como_botiquines_de_primeros_auxilios_y_suministros_de_emergencia,_a_las_escuelas_seleccionadas. | AJ21: CA303-02_Establecer_o_apoyar_mecanismos_de_coordinación_con_los_sistemas_nacionales_de_búsqueda_y_reunificación_(por_ejemplo,_el_Comité_Internacional_de_la_Cruz_Roja_(CICR),_las_autoridades_de_protección_infantil)_(P3.2.2) | AK21: AA512-03_Se_han_establecido_o_mejorado_mecanismos_de_seguimiento_y_rendición_de_cuentas_basados_en_la_comunidad | AL21: MA343-05_Fortalecimiento_de_la_capacidad_de_los_docentes_y_los_comités_escolares_para_reconocer_el_ausentismo_vinculado_al_estrés_psicosocial,_la_discapacidad_o_los_riesgos_de_protección_y_desarrollar_vías_de_derivación_adaptadas_a_los_niños. | AQ21: BB | AR21: BB_Cuidado_del_medio_ambiente | AT21: 50504-Transporte
B22: ABR | C22: Tecn-Prog-Desarrollo PI | D22: 11 | O22: Yimi Alexander Hernández - Técnico de Desarrollo Comunitario | P22: 0802-2004-00095 | AE22: LB422-02_Programas_de_mentoría,_aprendizaje_e_incubación_para_nuevas_empresas_lideradas_por_jóvenes. | AG22: BA451-02__Sesiones_de_capacitación_comunitaria_sobre_el_diseño,_la_producción_y_la_instalación/aplicación_de_tecnologías_de_energía_renovable_y_de_bajo_consumo_energético_(como_cocinas_de_bajo_consumo_de_combustible_y_otras_fuentes_de_energía_renovable_como_lámparas_solares,_bombas_de_agua_solares,_energía_eólica,_biogás_e_hidroeléctrica)_para_reducir_las_emisiones_de_gases_de_efecto_invernadero_y_promover_prácticas_energéticas_sostenibles. | AI22: BC493-03_Asociaciones_entre_escuelas_y_comunidades_locales_para_desarrollar_e_implementar_planes_de_emergencia/gestión_de_riesgos_de_desastres_entre_escuelas_y_comunidades | AJ22: CA303-03_Identificar_y_evaluar_opciones_de_atención_alternativa_apropiadas_al_contexto_(P3.2.3) | AK22: AA521-01_Proveedores_de_servicios_que_reciben_capacitación_y/o_coaching | AL22: MA343-06_Sistemas_de_protección_infantil_y_mapeo_CBCP_para_identificar_a_niños_en_riesgo_o_involucrados_en_trabajo_peligroso | AQ22: BC | AR22: BC_Reducción_del_Riesgo_de_Desastres__RRD | AT22: 50505-Otros_gastos_de_viaje
B23: MAY | C23: Tecn-Prog-Educacion | D23: 12 | O23: Jose Adalid Funes - Técnico de Desarrollo Comunitario | P23: 0809-1985-00088 | AE23: LB423-01_Capacitación_y_alianzas_que_vinculan_a_los_jóvenes_con_las_cadenas_de_valor_de_la_agroindustria_y_la_economía_digital | AG23: BA451-03_Incentivos_y/o_subsidios_para_que_los_hogares_utilicen_tecnologías/prácticas_de_energía_renovable_y_eficiente_y_sostenible_(como_cocinas_de_bajo_consumo_de_combustible_y_fuentes_de_energía_renovables_como_lámparas_solares,_bombas_de_agua_solares,_biogás,_energía_eólica_e_hidroeléctrica)_para_reducir_las_emisiones_de_gases_de_efecto_invernadero. | AI23: BC493-04__Evaluaciones_de_riesgos_y_resiliencia_locales_basadas_en_las_escuelas_(incluida_la_infraestructura_escolar)_para_permitir_la_planificación_y_la_toma_de_decisiones_basadas_en_el_riesgo | AJ23: CA303-04_Apoyar_la_colocación_segura_y_el_seguimiento_de_los_niños_no_acompañados_y_separados_(UASC)_en_opciones_de_cuidado_alternativo_adecuadas_(P3.2.4) | AK23: AA521-02_Se_desarrollaron_y_distribuyeron_directrices_operativas,_procedimientos_operativos_estándar_(POE)_y_conjuntos_de_herramientas | AQ23: CA | AR23: CA_Niños_desplazados_en_crisis_protegidas | AT23: 50601-DFCs_pagados
B24: JUN | C24: Técnico integral | D24: 13 | O24: David Alonzo Ramos - Técnico de Desarrollo Comunitario | P24: 0809-1997-00031 | AE24: LB424-01_Acceso_a_activos_productivos_(por_ejemplo,_herramientas,_tierras,_plataformas_digitales)_y_modelos_cooperativos. | AG24: BA452-01_Campañas_de_concientización_comunitaria,_talleres_y_sesiones_de_capacitación_sobre_prácticas_sostenibles_de_conservación_del_agua,_como_el_uso_eficiente_del_agua,_la_protección_de_las_fuentes_de_agua,_los_humedales,_la_recolección_de_agua_de_lluvia,_el_reciclaje_de_agua,_etc. | AI24: BC494-01_Instalación_de_un_sistema_de_alerta_temprana_en_escuelas_seleccionadas_para_monitorear_la_evolución_de_desastres_(fenómenos_climáticos_y_meteorológicos_extremos)_y_proporcionar_actualizaciones_oportunas_en_todas_las_áreas_de_alto_riesgo,_alertas_meteorológicas_y_avisos_de_evacuación. | AJ24: CA241-01_Realizar_evaluaciones_participativas_con_jóvenes_utilizando_metodologías_apropiadas_para_su_edad_y_su_relevancia_cultural_para_explorar_sus_experiencias_vividas,_las_barreras_que_les_impiden_el_bienestar_y_sus_mecanismos_de_afrontamiento_existentes._(YA1.1.1) | AK24: AA522-01_Desarrollo_de_sistemas_de_datos_digitales_y_comunitarios | AQ24: AA | AR24: AA_Incidencia | AT24: 50602-Proyectos_comunitarios
B25: JUL-SEP | C25: Tecnico Patrocinio | D25: 14 | O25: Goel Garcia Alvarado - Técnico de Desarrollo Comunitario | P25: 0804-1992-00084 | AE25: LB425-01_Ferias_y_exposiciones_empresariales_dirigidas_por_jóvenes_para_mostrar_innovaciones_y_atraer_inversiones. | AG25: BA452-02__Esfuerzos_locales_de_conservación_para_implementar_prácticas_sostenibles_de_conservación_del_agua,_como_el_uso_eficiente_del_agua,_la_protección_de_las_fuentes_de_agua,_la_recolección_de_agua_de_lluvia,_la_purificación_de_agua_con_energía_solar,_el_reciclaje_de_agua,_etc. | AI25: BC494-02_Diseño_y_prestación_de_servicios_de_información_climática_oportuna_y_basada_en_la_demanda,_tales_como_pronósticos_meteorológicos,_sistemas_de_alerta_temprana,_información_de_evaluación_de_riesgos_climáticos_y_conocimientos_tradicionales_para_ayudar_en_el_proceso_de_toma_de_decisiones_basado_en_riesgos. | AJ25: CA241-02_Mapear_los_activos_y_recursos_individuales_y_colectivos_de_los_jóvenes,_incluyendo_grupos_liderados_por_jóvenes_y_redes_de_apoyo_informales,_para_fundamentar_el_diseño_de_programas._(YA1.1.2) | AK25: AA522-02_Se_implementaron_plataformas_conjuntas_de_planificación_y_coordinación_entre_sectores | AQ25: MA | AR25: MA_Salud_mental_y_apoyo_psicosocial | AT25: 50701-Combustible
B26: JUL-DIC | C26: PF-Comunicac | D26: 15 | O26: Nubia Lisseth Medina Munguía - Técnico de Desarrollo Comunitario | P26: 0802-1985-00094 | AE26: LB426-01_Evaluación_de_mercado_e_integración_digital_para_proporcionar_información_de_mercado_en_tiempo_real_para_la_selección_y_el_desarrollo_de_empresas. | AG26: BA452-03_Desarrollo_de_sistemas_de_agua_de_uso_múltiple_(infraestructura)_para_uso_doméstico,_producción_agrícola_y_ganadera:_aprovechamiento_de_aguas_subterráneas,_presas_de_valles,_aguas_superficiales_y_atmosféricas. | AI26: BC495-01_Evaluación_de_sostenibilidad_y_medio_ambiente_dirigida_por_niños_y_jóvenes_(a_través_de_encuestas_y_entrevistas)_para_recopilar_comentarios_sobre_los_riesgos_y_peligros_climáticos_en_la_comunidad_y_las_escuelas_para_crear_entornos_de_aprendizaje_sostenibles_dentro_de_la_escuela. | AJ26: CA241-03_Facilitar_a_los_jóvenes_el_diseño_y_la_dirección_de_iniciativas_comunitarias_basadas_en_los_resultados_de_las_evaluaciones,_promoviendo_la_seguridad,_la_inclusión_y_las_alternativas_locales_a_los_desafíos_de_la_migración_irregular_y_la_reintegración._(YA1.1.3) | AK26: AA522-03_Evaluaciones_institucionales_y_planificación_de_acciones_de_apoyo | AQ26: YA | AR26: YA_Agencia_Infantil_y_Juvenil | AT26: 50702-Mantenimiento_de_vehículos
B27: JUL-MAR | C27: Equipo Tecnico | D27: 16 | O27: Roger Neptaly Silva Sánchez - Técnico de Desarrollo Comunitario | P27: 0809-1984-00317 | AE27: LB431-01_Grupos_de_ahorro_y_préstamo_para_jóvenes_y_vínculos_con_instituciones_financieras_favorables_a_los_jóvenes | AG27: BA452-04_Esfuerzos_locales_de_conservación_para_conservar_y_restaurar_humedales_degradados,_como_la_demarcación_de_humedales_mediante_el_establecimiento_de_una_zona_de_amortiguación. | AJ27: CA242-01_Impartir_talleres_estructurados_de_habilidades_para_la_vida_y_toma_de_decisiones_que_aumenten_el_conocimiento_de_los_jóvenes_sobre_los_riesgos_relacionados_con_la_migración_y_reduzcan_su_intención_de_migrar,_fomentando_la_confianza,_el_pensamiento_crítico_y_la_capacidad_de_establecer_metas._(YA1.2.1) | AK27: AA531-01_Líderes_comunitarios,_grupos_juveniles_y_OSC_capacitados_en_incidencia_y_gobernanza | AQ27: ZA | AR27: ZA_Gestión_Administrativa | AT27: 50703-Mantenimiento:equipos
B28: JUL-JUN | C28: CEO | D28: 17 | O28: Jeniffer Abigail Canales Flores - Técnico de Desarrollo Comunitario | P28: 0611-1995-00349 | AE28: LB431-02_Talleres_de_educación_financiera_que_cubren_presupuestos,_ahorro,_crédito_y_banca_móvil. | AG28: BA453-01_Campañas_de_concientización,_talleres_y_sesiones_de_capacitación_sobre_gestión_sostenible_de_residuos_para_reducir_la_generación_de_residuos,_promover_el_reciclaje_y_hacer_cumplir_la_eliminación_adecuada. | AJ28: CA242-02_Facilitar_iniciativas_de_mentoría_y_coaching_entre_pares_que_fortalezcan_la_comprensión_de_los_jóvenes_sobre_los_riesgos_migratorios_mediante_la_autorreflexión,_experiencias_compartidas_y_estrategias_prácticas_para_afrontar_los_desafíos._(YA1.2.2) | AK28: AA531-02_Se_implementaron_cuadros_de_mando_comunitarios,_auditorías_sociales_y/o_foros_públicos | AQ28: XA | AR28: XA_Gestión_de_Patrocinios | AT28: 50704-Mantenimiento:oficinas
C29: Red de Madres guia | D29: 18 | O29: Francisca Baiza García - Técnico de Desarrollo Comunitario | P29: 0804-1984-00828 | AE29: LB431-03_Asociación_con_proveedores_de_tecnología_financiera_para_implementar_productos_y_servicios_financieros_móviles_en_áreas_desatendidas | AG29: BA453-02_Esfuerzos_locales_de_conservación_para_reducir_la_generación_de_residuos,_promover_el_reciclaje_y_garantizar_la_eliminación_adecuada | AJ29: CA242-03_Apoyar_la_planificación_e_implementación,_impulsadas_por_jóvenes,_de_acciones_comunitarias_que_fomenten_el_liderazgo_y_refuercen_la_toma_de_decisiones_informada_sobre_las_opciones_migratorias._(YA1.2.3) | AK29: AA531-03__Se_formaron_e_implementaron_plataformas_comunitarias_inclusivas | AQ29: ML | AR29: MA_Monitoreo_y_soporte_técnico_del_programa | AT29: 50705-Alquileres-arrendamiento
C30: Red de Docentes | D30: 19 | O30: Alex Omar Alvarado A - Técnico de Desarrollo Comunitario | P30: 0804-2000-00305 | AE30: LB432-01_Abogar_por_cuotas_de_jóvenes_en_los_organismos_de_formulación_de_políticas_agrícolas_y_las_cooperativas_de_agricultores. | AG30: BA454-01_Campañas_de_concientización,_talleres_y_sesiones_de_capacitación_sobre_soluciones_basadas_en_la_naturaleza,_como_la_conservación,_gestión_y_restauración_de_bosques,_manglares,_turberas_y_ecosistemas_con_alto_contenido_de_carbono. | AJ30: CA421-01_Impartir_educación_y_formación_técnica_y_profesional_(EFTP)_y_aprendizajes_vinculados_a_la_demanda_del_mercado_(por_ejemplo,_energía_limpia,_tecnología_agrícola,_servicios_digitales)_(YA2.1.1) | AK30: AA532-01__Niños_y_jóvenes_capacitados_en_liderazgo_y_defensa_de_derechos | AT30: 50706-Cargos_bancarios_y_otros_serv
C31: Red de Apoyo Juvenil | D31: 20 | O31: Alex Francisco Castillo - Técnico de Desarrollo Comunitario | P31: 0801-1992-16893 | AE31: LB432-02_Trabajar_con_los_gobiernos_locales_para_asignar_tierras_y_líneas_presupuestarias_específicamente_para_iniciativas_agrícolas_juveniles. | AG31: BA454-02_Actividades_locales_de_conservación,_gestión_y_restauración_de_ecosistemas_con_alto_contenido_de_carbono,_como_bosques_y_manglares,_mediante_la_plantación_de_árboles,_incluida_la_regeneración_a_partir_de_tocones_de_árboles_vivos_y_plántulas_silvestres. | AJ31: CA421-02_Proporcionar_kits_de_inicio_o_financiación_inicial_para_iniciativas_de_generación_de_ingresos_lideradas_por_jóvenes_(YA2.1.2) | AK31: AA532-02_Campañas,_foros_y_plataformas_de_participación_digital_lideradas_por_jóvenes | AT31: 50707-Seguros
C32: Red de MPBC | O32: Nancy Nicol Sevilla M - Técnico de Desarrollo Comunitario | P32: 0802-1999-00032 | AE32: LB432-03_Brindar_acceso_a_crédito,_subsidios_y_equipos_agrícolas_para_emprendimientos_agrícolas_liderados_por_jóvenes. | AG32: BA454-03_Intercambios_de_conocimientos_locales_e_indígenas_e_intercambios_de_conocimientos_intergeneracionales_para_fortalecer_las_soluciones_basadas_en_la_naturaleza_y_la_movilización_comunitaria_para_la_restauración_de_ecosistemas. | AJ32: CA421-03_Educación_sobre_técnicas_de_adaptación_climática,_en_particular_en_entornos_agrícolas_(YA2.1.3) | AK32: AA532-03_Diálogos_intergeneracionales_y_programas_de_mentoría | AT32: 50708-Telefono_e_internet
C33: Tecnico Vol. Patrocinio | O33: Jhony Alfredo Amador - Técnico de Desarrollo Comunitario | P33: 0801-1992-16893 | AE33: LB432-04_Facilitar_modelos_de_agricultura_grupal,_reduciendo_las_barreras_de_propiedad_de_la_tierra_y_los_riesgos_operativos | AG33: BA455-01_Suministro_de_variedades_de_cultivos_adaptables_y_productivos_al_clima_a_las_familias_agrícolas,_incluidos_híbridos_propensos_a_sequías_e_inundaciones | AJ33: CA422-01_Realizar_un_mapeo_del_mercado_y_de_las_competencias_para_identificar_oportunidades_de_empleo_basadas_en_la_demanda_y_evaluar_las_capacidades_individuales_de_los_jóvenes,_incluyendo_las_habilidades_técnicas,_digitales_y_blandas,_para_fundamentar_rutas_de_subsistencia_personalizadas._(YA2.2.1) | AT33: 50709-Correo_y_fletes
O34: Norma Waleska Hernandez - Técnico de Desarrollo Comunitario | P34: 0809-1995-00445 | AG34: BA456-01_Campañas_de_concienciación_ambiental_dirigidas_por_niños,_jóvenes_y_la_comunidad_sobre_responsabilidad_compartida,_cambio_de_sistemas_para_acciones_sostenibles_y_prácticas_sostenibles. | AJ34: CA422-02_Facilitar_la_interacción_con_empresas_locales_para_la_tutoría_y_la_experiencia_laboral_(YA2.2.2) | AT34: 50710-Servicios_Basicos
O35: Osterly Samir Vásquez - Técnico de Desarrollo Comunitario | P35: 0815-1999-00266 | AG35: BA456-02_Campañas_de_educación_y_concientización_comunitaria_sobre_infraestructura_resiliente_para_proteger_a_los_hogares_de_eventos_climáticos_y_meteorológicos_extremos_(por_ejemplo,_viviendas_resistentes_a_inundaciones_y_sequías_o_a_prueba_del_clima). | AJ35: CA422-03_Facilitar_grupos_de_ahorro_para_jóvenes_y_conectarlos_con_servicios_financieros_adaptados_a_sus_necesidades_(YA2.2.3) | AT35: 50711-Gastos_varios
O36: Eliberth Fabricio Galileo García Martínez - Especialista en soluciones tecnologicas y recursos digitales | P36: 0809-1998-00030 | AG36: BA456-03_Foros_y_plataformas_inclusivos_de_gestión_del_clima_y_el_medio_ambiente,_como_clubes_escolares,_clubes_juveniles,_comités_verdes,_consejos_asesores_juveniles,_COP_(por_ejemplo,_verde,_eco-embajador,_eco-scouts)_para_la_colaboración_en_proyectos_ecológicos. | AJ36: CA111-01_Realizar_una_evaluación_de_necesidades_y_acceso_para_determinar_las_ubicaciones,_la_frecuencia_y_el_alcance_óptimos_de_la_prestación_de_servicios_de_salud_móviles_(H1.1.1) | AT36: 50901-Equipamiento
O37: Jennifer Sabrina Romero Martínez - Especialista en Protección e Incidencia | P37: 0809-1992-00487 | AG37: BA457-01_Desarrollo_de_políticas_y_planes_sostenibles,_políticas_de_compras_y_adquisiciones_éticas_y_planes_de_acción_por_parte_de_los_socios_implementadores_locales_y_las_escuelas | AJ37: CA111-02_Adquirir,_personalizar_y_equipar_unidades_móviles_de_salud_con_suministros_médicos_esenciales_y_materiales_sensibles_a_las_cuestiones_de_género_y_a_los_jóvenes_(H1.1.2) | AT37: 50902-Muebles_y_accesorios
AG38: BA461-01_Integración_del_cambio_climático_y_la_educación_ambiental_en_los_programas_escolares,_incluidas_actividades_intracurriculares,_cocurriculares_y_extracurriculares_como_educación_climática_y_ambiental_en_las_asignaturas,_orientación_profesional_sobre_oportunidades_agrícolas,_proyectos_de_ecoarte_y_actividades_sostenibles_como_el_reciclaje_y_la_conservación_de_la_energía,_ecoescuelas_y_plan_de_estudios_de_restauración_de_ecosistemas_para_jóvenes. | AJ38: CA111-03_Establecer_puntos_de_prestación_de_servicios_móviles_o_en_refugios_en_colaboración_con_socios_locales_(H1.1.3) | AT38: 50903-Procesamiento_datos_y_software
AG39: BA461-02_Iniciativas_y_estrategias_dirigidas_por_niños_y_jóvenes,_como_simulacros_periódicos_(inundaciones,_sequías_y_olas_de_calor),_simulación_de_escenarios_de_desastres_locales_y_capacitación_de_estudiantes_y_personal_docente_y_no_docente. | AJ39: CA111-04_Reclutar_y_desplegar_equipos_móviles_de_salud_multidisciplinarios_(H1.1.4) | AT39: 50904-Otros_activos_fijos
AG40: BA462-01_Desarrollo_e_implementación_de_la_Gestión_del_Riesgo_de_Desastres_relacionada_con_el_clima_por_parte_de_las_escuelas_objetivo_(incluidos_los_grupos_vulnerables_y_subrepresentados)_para_la_mitigación_de_desastres,_la_preparación,_la_reducción_de_riesgos,_la_respuesta_y_los_planes_de_recuperación_pertinentes_al_contexto:_Planes_como_CB-DRR,_planes_de_respuesta_y_recuperación,_y_EPP,_incluidos_los_planes_de_DRR_para_la_comunidad,_los_adolescentes_y_los_jóvenes. | AJ40: CA112-01_Diseñar_y_difundir_materiales_de_IEC_(Información,_Educación,_Comunicación)_inclusivos_y_culturalmente_integrados_(folletos,_carteles,_mensajes_de_radio)_en_idiomas_locales_sobre_los_servicios_de_salud_disponibles_(H1.2.1)
O41: Beyquer Odan Maldonado - Lider Programa EV-1 | P41: 1211-1981-00305 | AG41: BA463-01__Establecimiento_de_una_visión_y_política_verde_(Estándar_Verde_de_la_UNESCO)_por_parte_de_las_escuelas_destinatarias. | AJ41: CA112-02_Organizar_sesiones_de_diálogo_comunitario_y_sesiones_informativas,_involucrando_a_líderes_juveniles,_cuidadores_y_proveedores_de_servicios_locales._(H1.2.2)
O42: Eliberth Fabricio Galileo García Martínez - Lider Programa EV-2 | P42: 0809-1998-00030 | AG42: BA464-01_Foros_y_plataformas_inclusivos_de_gestión_del_clima_y_el_medio_ambiente,_como_clubes_escolares,_clubes_juveniles,_comités_verdes,_consejos_asesores_juveniles,_COP_(por_ejemplo,_verde,_eco-embajador,_eco-scouts)_para_la_colaboración_en_proyectos_ecológicos. | AJ42: CA113-01_Capacitar_al_personal_de_salud_en_la_prestación_de_servicios_adaptados_a_los_niños_y_adolescentes,_incluidas_las_habilidades_de_comunicación,_la_confidencialidad_y_los_protocolos_de_protección_(H1.3.1)
O43: Edwing Armando Lopez Esteves - Lider Programa EV-3 | P43: 0801-1968-05630 | AG43: BA464-02_Becas_y_subvenciones_para_jóvenes_en_oportunidades_climáticas_y_ambientales. | AJ43: CA113-02_Mejorar_la_infraestructura_física_para_crear_entornos_de_instalaciones_de_salud_seguros,_inclusivos_y_acogedores_para_jóvenes_y_niños_(H1.3.2)
C44: PROG | O44: Jennifer Sabrina Romero Martínez - Lider en Protección e Incidencia | P44: 0809-1992-00487 | AG44: BA464-03_Capacitación,_talleres_y_tutoría_para_clubes_escolares,_clubes_juveniles,_comités_verdes,_consejos_asesores_juveniles,_consejos_juveniles,_plataformas_de_medios,_clubes_sobre_causas_de_desastres_relacionados_con_el_clima,_mitigantes,_preparación,_reducción_de_riesgos_y_respuesta,_incluidos_liderazgo,_defensa_y_educación_entre_pares. | AJ44: CA541-01_Realizar_una_evaluación_de_las_necesidades_de_capacidad_para_identificar_las_brechas_de_conocimientos_y_habilidades_entre_los_proveedores_de_servicios_de_salud_sobre_el_apoyo_a_los_sobrevivientes_de_la_violencia_de_género_(H2.1.1)
C45: MEAL | O45: Carmen Suyapa Pavón Almendarez - Oficial de Patrocinio | P45: 0816-1975-00222 | AG45: BA465-01_Actividades_ambientales_y_sostenibles_dirigidas_por_niños_y_jóvenes_en_la_escuela_(agua,_tierra,_gestión_de_residuos,_plantación_de_árboles,_caminatas_por_la_naturaleza,_excursiones_a_parques_locales,_viajes_de_campamento,_reservas_naturales,_centros_ambientales_y_observación_de_vida_silvestre_para_fomentar_la_conexión_con_la_naturaleza,_etc.) | AJ45: CA541-02_Desarrollar_o_adaptar_un_programa_de_capacitación_sobre_atención_centrada_en_el_sobreviviente,_manejo_clínico_de_la_violación_y_vías_de_derivación_(H2.1.2)
C46: PATR | O46: David Alonzo Ramos - Técnico Programa EV-1 | P46: 0809-1985-00088 | AG46: BA465-02_Evaluación_de_sostenibilidad_y_medio_ambiente_dirigida_por_niños_y_jóvenes_(a_través_de_encuestas_y_entrevistas)_para_recopilar_comentarios_sobre_los_riesgos_y_peligros_climáticos_en_la_comunidad_y_las_escuelas_para_crear_entornos_de_aprendizaje_sostenibles_dentro_de_la_escuela. | AJ46: CA541-03_Ofrecer_sesiones_de_capacitación_interactivas_basadas_en_competencias_para_los_trabajadores_de_salud_de_primera_línea_y_los_administradores_de_instalaciones_(H2.1.3)
C47: PROT | O47: Jeniffer Abigail Canales Flores - Técnico Programa EV-2 | P47: 0611-1995-00349 | AG47: BA466-01_Incentivos_para_esfuerzos_de_conservación_local,_como_subsidios_para_productos_ecológicos_como_abono_orgánico,_productos_energéticamente_eficientes_y_recompensas_para_esfuerzos_de_conservación_locales_innovadores,_etc. | AJ47: CA542-01_Ampliar_el_acceso_a_servicios_de_violencia_de_género_(VG)_centrados_en_las_sobrevivientes_mediante_clínicas_móviles_y_equipos_de_extensión_comunitaria,_garantizando_la_confidencialidad_y_la_seguridad._(H2.2.1)
C48: INCID | O48: Goel Garcia Alvarado - Técnico Programa EV-3 | P48: 0804-1992-00084 | AG48: BA466-02__Evaluaciones_de_riesgos_y_resiliencia_locales_basadas_en_las_escuelas_(incluida_la_infraestructura_escolar)_para_permitir_la_planificación_y_la_toma_de_decisiones_basadas_en_el_riesgo | AJ48: CA542-02_Adquirir,_almacenar_y_reponer_periódicamente_botiquines_para_el_tratamiento_post-violación_y_otros_suministros_esenciales_en_centros_de_salud_y_unidades_móviles_específicos._(H2.2.2)
C49: COMU | O49: Nubia Lisseth Medina Munguía - Técnico en Proteccion e Incidencia | P49: 0802-1985-00094 | AG49: BA467-01_Instalación_de_un_sistema_de_alerta_temprana_en_escuelas_seleccionadas_para_monitorear_la_evolución_de_desastres_(fenómenos_climáticos_y_meteorológicos_extremos)_y_proporcionar_actualizaciones_oportunas_en_todas_las_áreas_de_alto_riesgo,_alertas_meteorológicas_y_avisos_de_evacuación. | AJ49: CA542-03_Modernizar_o_adaptar_la_infraestructura_física_para_crear_espacios_privados,_seguros_y_accesibles_para_los_sobrevivientes_dentro_de_los_centros_de_salud_para_la_atención_de_la_VBG_(H2.2.3)
C50: ADM | O50: Yessenia Milixa Amador - Técnico en Patrocinio | P50: 0809-1977-00223 | AG50: BA467-02_Diseño_y_prestación_de_servicios_de_información_climática_oportuna_y_basada_en_la_demanda,_tales_como_pronósticos_meteorológicos,_sistemas_de_alerta_temprana,_información_de_evaluación_de_riesgos_climáticos_y_conocimientos_tradicionales_para_ayudar_en_el_proceso_de_toma_de_decisiones_basado_en_riesgos. | AJ50: CA542-04_Desarrollar,_institucionalizar_y_capacitar_al_personal_sobre_procedimientos_operativos_estándar_(POE)_para_la_gestión_de_casos,_derivaciones_y_documentación_de_violencia_de_género_(VG)_(H2.2.4)
C51: RRHH | AJ51: CA161-01_Diseñar_y_ofrecer_sesiones_de_educación_no_formal_móviles_o_comunitarias_(E1.1.1)
C52: MMRR | AJ52: CA161-02_Establecer_espacios_temporales_de_aprendizaje_dentro_de_albergues_de_tránsito_o_espacios_seguros,_garantizando_horarios_flexibles_para_adaptarse_a_las_necesidades_de_movimiento_y_protección._(E1.1.2)
C53: DIR | AJ53: CA162-01_Brindar_apoyo_de_divulgación_y_matriculación_a_niños_y_jóvenes_migrantes,_incluyendo_asistencia_con_la_documentación_y_los_procesos_de_matriculación_escolar._(E1.2.1)
C54: EMER | O54: Jose Adalid Funes - Técnico de Desarrollo Comunitario | P54: 0809-1985-00088 | AJ54: CA162-02_Implementar_clases_de_recuperación_y_de_apoyo_para_ayudar_a_los_estudiantes_a_superar_las_brechas_académicas_e_integrarse_en_grados_apropiados_para_su_edad._(E1.2.2)
O55: Roger Neptaly Silva Sánchez - Técnico de Desarrollo Comunitario | P55: 0809-1984-00317 | AJ55: CA162-03_Capacitar_a_docentes_y_personal_escolar_sobre_prácticas_inclusivas_y_las_necesidades_y_derechos_específicos_de_los_niños_migrantes_para_reducir_el_estigma_y_mejorar_el_apoyo_en_el_aula._(E1.2.3)
O56: Jhony Alfredo Amador - Técnico de Desarrollo Comunitario | P56: 0801-1992-16893 | AJ56: CA162-04_Facilitar_sesiones_de_participación_de_la_comunidad_y_los_cuidadores_para_crear_conciencia_sobre_la_importancia_de_la_educación_y_reducir_las_barreras_culturales_o_económicas_para_la_asistencia_(E1.2.4)
O57: Norma Waleska Hernandez - Técnico de Desarrollo Comunitario | P57: 0809-1995-00445 | AJ57: CA191-01_Impartir_sesiones_de_Aprendizaje_Socioemocional_(ASE)_culturalmente_apropiadas,_utilizando_currículos_que_tengan_en_cuenta_la_edad_y_la_migración,_en_espacios_seguros_y_entornos_de_aprendizaje_no_formal._(E2.1.1)
AJ58: CA191-02_Utilizar_enfoques_basados_en_las_artes,_el_juego_y_las_historias_para_apoyar_la_expresión_emocional,_la_empatía_y_la_conexión_entre_pares_(E2.1.2)
AJ59: CA192-01_Impartir_capacitación_específica_para_facilitadores_y_trabajadores_de_primera_línea_sobre_enfoques_de_Aprendizaje_Socioemocional_(ASE)_culturalmente_sensibles_y_adaptados_a_las_necesidades_de_los_niños_migrantes._(E2.2.1)
O60: Yimi Alexander Hernández - Técnico de Desarrollo Comunitario | P60: 0802-2004-00095 | AJ60: CA192-02_Establecer_vías_de_derivación_claras_y_fortalecer_la_capacidad_para_identificar_a_los_niños_que_necesitan_servicios_adicionales_de_salud_mental_o_protección_durante_la_programación_del_Aprendizaje_Socioemocional_(ASE)._(E2.2.2)
O61: Francisca Baiza García - Técnico de Desarrollo Comunitario | P61: 0804-1984-00828
O62: Alex Omar Alvarado A - Técnico de Desarrollo Comunitario | P62: 0804-2000-00305
O63: Alex Francisco Castillo - Técnico de Desarrollo Comunitario | P63: 0801-1992-16893
O64: Nancy Nicol Sevilla M - Técnico de Desarrollo Comunitario | P64: 0802-1999-00032
O65: Osterly Samir Vásquez - Técnico de Desarrollo Comunitario | P65: 0815-1999-00266

Sheet EV1-Nancy
A1: ACCION HONDURAS
A2: MATRIZ DE EVALUACION DE DESEMPEÑO DEL COLABORADOR
A4: Nombre y cargo del Colaborador: | G4: Jose Adalid Funes - Técnico de Desarrollo Comunitario | I4: Nancy Nicol Sevilla M - Técnico de Desarrollo Comunitario | P4: Evaluador: | R4: Edwing Armando Lopez Esteves - Lider de Programa EV-3
P5: VoBo RRHH | R5: Jennifer Sabrina Romero Martínez - Especialista en RRHH
A7: Area | D7: Periodo evaluado | E7: Marco de Resultados | I7: Responsabilidades del colaborador | J7: Cantidad a Lograr | Q7: Tiempo Definido (dias) | U7: Estandares de calidad (Escala de 10) | AB7: Nota Final | AC7: Observación
A8: Principal | B8: Transversal | C8: Responsable | E8: S | F8: SS | G8: ML | H8: Ext | J8: Programada | K8: Entregada | L8: Diferencia | M8: Justificacion | N8: Pendiente en tiempo | O8: Vencidas | P8: % | Q8: Programado | R8: Entregada | S8: Diferencia | T8: % | U8: Puntualidad | V8: Resolucion de Problemas | W8: Coordinaciión local | X8: Nivel de satisfacción de Grupos meta | Y8: Nivel de preparación | Z8: Total Estandares (Nota max. 20) | AA8: %
A10: PROG | B10: MEAL | C10: Tecn-Prog-Desarrollo PI | D10: JUL-SEP | E10: H_Salud | F10: HB_Nutrición | G10: HB041-01_Suplementos_nutricionales_para_niños_con_desnutrición_aguda_grave_o_desnutrición_aguda_moderada | H10: 1 | I10: Levantar Diagnostico situacional de primera infancia | J10: 157 | K10: 135 | L10: =+J10-K10 -> 22 | P10: =IFERROR(IF(7<>0, K10*100/J10, IF(J10=K10, K10*100/J10, 0)), 0) -> 85.987261 | Q10: 21 | R10: 22 | S10: =+Q10-R10 -> -1 | T10: =IFERROR(IF(S10<>0, Q10*100/R10, IF(Q10=R10, Q10*100/R10, 0)), 0) -> 95.454545 | U10: 9 | Y10: 10 | Z10: =+U10+Y10 -> 19 | AA10: =+Z10*100/20 -> 95 | AB10: =+(P10+AA10)/2 -> 90.493631
A11: PROG | B11: MEAL | C11: Lider-Prog-Educacion | I11: Levantar diagnóstico situacional de NN en el Centro Educativo. | L11: =+J11-K11 -> 0 | P11: =IFERROR(IF(7<>0, K11*100/J11, IF(J11=K11, K11*100/J11, 0)), 0) -> 0 | S11: =+Q11-R11 -> 0 | T11: =IFERROR(IF(S11<>0, Q11*100/R11, IF(Q11=R11, Q11*100/R11, 0)), 0) -> 0 | Z11: =SUM(U11:Y11) -> 0 | AA11: =+Z11*100/20 -> 0 | AB11: =+(T11+P11+AA11)/3 -> 0
A12: PROG | B12: PROG | C12: Tecn-Prog-Educacion | I12: Acuerdo de docentes | L12: =+J12-K12 -> 0 | P12: =IFERROR(IF(7<>0, K12*100/J12, IF(J12=K12, K12*100/J12, 0)), 0) -> 0 | Z12: =SUM(U12:Y12) -> 0 | AA12: =+Z12*100/20 -> 0 | AB12: =+(T12+P12+AA12)/3 -> 0
A13: PROG | B13: MEAL | C13: Tecn-Prog-Medios Vida | D13: JUL-SEP | I13: Levantar diagnóstico aptitudinal y de intereses de AJ en las comunidades | J13: =95+53 -> 148 | K13: 147 | L13: =+J13-K13 -> 1 | P13: =IFERROR(IF(7<>0, K13*100/J13, IF(J13=K13, K13*100/J13, 0)), 0) -> 99.324324 | S13: =+Q13-R13 -> 0 | T13: =IFERROR(IF(S13<>0, Q13*100/R13, IF(Q13=R13, Q13*100/R13, 0)), 0) -> 0 | U13: 10 | Y13: 10 | Z13: =+U13+Y13 -> 20 | AA13: =+Z13*100/20 -> 100 | AB13: =+(P13+AA13)/2 -> 99.662162
A14: PROG | B14: MEAL | C14: Tecn-Prog-Desarrollo PI | D14: JUL-SEP | I14: Organizar evento de socialización de resultados de Dx.situacional EV-1 | J14: 1 | K14: 0 | L14: =+J14-K14 -> 1 | P14: =IFERROR(IF(7<>0, K14*100/J14, IF(J14=K14, K14*100/J14, 0)), 0) -> 0 | S14: =+Q14-R14 -> 0 | T14: =IFERROR(IF(S14<>0, Q14*100/R14, IF(Q14=R14, Q14*100/R14, 0)), 0) -> 0 | U14: 0 | Y14: 0 | Z14: =+U14+Y14 -> 0 | AA14: =+Z14*100/20 -> 0 | AB14: =+(P14+AA14)/2 -> 0 | AC14: Lineamientos de socialización dependen de Lider de E.V.
A15: PROG | B15: MEAL | C15: Lider-Prog-Educacion | I15: Organizar evento de socialización de resultados de Dx.situacional EV-2 | L15: =+J15-K15 -> 0 | P15: =IFERROR(IF(7<>0, K15*100/J15, IF(J15=K15, K15*100/J15, 0)), 0) -> 0 | S15: =+Q15-R15 -> 0 | T15: =IFERROR(IF(S15<>0, Q15*100/R15, IF(Q15=R15, Q15*100/R15, 0)), 0) -> 0 | Z15: =SUM(U15:Y15) -> 0 | AA15: =+Z15*100/20 -> 0 | AB15: =+(T15+P15+AA15)/3 -> 0
A16: PROG | B16: MEAL | C16: Tecn-Prog-Medios Vida | I16: Organizar evento de socialización de resultados de Dx.situacional EV-3 | L16: =+J16-K16 -> 0 | P16: =IFERROR(IF(7<>0, K16*100/J16, IF(J16=K16, K16*100/J16, 0)), 0) -> 0 | S16: =+Q16-R16 -> 0 | T16: =IFERROR(IF(S16<>0, Q16*100/R16, IF(Q16=R16, Q16*100/R16, 0)), 0) -> 0 | Z16: =SUM(U16:Y16) -> 0 | AA16: =+Z16*100/20 -> 0 | AB16: =+(T16+P16+AA16)/3 -> 0
A17: PROG | C17: Tecn-Prog-Desarrollo PI | D17: JUL-SEP | I17: Organizar, coordinar y dar asistencia tecnica a Red de madres guía. | J17: 60 | K17: 60 | L17: =+J17-K17 -> 0 | P17: =IFERROR(IF(7<>0, K17*100/J17, IF(J17=K17, K17*100/J17, 0)), 0) -> 100 | S17: =+Q17-R17 -> 0 | T17: =IFERROR(IF(S17<>0, Q17*100/R17, IF(Q17=R17, Q17*100/R17, 0)), 0) -> 0 | U17: 10 | Y17: 10 | Z17: =+U17+Y17 -> 20 | AA17: =+Z17*100/20 -> 100 | AB17: =+(P17+AA17)/2 -> 100
A18: PROT | B18: PROG | C18: Tecn-Prog-Desarrollo PI | I18: Organizar, capacitar y monitorear plan de acción de los MPBC | L18: =+J18-K18 -> 0 | P18: =IFERROR(IF(7<>0, K18*100/J18, IF(J18=K18, K18*100/J18, 0)), 0) -> 0 | S18: =+Q18-R18 -> 0 | T18: =IFERROR(IF(S18<>0, Q18*100/R18, IF(Q18=R18, Q18*100/R18, 0)), 0) -> 0 | Z18: =SUM(U18:Y18) -> 0 | AA18: =+Z18*100/20 -> 0 | AB18: =+(T18+P18+AA18)/3 -> 0
A19: PROG | C19: Lider-Prog-Educacion | I19: Organizar, coordinar y dar asistencia tecnica a Red Educativa-APF y docente. | L19: =+J19-K19 -> 0 | P19: =IFERROR(IF(7<>0, K19*100/J19, IF(J19=K19, K19*100/J19, 0)), 0) -> 0 | S19: =+Q19-R19 -> 0 | T19: =IFERROR(IF(S19<>0, Q19*100/R19, IF(Q19=R19, Q19*100/R19, 0)), 0) -> 0 | Z19: =SUM(U19:Y19) -> 0 | AA19: =+Z19*100/20 -> 0 | AB19: =+(T19+P19+AA19)/3 -> 0
A20: PROG | C20: Tecn-Prog-Medios Vida | I20: Organizar, coordinar y dar asistencia tecnica a Red de Apoyo Juvenil | L20: =+J20-K20 -> 0 | P20: =IFERROR(IF(7<>0, K20*100/J20, IF(J20=K20, K20*100/J20, 0)), 0) -> 0 | S20: =+Q20-R20 -> 0 | T20: =IFERROR(IF(S20<>0, Q20*100/R20, IF(Q20=R20, Q20*100/R20, 0)), 0) -> 0 | Z20: =SUM(U20:Y20) -> 0 | AA20: =+Z20*100/20 -> 0 | AB20: =+(T20+P20+AA20)/3 -> 0
A21: RRHH | B21: PROG | C21: Tecn-Prog-Desarrollo PI | I21: Completar proceso de capacitación EV-1 virtual-presencial | L21: =+J21-K21 -> 0 | P21: =IFERROR(IF(7<>0, K21*100/J21, IF(J21=K21, K21*100/J21, 0)), 0) -> 0 | S21: =+Q21-R21 -> 0 | T21: =IFERROR(IF(S21<>0, Q21*100/R21, IF(Q21=R21, Q21*100/R21, 0)), 0) -> 0 | Z21: =SUM(U21:Y21) -> 0 | AA21: =+Z21*100/20 -> 0 | AB21: =+(T21+P21+AA21)/3 -> 0
A22: RRHH | B22: PROG | C22: Lider-Prog-Educacion | I22: Completar proceso de capacitación EV-2 institucional virtual-presencial | L22: =+J22-K22 -> 0 | P22: =IFERROR(IF(7<>0, K22*100/J22, IF(J22=K22, K22*100/J22, 0)), 0) -> 0 | S22: =+Q22-R22 -> 0 | T22: =IFERROR(IF(S22<>0, Q22*100/R22, IF(Q22=R22, Q22*100/R22, 0)), 0) -> 0 | Z22: =SUM(U22:Y22) -> 0 | AA22: =+Z22*100/20 -> 0 | AB22: =+(T22+P22+AA22)/3 -> 0
A23: RRHH | B23: PROG | C23: Tecn-Prog-Medios Vida | I23: Completar proceso de capacitación EV-3 institucional virtual-presencial | L23: =+J23-K23 -> 0 | P23: =IFERROR(IF(7<>0, K23*100/J23, IF(J23=K23, K23*100/J23, 0)), 0) -> 0 | S23: =+Q23-R23 -> 0 | T23: =IFERROR(IF(S23<>0, Q23*100/R23, IF(Q23=R23, Q23*100/R23, 0)), 0) -> 0 | Z23: =SUM(U23:Y23) -> 0 | AA23: =+Z23*100/20 -> 0 | AB23: =+(T23+P23+AA23)/3 -> 0
A24: PROT | C24: Equipo Tecnico | D24: JUL-SEP | I24: Completar capacitacion y firma de politica de proteccion y salvaguarda de NNAJ | J24: 1 | K24: 1 | L24: =+J24-K24 -> 0 | P24: =IFERROR(IF(7<>0, K24*100/J24, IF(J24=K24, K24*100/J24, 0)), 0) -> 100 | S24: =+Q24-R24 -> 0 | T24: =IFERROR(IF(S24<>0, Q24*100/R24, IF(Q24=R24, Q24*100/R24, 0)), 0) -> 0 | U24: 10 | Y24: 10 | Z24: =+U24+Y24 -> 20 | AA24: =+Z24*100/20 -> 100 | AB24: =+(P24+AA24)/2 -> 100
A25: PROG | C25: Tecn-Prog-Desarrollo PI | I25: Implementar metodologías y acciones con grupos meta en Centros ADN | L25: =+J25-K25 -> 0 | P25: =IFERROR(IF(7<>0, K25*100/J25, IF(J25=K25, K25*100/J25, 0)), 0) -> 0 | S25: =+Q25-R25 -> 0 | T25: =IFERROR(IF(S25<>0, Q25*100/R25, IF(Q25=R25, Q25*100/R25, 0)), 0) -> 0 | Z25: =SUM(U25:Y25) -> 0 | AA25: =+Z25*100/20 -> 0 | AB25: =+(T25+P25+AA25)/3 -> 0
A26: PROG | C26: Lider-Prog-Educacion | I26: Implementar metodologías y acciones con grupos meta en Centros Educativos | L26: =+J26-K26 -> 0 | P26: =IFERROR(IF(7<>0, K26*100/J26, IF(J26=K26, K26*100/J26, 0)), 0) -> 0 | S26: =+Q26-R26 -> 0 | T26: =IFERROR(IF(S26<>0, Q26*100/R26, IF(Q26=R26, Q26*100/R26, 0)), 0) -> 0 | Z26: =SUM(U26:Y26) -> 0 | AA26: =+Z26*100/20 -> 0 | AB26: =+(T26+P26+AA26)/3 -> 0
A27: PROG | C27: Tecn-Prog-Medios Vida | I27: Acompañar el desarrollo de plan de vida y formación en liderazgo a AJ | L27: =+J27-K27 -> 0 | P27: =IFERROR(IF(7<>0, K27*100/J27, IF(J27=K27, K27*100/J27, 0)), 0) -> 0 | S27: =+Q27-R27 -> 0 | T27: =IFERROR(IF(S27<>0, Q27*100/R27, IF(Q27=R27, Q27*100/R27, 0)), 0) -> 0 | Z27: =SUM(U27:Y27) -> 0 | AA27: =+Z27*100/20 -> 0 | AB27: =+(T27+P27+AA27)/3 -> 0
A28: PROG | B28: PROT | C28: Tecn-Prog-Desarrollo PI | D28: JUL-SEP | I28: Organizar e implementar en centros ADN, feria promocional de DDNN en EV-1 | J28: =120+62 -> 182 | K28: 140 | L28: =+J28-K28 -> 42 | P28: =IFERROR(IF(7<>0, K28*100/J28, IF(J28=K28, K28*100/J28, 0)), 0) -> 76.923077 | S28: =+Q28-R28 -> 0 | T28: =IFERROR(IF(S28<>0, Q28*100/R28, IF(Q28=R28, Q28*100/R28, 0)), 0) -> 0 | U28: 7 | Y28: 10 | Z28: =+U28+Y28 -> 17 | AA28: =+Z28*100/20 -> 85 | AB28: =+(P28+AA28)/2 -> 80.961538
A29: PROG | B29: PROT | C29: Lider-Prog-Educacion | I29: Organizar e implementar en Escuelas, feria promocional de DDNN en EV-2 | L29: =+J29-K29 -> 0 | P29: =IFERROR(IF(7<>0, K29*100/J29, IF(J29=K29, K29*100/J29, 0)), 0) -> 0 | S29: =+Q29-R29 -> 0 | T29: =IFERROR(IF(S29<>0, Q29*100/R29, IF(Q29=R29, Q29*100/R29, 0)), 0) -> 0 | Z29: =SUM(U29:Y29) -> 0 | AA29: =+Z29*100/20 -> 0 | AB29: =+(T29+P29+AA29)/3 -> 0
A30: PROG | B30: PROT | C30: Tecn-Prog-Medios Vida | I30: Organizar e implementar encuentros juveniles EV-3 en la comunidad | L30: =+J30-K30 -> 0 | P30: =IFERROR(IF(7<>0, K30*100/J30, IF(J30=K30, K30*100/J30, 0)), 0) -> 0 | S30: =+Q30-R30 -> 0 | T30: =IFERROR(IF(S30<>0, Q30*100/R30, IF(Q30=R30, Q30*100/R30, 0)), 0) -> 0 | Z30: =SUM(U30:Y30) -> 0 | AA30: =+Z30*100/20 -> 0 | AB30: =+(T30+P30+AA30)/3 -> 0
A31: PROG | B31: PROG | C31: Tecn-Prog-Desarrollo PI | I31: Convocar jardineras de Centros Pre-escolares para socializar acuerdos | L31: =+J31-K31 -> 0 | P31: =IFERROR(IF(7<>0, K31*100/J31, IF(J31=K31, K31*100/J31, 0)), 0) -> 0 | S31: =+Q31-R31 -> 0 | T31: =IFERROR(IF(S31<>0, Q31*100/R31, IF(Q31=R31, Q31*100/R31, 0)), 0) -> 0 | Z31: =SUM(U31:Y31) -> 0 | AA31: =+Z31*100/20 -> 0 | AB31: =+(T31+P31+AA31)/3 -> 0
A32: MEAL | B32: PROG | C32: Tecn-Prog-Desarrollo PI | D32: JUL-SEP | I32: Entregar herramientas de MEAL digitales y fisicas a Red de madres guia | J32: 6 | K32: 6 | L32: =+J32-K32 -> 0 | P32: =IFERROR(IF(7<>0, K32*100/J32, IF(J32=K32, K32*100/J32, 0)), 0) -> 100 | S32: =+Q32-R32 -> 0 | T32: =IFERROR(IF(S32<>0, Q32*100/R32, IF(Q32=R32, Q32*100/R32, 0)), 0) -> 0 | U32: 10 | Y32: 10 | Z32: =+U32+Y32 -> 20 | AA32: =+Z32*100/20 -> 100 | AB32: =+(P32+AA32)/2 -> 100
A33: MEAL | B33: PROG | C33: Lider-Prog-Educacion | I33: Entregar herramientas de MEAL digitales y fisicas a Docentes | L33: =+J33-K33 -> 0 | P33: =IFERROR(IF(7<>0, K33*100/J33, IF(J33=K33, K33*100/J33, 0)), 0) -> 0 | S33: =+Q33-R33 -> 0 | T33: =IFERROR(IF(S33<>0, Q33*100/R33, IF(Q33=R33, Q33*100/R33, 0)), 0) -> 0 | Z33: =SUM(U33:Y33) -> 0 | AA33: =+Z33*100/20 -> 0 | AB33: =+(T33+P33+AA33)/3 -> 0
A34: MEAL | B34: PROG | C34: Tecn-Prog-Medios Vida | D34: JUL-SEP | I34: Entregar herramientas de MEAL digitales y fisicas a Red de Apoyo Juvenil | J34: 1 | K34: 1 | L34: =+J34-K34 -> 0 | P34: =IFERROR(IF(7<>0, K34*100/J34, IF(J34=K34, K34*100/J34, 0)), 0) -> 100 | S34: =+Q34-R34 -> 0 | T34: =IFERROR(IF(S34<>0, Q34*100/R34, IF(Q34=R34, Q34*100/R34, 0)), 0) -> 0 | U34: 10 | Y34: 10 | Z34: =+U34+Y34 -> 20 | AA34: =+Z34*100/20 -> 100 | AB34: =+(P34+AA34)/2 -> 100
A35: MEAL | B35: PROG | C35: Tecn-Prog-Desarrollo PI | D35: JUL-SEP | I35: Recolectar, revisar y subir en linea los medios de verificacion de EV-1 completos | J35: 11 | K35: 10 | L35: =+J35-K35 -> 1 | P35: =IFERROR(IF(7<>0, K35*100/J35, IF(J35=K35, K35*100/J35, 0)), 0) -> 90.909091 | S35: =+Q35-R35 -> 0 | T35: =IFERROR(IF(S35<>0, Q35*100/R35, IF(Q35=R35, Q35*100/R35, 0)), 0) -> 0 | U35: 9 | Y35: 10 | Z35: =+U35+Y35 -> 19 | AA35: =+Z35*100/20 -> 95 | AB35: =+(P35+AA35)/2 -> 92.954545
A36: MEAL | B36: PROG | C36: Lider-Prog-Educacion | I36: Recolectar, revisar y subir en linea los medios de verificacion de EV-2 completos | L36: =+J36-K36 -> 0 | P36: =IFERROR(IF(7<>0, K36*100/J36, IF(J36=K36, K36*100/J36, 0)), 0) -> 0 | S36: =+Q36-R36 -> 0 | T36: =IFERROR(IF(S36<>0, Q36*100/R36, IF(Q36=R36, Q36*100/R36, 0)), 0) -> 0 | Z36: =SUM(U36:Y36) -> 0 | AA36: =+Z36*100/20 -> 0 | AB36: =+(T36+P36+AA36)/3 -> 0
A37: MEAL | B37: PROG | C37: Tecn-Prog-Medios Vida | D37: JUL-SEP | I37: Recolectar, revisar y subir en linea los medios de verificacion de EV-3 completos | J37: 2 | K37: 2 | L37: =+J37-K37 -> 0 | P37: =IFERROR(IF(7<>0, K37*100/J37, IF(J37=K37, K37*100/J37, 0)), 0) -> 100 | S37: =+Q37-R37 -> 0 | T37: =IFERROR(IF(S37<>0, Q37*100/R37, IF(Q37=R37, Q37*100/R37, 0)), 0) -> 0 | U37: 10 | Y37: 10 | Z37: =+U37+Y37 -> 20 | AA37: =+Z37*100/20 -> 100 | AB37: =+(P37+AA37)/2 -> 100
A38: MEAL | C38: Equipo Tecnico | I38: Completar capacitacion y levantamiento de encuesta global según plan de MEAL | L38: =+J38-K38 -> 0 | P38: =IFERROR(IF(7<>0, K38*100/J38, IF(J38=K38, K38*100/J38, 0)), 0) -> 0 | S38: =+Q38-R38 -> 0 | T38: =IFERROR(IF(S38<>0, Q38*100/R38, IF(Q38=R38, Q38*100/R38, 0)), 0) -> 0 | Z38: =SUM(U38:Y38) -> 0 | AA38: =+Z38*100/20 -> 0 | AB38: =+(T38+P38+AA38)/3 -> 0
A39: COMU | B39: PROG | C39: Tecn-Prog-Desarrollo PI | D39: JUL-SEP | I39: Recopilar datos promocionales (historias, videos) de actividades EV-1 | J39: 1 | K39: 1 | L39: =+J39-K39 -> 0 | P39: =IFERROR(IF(7<>0, K39*100/J39, IF(J39=K39, K39*100/J39, 0)), 0) -> 100 | S39: =+Q39-R39 -> 0 | T39: =IFERROR(IF(S39<>0, Q39*100/R39, IF(Q39=R39, Q39*100/R39, 0)), 0) -> 0 | U39: 10 | Y39: 10 | Z39: =+U39+Y39 -> 20 | AA39: =+Z39*100/20 -> 100 | AB39: =+(P39+AA39)/2 -> 100
A40: COMU | B40: PROG | C40: Lider-Prog-Educacion | I40: Recopilar y entregar promocionales (historias, videos) de actividades EV-2 | L40: =+J40-K40 -> 0 | P40: =IFERROR(IF(7<>0, K40*100/J40, IF(J40=K40, K40*100/J40, 0)), 0) -> 0 | S40: =+Q40-R40 -> 0 | T40: =IFERROR(IF(S40<>0, Q40*100/R40, IF(Q40=R40, Q40*100/R40, 0)), 0) -> 0 | Z40: =SUM(U40:Y40) -> 0 | AA40: =+Z40*100/20 -> 0 | AB40: =+(T40+P40+AA40)/3 -> 0
A41: COMU | B41: PROG | C41: Tecn-Prog-Medios Vida | I41: Recopilar y entregar promocionales (historias, videos) de actividades EV-3 | L41: =+J41-K41 -> 0 | P41: =IFERROR(IF(7<>0, K41*100/J41, IF(J41=K41, K41*100/J41, 0)), 0) -> 0 | S41: =+Q41-R41 -> 0 | T41: =IFERROR(IF(S41<>0, Q41*100/R41, IF(Q41=R41, Q41*100/R41, 0)), 0) -> 0 | Z41: =SUM(U41:Y41) -> 0 | AA41: =+Z41*100/20 -> 0 | AB41: =+(T41+P41+AA41)/3 -> 0
A42: PATR | C42: Tecnico Patrocinio | D42: JUL-SEP | I42: Completar formación personal para la gestion del Patrocinio: | J42: 1 | K42: 1 | L42: =+J42-K42 -> 0 | P42: =IFERROR(IF(7<>0, K42*100/J42, IF(J42=K42, K42*100/J42, 0)), 0) -> 100 | S42: =+Q42-R42 -> 0 | T42: =IFERROR(IF(S42<>0, Q42*100/R42, IF(Q42=R42, Q42*100/R42, 0)), 0) -> 0 | U42: 10 | Y42: 10 | Z42: =SUM(U42:Y42) -> 20 | AA42: =+Z42*100/20 -> 100 | AB42: =+(T42+P42+AA42)/3 -> 66.666667
A43: PATR | C43: Tecnico Patrocinio | I43: Digitalizar expedientes de NNAJ inscritos | L43: =+J43-K43 -> 0 | P43: =IFERROR(IF(7<>0, K43*100/J43, IF(J43=K43, K43*100/J43, 0)), 0) -> 0 | S43: =+Q43-R43 -> 0 | T43: =IFERROR(IF(S43<>0, Q43*100/R43, IF(Q43=R43, Q43*100/R43, 0)), 0) -> 0 | Z43: =SUM(U43:Y43) -> 0 | AA43: =+Z43*100/20 -> 0 | AB43: =+(T43+P43+AA43)/3 -> 0
A44: PATR | C44: Tecnico Patrocinio | D44: JUL-SEP | I44: Actualizar y completar expedientes de NNAJ, mantener actualizado el archivo | L44: =+J44-K44 -> 0 | P44: =IFERROR(IF(7<>0, K44*100/J44, IF(J44=K44, K44*100/J44, 0)), 0) -> 0 | S44: =+Q44-R44 -> 0 | T44: =IFERROR(IF(S44<>0, Q44*100/R44, IF(Q44=R44, Q44*100/R44, 0)), 0) -> 0 | Z44: =SUM(U44:Y44) -> 0 | AA44: =+Z44*100/20 -> 0 | AB44: =+(T44+P44+AA44)/3 -> 0 | AC44: Solicitar información de hojas de movimiento por tecnico a oficial de patrocinio.
A45: PATR | C45: Tecnico Patrocinio | D45: JUL-SEP | I45: Completar proceso de entrega de DFCs y carta de agradecimiento según estandares | J45: 44 | K45: 31 | L45: =+J45-K45 -> 13 | P45: =IFERROR(IF(7<>0, K45*100/J45, IF(J45=K45, K45*100/J45, 0)), 0) -> 70.454545 | S45: =+Q45-R45 -> 0 | T45: =IFERROR(IF(S45<>0, Q45*100/R45, IF(Q45=R45, Q45*100/R45, 0)), 0) -> 0 | Z45: =SUM(U45:Y45) -> 0 | AA45: =+Z45*100/20 -> 0 | AB45: =+(T45+P45+AA45)/3 -> 23.484848
A46: PATR | C46: Tecnico Patrocinio | D46: JUL-SEP | I46: Completar proceso de entrega de correspondencia según Estándares | J46: 286 | K46: 262 | L46: =+J46-K46 -> 24 | M46: 4 | N46: =+L46-M46 -> 20 | O46: 0 | P46: =IFERROR(IF(7<>0, K46*100/J46, IF(J46=K46, K46*100/J46, 0)), 0) -> 91.608392 | Q46: 36 | R46: 24 | S46: =+Q46-R46 -> 12 | T46: =IFERROR(IF(S46<>0, Q46*100/R46, IF(Q46=R46, Q46*100/R46, 0)), 0) -> 150 | Z46: =SUM(U46:Y46) -> 0 | AA46: =+Z46*100/20 -> 0 | AB46: =+(T46+P46+AA46)/3 -> 80.536131
A47: PATR | B47: COMU | C47: Tecnico Patrocinio | D47: JUL-SEP | I47: Recopilar y entregar Momentos Mágicos según asignacion | J47: 1 | K47: 1 | L47: =+J47-K47 -> 0 | P47: =IFERROR(IF(7<>0, K47*100/J47, IF(J47=K47, K47*100/J47, 0)), 0) -> 100 | S47: =+Q47-R47 -> 0 | T47: =IFERROR(IF(S47<>0, Q47*100/R47, IF(Q47=R47, Q47*100/R47, 0)), 0) -> 0 | Z47: =SUM(U47:Y47) -> 0 | AA47: =+Z47*100/20 -> 0 | AB47: =+(T47+P47+AA47)/3 -> 33.333333
A48: PATR | C48: Tecnico Patrocinio | D48: JUL-SEP | I48: Gestionar nuevas inscripciones según analisis de LM | J48: 5 | K48: 5 | L48: =+J48-K48 -> 0 | P48: =IFERROR(IF(7<>0, K48*100/J48, IF(J48=K48, K48*100/J48, 0)), 0) -> 100 | S48: =+Q48-R48 -> 0 | T48: =IFERROR(IF(S48<>0, Q48*100/R48, IF(Q48=R48, Q48*100/R48, 0)), 0) -> 0 | Z48: =SUM(U48:Y48) -> 0 | AA48: =+Z48*100/20 -> 0 | AB48: =+(T48+P48+AA48)/3 -> 33.333333
A49: PATR | C49: Tecnico Patrocinio | D49: JUL-SEP | I49: Gestionar nuevas salidas según analisis de LM | J49: 1 | K49: 1 | L49: =+J49-K49 -> 0 | P49: =IFERROR(IF(7<>0, K49*100/J49, IF(J49=K49, K49*100/J49, 0)), 0) -> 100 | Z49: =SUM(U49:Y49) -> 0 | AA49: =+Z49*100/20 -> 0
A50: PATR | C50: Tecnico Patrocinio | D50: JUL-SEP | I50: Gestionar actualizaciones (RAM) según analisis de LM | J50: 55 | K50: 9 | L50: =+J50-K50 -> 46 | P50: =IFERROR(IF(7<>0, K50*100/J50, IF(J50=K50, K50*100/J50, 0)), 0) -> 16.363636 | Z50: =SUM(U50:Y50) -> 0 | AA50: =+Z50*100/20 -> 0
A51: PATR | B51: MEAL | C51: Tecnico Patrocinio | I51: Levantar CPR según lineamientos de calidad, tiempo y forma | L51: =+J51-K51 -> 0 | P51: =IFERROR(IF(7<>0, K51*100/J51, IF(J51=K51, K51*100/J51, 0)), 0) -> 0 | S51: =+Q51-R51 -> 0 | T51: =IFERROR(IF(S51<>0, Q51*100/R51, IF(Q51=R51, Q51*100/R51, 0)), 0) -> 0 | Z51: =SUM(U51:Y51) -> 0 | AA51: =+Z51*100/20 -> 0 | AB51: =+(T51+P51+AA51)/3 -> 0
A52: PATR | B52: PROG | C52: Tecnico Patrocinio | I52: Organizar eventos de graduacion para AJ que salen del sistema | L52: =+J52-K52 -> 0 | P52: =IFERROR(IF(7<>0, K52*100/J52, IF(J52=K52, K52*100/J52, 0)), 0) -> 0 | S52: =+Q52-R52 -> 0 | T52: =IFERROR(IF(S52<>0, Q52*100/R52, IF(Q52=R52, Q52*100/R52, 0)), 0) -> 0 | Z52: =SUM(U52:Y52) -> 0 | AA52: =+Z52*100/20 -> 0 | AB52: =+(T52+P52+AA52)/3 -> 0
A53: ADM | B53: PROG | C53: Tecn-Prog-Desarrollo PI | D53: JUL-SEP | I53: Gestionar entregas a lideres y participantes en EV-1 según estandares administrativos. | L53: =+J53-K53 -> 0 | P53: =IFERROR(IF(7<>0, K53*100/J53, IF(J53=K53, K53*100/J53, 0)), 0) -> 0 | S53: =+Q53-R53 -> 0 | T53: =IFERROR(IF(S53<>0, Q53*100/R53, IF(Q53=R53, Q53*100/R53, 0)), 0) -> 0 | Z53: =+U53+Y53 -> 0 | AA53: =+Z53*100/20 -> 0 | AB53: =+(P53+AA53)/2 -> 0 | AC53: Solicitar datos de actas entregadas a administración
A54: ADM | B54: PROG | C54: Lider-Prog-Educacion | I54: Gestionar entregas a lideres y participantes en EV-2 según estandares administrativos. | L54: =+J54-K54 -> 0 | P54: =IFERROR(IF(7<>0, K54*100/J54, IF(J54=K54, K54*100/J54, 0)), 0) -> 0 | S54: =+Q54-R54 -> 0 | T54: =IFERROR(IF(S54<>0, Q54*100/R54, IF(Q54=R54, Q54*100/R54, 0)), 0) -> 0 | Z54: =SUM(U54:Y54) -> 0 | AA54: =+Z54*100/20 -> 0 | AB54: =+(T54+P54+AA54)/3 -> 0
A55: ADM | B55: PROG | C55: Tecn-Prog-Medios Vida | D55: JUL-SEP | I55: Gestionar entregas a lideres y participantes en EV-3 según estandares administrativos. | L55: =+J55-K55 -> 0 | P55: =IFERROR(IF(7<>0, K55*100/J55, IF(J55=K55, K55*100/J55, 0)), 0) -> 0 | S55: =+Q55-R55 -> 0 | T55: =IFERROR(IF(S55<>0, Q55*100/R55, IF(Q55=R55, Q55*100/R55, 0)), 0) -> 0 | Z55: =+U55+Y55 -> 0 | AA55: =+Z55*100/20 -> 0 | AB55: =+(P55+AA55)/2 -> 0 | AC55: Solicitar datos de actas entregadas a administración
A56: ADM | C56: Equipo Tecnico | I56: Completar proceso de Revision periodica de equipo asignado | L56: =+J56-K56 -> 0 | P56: =IFERROR(IF(7<>0, K56*100/J56, IF(J56=K56, K56*100/J56, 0)), 0) -> 0 | S56: =+Q56-R56 -> 0 | T56: =IFERROR(IF(S56<>0, Q56*100/R56, IF(Q56=R56, Q56*100/R56, 0)), 0) -> 0 | Z56: =+U56+Y56 -> 0 | AA56: =+Z56*100/20 -> 0 | AB56: =+(P56+AA56)/2 -> 0
A57: DIR | C57: Equipo Tecnico | I57: Participar en reuniones de evaluacion y analisis del desempeño mensual | L57: =+J57-K57 -> 0 | P57: =IFERROR(IF(7<>0, K57*100/J57, IF(J57=K57, K57*100/J57, 0)), 0) -> 0 | S57: =+Q57-R57 -> 0 | T57: =IFERROR(IF(S57<>0, Q57*100/R57, IF(Q57=R57, Q57*100/R57, 0)), 0) -> 0 | Z57: =SUM(U57:Y57) -> 0 | AA57: =+Z57*100/20 -> 0 | AB57: =+(T57+P57+AA57)/3 -> 0
A58: T | B58: T | C58: T | D58: T | J58: =SUM(J10:J55) -> 963 | K58: =SUM(K10:K55) -> 813 | L58: =+J58-K58 -> 150 | P58: =(K58*100)/J58 -> 84.423676 | T58: =AVERAGEIF(T10:T57,">0") -> 122.72727 | U58: =AVERAGEIF(U10:U55,">0") -> 9.5454545 | V58: =AVERAGEIF(V10:V55,">0") -> #DIV/0! | W58: =AVERAGEIF(W10:W55,">0") -> #DIV/0! | X58: =AVERAGEIF(X10:X55,">0") -> #DIV/0! | Y58: =AVERAGEIF(Y10:Y55,">0") -> 10 | Z58: =+U58+Y58 -> 19.545455 | AA58: =(Z58*100)/20 -> 97.727273 | AC58: =SUBTOTAL(109,AB10:AB55)/10 -> 96.407188

Sheet Nancy
A1: ACCION HONDURAS
A2: MATRIZ DE EVALUACION DE DESEMPEÑO DEL COLABORADOR
A4: Nombre y cargo del Colaborador: | G4: Jose Adalid Funes - Técnico de Desarrollo Comunitario | I4: Nancy Nicol Sevilla M - Técnico de Desarrollo Comunitario | P4: Evaluador: | R4: Edwing Armando Lopez Esteves - Lider de Programa EV-3
P5: VoBo RRHH | R5: Jennifer Sabrina Romero Martínez - Especialista en RRHH
A7: Area | D7: Periodo evaluado | E7: Marco de Resultados | I7: Responsabilidades del colaborador | J7: Cantidad a Lograr | Q7: Tiempo Definido (dias) | U7: Estandares de calidad (Escala de 10) | AB7: Nota Final
A8: Principal | B8: Transversal | C8: Responsable | E8: S | F8: SS | G8: ML | H8: Ext | J8: Programada | K8: Entregada | L8: Diferencia | M8: Justificacion | N8: Pendiente en tiempo | O8: Vencidas | P8: % | Q8: Programado | R8: Entregada | S8: Diferencia | T8: % | U8: Puntualidad | V8: Resolucion de Problemas | W8: Coordinaciión local | X8: Nivel de satisfacción de Grupos meta | Y8: Nivel de preparación | Z8: Total Estandares (Nota max. 50) | AA8: %
A10: PROG | B10: MEAL | C10: Lider-Prog-EV1 | E10: H_Salud | F10: HB_Nutrición | G10: HB041-01_Suplementos_nutricionales_para_niños_con_desnutrición_aguda_grave_o_desnutrición_aguda_moderada | H10: 1 | I10: Diseñar herramientas y protocolo para Dx.situacional de EV-1 | L10: =+J10-K10 -> 0 | P10: =IFERROR(IF(7<>0, K10*100/J10, IF(J10=K10, K10*100/J10, 0)), 0) -> 0 | S10: =+Q10-R10 -> 0 | T10: =IFERROR(IF(S10<>0, Q10*100/R10, IF(Q10=R10, Q10*100/R10, 0)), 0) -> 0 | Z10: =SUM(U10:Y10) -> 0 | AA10: =+Z10*100/50 -> 0 | AB10: =+(T10+P10+AA10)/3 -> 0
A11: PROG | B11: MEAL | C11: Lider-Prog-EV2 | E11: H_Salud | F11: HB_Nutrición | G11: HB041-01_Suplementos_nutricionales_para_niños_con_desnutrición_aguda_grave_o_desnutrición_aguda_moderada | H11: 1 | I11: Diseñar herramientas y protocolo para Dx.situacional de EV-2 | L11: =+J11-K11 -> 0 | P11: =IFERROR(IF(7<>0, K11*100/J11, IF(J11=K11, K11*100/J11, 0)), 0) -> 0 | S11: =+Q11-R11 -> 0 | T11: =IFERROR(IF(S11<>0, Q11*100/R11, IF(Q11=R11, Q11*100/R11, 0)), 0) -> 0 | Z11: =SUM(U11:Y11) -> 0 | AA11: =+Z11*100/50 -> 0 | AB11: =+(T11+P11+AA11)/3 -> 0
